Workbook

Sheet EQUIPO ENERO 2025
C1: SOLUCIONES EXACTAS, S.A. | AQ1: Codigo: FO-SE-053 | AU1: Codigo: FO-SE-053
C3: LISTADO INVENTARIO BODEGAS | AQ3: Versión: 02 | AU3: Versión: 02
A4: No. | B4: PRODUCTO | C4: No. BODEGA | D4: MARCA | E4: MODELO | F4: CAPACIDAD | G4: IMAGEN | H4: PRECIO | I4: CODIGO INTERNO | J4: PROVEEDOR | K4: FECHA INGRESO BODEGA | L4: FACTURA No. PROVEEDOR | M4: BOLETA INGRESO BODEGA | N4: OBSERVACION | O4: VIENE MES ANTERIOR | P4: EXISTENCIA INICIO SEMANA | U4: INGRESO POR IMPORTACION O COMPRA | Z4: DESCARGA Y/O SALIDA | AE4: DEVOLUCIONES | AJ4: EXISTENCIA POR SEMANA | AO4: DEMO | AP4: TOTAL EXISTENCIA MENSUAL | AQ4: FACTURA VENTA | AR4: BOLETA DE SALIDA | AS4: ENVIO | AT4: FIRMA ULTIMO INVENTARIO | AU4: FECHA ULTIMA REVISION
P5: 1 | Q5: 2 | R5: 3 | S5: 4 | T5: 5 | U5: 1 | V5: 2 | W5: 3 | X5: 4 | Y5: 5 | Z5: 1 | AA5: 2 | AB5: 3 | AC5: 4 | AD5: 5 | AE5: 1 | AF5: 2 | AG5: 3 | AH5: 4 | AI5: 5 | AJ5: 1 | AK5: 2 | AL5: 3 | AM5: 4 | AN5: 5
A6: 1 | B6: ADAPTADOR PARA INDICADOR 9V1.2A MODELO: KEERDA | C6: No. 2 | D6: KEERDA | E6: DZ012ELL090120U | F6: 9V | G6: #VALUE! | H6: 395 | I6: SE-ADAT9V | J6: SIZEIN | K6: 45666 | L6: LK24112701 | M6: 118 | N6: 1 IVAN LEIVA/ 2 JESUS LORENZANA//1-PANTALEON//COPASA 4 | O6: 5 | P6: =O6 -> 5 | Q6: =AJ6 -> 54 | R6: =AK6 -> 51 | S6: =AL6 -> 51 | T6: =AM6 -> 47 | U6: 50 | Z6: 1 | AA6: 3 | AC6: 4 | AJ6: =P6-Z6+AE6+U6 -> 54 | AK6: =Q6-AA6+AF6+V6 -> 51 | AL6: =R6-AB6+AG6+W6 -> 51 | AM6: =S6-AC6+AH6+X6 -> 47 | AN6: =T6-AD6+AI6+Y6 -> 47 | AP6: =AN6 -> 47 | AQ6: 2364686916 | AR6: 244/253//268//292 | AS6: E:4587-IVAN//E: -JESUS//E:-PANTALEON
A7: =+A6+1 -> 2 | AP7: =AN7 -> 0
A8: =+A7+1 -> 3 | B8: ADAPTADORES GENERICOS 5 V 1 AMP AC/DC | C8: No. 2 | D8: BRECKNELL | E8: S/M | G8: #VALUE! | I8: SE-ADAP-1 AMP | J8: BRECKNELL | K8: 44592 | O8: 2 | P8: =O8 -> 2 | Q8: =AJ8 -> 2 | R8: =AK8 -> 2 | S8: =AL8 -> 2 | T8: =AM8 -> 2 | AJ8: =P8-Z8+AE8+U8 -> 2 | AK8: =Q8-AA8+AF8+V8 -> 2 | AL8: =R8-AB8+AG8+W8 -> 2 | AM8: =S8-AC8+AH8+X8 -> 2 | AN8: =T8-AD8+AI8+Y8 -> 2 | AP8: =AN8 -> 2
A9: =+A8+1 -> 4 | B9: ADAPTADORES SBI 505 ORIGINAL AWT05-505896 | C9: No. 2 | D9: AVERY WEIGH TRONIX | E9: AWT05-505896 | G9: #VALUE! | H9: 550 | I9: SE-ADAP-SBI505 | J9: AVERY WEIGH TRONIX | K9: 44592 | O9: 8 | P9: =O9 -> 8 | Q9: =AJ9 -> 8 | R9: =AK9 -> 8 | S9: =AL9 -> 8 | T9: =AM9 -> 8 | AJ9: =P9-Z9+AE9+U9 -> 8 | AK9: =Q9-AA9+AF9+V9 -> 8 | AL9: =R9-AB9+AG9+W9 -> 8 | AM9: =S9-AC9+AH9+X9 -> 8 | AN9: =T9-AD9+AI9+Y9 -> 8 | AP9: =AN9 -> 8
A10: =+A9+1 -> 5 | B10: ADAPTADOR BI 12T | C10: No. 2 | D10: BRECKNELL | E10: BI 12T | F10: 12t | G10: #VALUE! | I10: SE-ADAP-BI-12T | J10: BRECKNELL | K10: 44592 | O10: 1 | P10: =O10 -> 1 | Q10: =AJ10 -> 1 | R10: =AK10 -> 1 | S10: =AL10 -> 1 | T10: =AM10 -> 1 | AJ10: =P10-Z10+AE10+U10 -> 1 | AK10: =Q10-AA10+AF10+V10 -> 1 | AL10: =R10-AB10+AG10+W10 -> 1 | AM10: =S10-AC10+AH10+X10 -> 1 | AN10: =T10-AD10+AI10+Y10 -> 1 | AP10: =AN10 -> 1
A11: =+A10+1 -> 6 | B11: ADAPTADOR DE MODULOS INALAMBRICOS SE-7660 | C11: No.2 | E11: SE-ADAPT-7660 | G11: #VALUE! | J11: LOCOSC | K11: 45464 | M11: 87 | O11: 2 | P11: =O11 -> 2 | Q11: =AJ11 -> 2 | R11: =AK11 -> 2 | S11: =AL11 -> 2 | T11: =AM11 -> 2 | AJ11: =P11-Z11+AE11+U11 -> 2 | AK11: =Q11-AA11+AF11+V11 -> 2 | AL11: =R11-AB11+AG11+W11 -> 2 | AM11: =S11-AC11+AH11+X11 -> 2 | AN11: =T11-AD11+AI11+Y11 -> 2 | AP11: =AN11 -> 2
A12: =+A11+1 -> 7 | B12: ADAPTADOR DE CORRIENTE DE INDICADOR SE7517/ REPARADO DE CABLE | C12: NO.2 | D12: KEERDA | E12: DZ007AHL050100U | F12: 5.0V/1.0Ah | I12: SE-DZ007 | J12: LOCOSC | M12: 113 | O12: 1 | P12: =O12 -> 1 | Q12: =AJ12 -> 1 | R12: =AK12 -> 1 | S12: =AL12 -> 1 | T12: =AM12 -> 1 | AJ12: =P12-Z12+AE12+U12 -> 1 | AK12: =Q12-AA12+AF12+V12 -> 1 | AL12: =R12-AB12+AG12+W12 -> 1 | AM12: =S12-AC12+AH12+X12 -> 1 | AN12: =T12-AD12+AI12+Y12 -> 1 | AP12: =AN12 -> 1
A13: =+A12+1 -> 8 | B13: ADAPTADORES DE CORRIENTE PARA MODULOS INALAMBRICOS SE-7519A | C13: NO.2 | D13: S/M | E13: ZF120A-0421000 | F13: 4.2V/10A | G13: #VALUE! | I13: SE-ADAP-A | J13: LOCOSC | K13: 45582 | M13: 81 | O13: 2 | P13: =O13 -> 2 | Q13: =AJ13 -> 2 | R13: =AK13 -> 2 | S13: =AL13 -> 2 | T13: =AM13 -> 2 | AJ13: =P13-Z13+AE13+U13 -> 2 | AK13: =Q13-AA13+AF13+V13 -> 2 | AL13: =R13-AB13+AG13+W13 -> 2 | AM13: =S13-AC13+AH13+X13 -> 2 | AN13: =T13-AD13+AI13+Y13 -> 2 | AP13: =AN13 -> 2
A14: =+A13+1 -> 9 | B14: ARMARIOS ELECTRICOS ST4-420 | C14: No. 2 | D14: BRECKNELL | E14: ST4-420 | G14: #VALUE! | I14: SE-ARMAELEC | J14: BRECKNELL | K14: 44592 | O14: 3 | P14: =O14 -> 3 | Q14: =AJ14 -> 3 | R14: =AK14 -> 3 | S14: =AL14 -> 3 | T14: =AM14 -> 3 | AJ14: =P14-Z14+AE14+U14 -> 3 | AK14: =Q14-AA14+AF14+V14 -> 3 | AL14: =R14-AB14+AG14+W14 -> 3 | AM14: =S14-AC14+AH14+X14 -> 3 | AN14: =T14-AD14+AI14+Y14 -> 3 | AP14: =AN14 -> 3
A15: =+A14+1 -> 10 | B15: ARGOLLAS PARA BÁSCULAS PESA EJES | C15: NO.2 | D15: S/M | E15: M-20 | F15: S/C | G15: #VALUE! | I15: SE-ARG-PPEJES | J15: LOCOSC | K15: 45673 | L15: 240907-1 | M15: 131 | N15: 4-YEGUADA | O15: 0 | P15: =O15 -> 0 | Q15: =AJ15 -> 0 | R15: =AK15 -> 0 | S15: =AL15 -> 0 | T15: =AM15 -> 0 | W15: 4 | AB15: 4 | AJ15: =P15-Z15+AE15+U15 -> 0 | AK15: =Q15-AA15+AF15+V15 -> 0 | AL15: =R15-AB15+AG15+W15 -> 0 | AM15: =S15-AC15+AH15+X15 -> 0 | AN15: =T15-AD15+AI15+Y15 -> 0 | AP15: =AN15 -> 0 | AR15: 285
A16: =+A15+1 -> 11 | B16: BALANZA DE BOLSILLO CAPACIDAD DE 200x0.01g | C16: No. 1 | E16: HY-YH-J100120 | F16: 2 000 x 0.01 g | G16: #VALUE! | H16: 150 | I16: SE-FAB-GUA | K16: 44592 | O16: 5 | P16: =O16 -> 5 | Q16: =AJ16 -> 5 | R16: =AK16 -> 5 | S16: =AL16 -> 5 | T16: =AM16 -> 5 | AJ16: =P16-Z16+AE16+U16 -> 5 | AK16: =Q16-AA16+AF16+V16 -> 5 | AL16: =R16-AB16+AG16+W16 -> 5 | AM16: =S16-AC16+AH16+X16 -> 5 | AN16: =T16-AD16+AI16+Y16 -> 5 | AP16: =AN16 -> 5
A17: =+A16+1 -> 12 | B17: BALANZA DE LABORATORIO 1 000 x0.01g | C17: N/A | D17: ELECTRONIC BALANCE | E17: SE10002K | F17: 1 000 x 0.01 g | G17: #VALUE! | H17: 9180 | I17: SE-WTB1002K | J17: LOCOSC | K17: 45316 | M17: 15 | O17: 0 | P17: =O17 -> 0 | Q17: =AJ17 -> 0 | R17: =AK17 -> 0 | S17: =AL17 -> 0 | T17: =AM17 -> 0 | AJ17: =P17-Z17+AE17+U17 -> 0 | AK17: =Q17-AA17+AF17+V17 -> 0 | AL17: =R17-AB17+AG17+W17 -> 0 | AM17: =S17-AC17+AH17+X17 -> 0 | AN17: =T17-AD17+AI17+Y17 -> 0 | AP17: =AN17 -> 0
A18: =+A17+1 -> 13 | B18: BALANZA DE LABORATORIO 10000x0.1g | C18: No. 1 | D18: ELECTRONIC BALANCE | E18: SE-WT100001X | F18: 1 000 x 0.1 g | G18: #VALUE! | H18: 4600 | I18: SE-WT100001X | J18: LOCOSC | K18: 45216 | L18: 2015 | M18: 451 | O18: 0 | P18: =O18 -> 0 | Q18: =AJ18 -> 0 | R18: =AK18 -> 0 | S18: =AL18 -> 0 | T18: =AM18 -> 0 | AJ18: =P18-Z18+AE18+U18 -> 0 | AK18: =Q18-AA18+AF18+V18 -> 0 | AL18: =R18-AB18+AG18+W18 -> 0 | AM18: =S18-AC18+AH18+X18 -> 0 | AN18: =T18-AD18+AI18+Y18 -> 0 | AP18: =AN18 -> 0
A19: =+A18+1 -> 14 | B19: BALANZA DE LABORATORIO 1500g x 0.5g | C19: N/A | D19: ELECTRONIC BALANCE | E19: SE-WT15002KF | F19: 1 500 x 0.05 kg | G19: #VALUE! | H19: 2800 | I19: SE-WT15002KF-5 | J19: LOCOSC | K19: 45107 | L19: LP230224-1 | M19: 393 | O19: 5 | P19: =O19 -> 5 | Q19: =AJ19 -> 5 | R19: =AK19 -> 5 | S19: =AL19 -> 5 | T19: =AM19 -> 5 | AJ19: =P19-Z19+AE19+U19 -> 5 | AK19: =Q19-AA19+AF19+V19 -> 5 | AL19: =R19-AB19+AG19+W19 -> 5 | AM19: =S19-AC19+AH19+X19 -> 5 | AN19: =T19-AD19+AI19+Y19 -> 5 | AP19: =AN19 -> 5
A20: =+A19+1 -> 15 | B20: BALANZA DE LABORATORIO CAPACIDAD 15 kg x 0.1g | C20: No. 1 | D20: ELECTRONIC BALANCE | E20: SE150001XD | F20: 15 kg x 0.1 g | G20: #VALUE! | H20: 9180 | I20: SE-WT150001XD | J20: LOCOSC | K20: 45316 | M20: 15 | O20: 0 | P20: =O20 -> 0 | Q20: =AJ20 -> 0 | R20: =AK20 -> 0 | S20: =AL20 -> 0 | T20: =AM20 -> 0 | AJ20: =P20-Z20+AE20+U20 -> 0 | AK20: =Q20-AA20+AF20+V20 -> 0 | AL20: =R20-AB20+AG20+W20 -> 0 | AM20: =S20-AC20+AH20+X20 -> 0 | AN20: =T20-AD20+AI20+Y20 -> 0 | AP20: =AN20 -> 0
A21: =+A20+1 -> 16 | B21: BALANZA DE LABORATORIO CAPACIDAD 300 g x 1 mg | C21: N/A | D21: ELECTRONIC BALANCE | E21: SE-3003GH | F21: 300 g x 1 mg | G21: #VALUE! | H21: 36300 | I21: SE3003GH | J21: LOCOSC | K21: 45299 | M21: 6 | O21: 0 | P21: =O21 -> 0 | Q21: =AJ21 -> 0 | R21: =AK21 -> 0 | S21: =AL21 -> 0 | T21: =AM21 -> 0 | AJ21: =P21-Z21+AE21+U21 -> 0 | AK21: =Q21-AA21+AF21+V21 -> 0 | AL21: =R21-AB21+AG21+W21 -> 0 | AM21: =S21-AC21+AH21+X21 -> 0 | AN21: =T21-AD21+AI21+Y21 -> 0 | AP21: =AN21 -> 0
A22: =+A21+1 -> 17 | B22: BALANZA ANALITICA CAPACIDAD DE 5 000g x 0.01 g | C22: N/A | D22: ELECTRONIC BALANCE | E22: SE-5 0002CF | F22: 5 000 x 0.01 g | G22: #VALUE! | I22: SE50002CF | J22: LOCOSC | K22: 45336 | L22: 669885E9 | M22: 37 | O22: 0 | P22: =O22 -> 0 | Q22: =AJ22 -> 0 | R22: =AK22 -> 0 | S22: =AL22 -> 0 | T22: =AM22 -> 0 | AJ22: =P22-Z22+AE22+U22 -> 0 | AK22: =Q22-AA22+AF22+V22 -> 0 | AL22: =R22-AB22+AG22+W22 -> 0 | AM22: =S22-AC22+AH22+X22 -> 0 | AN22: =T22-AD22+AI22+Y22 -> 0 | AP22: =AN22 -> 0
A23: =+A22+1 -> 18 | B23: BALANZA ANALITICA CAPACIDAD DE 1 000 g x 20 mg | C23: N/A | D23: ELECTRONIC BALANCE | E23: SE-10003N | F23: 1 000 g x 20 mg | G23: #VALUE! | I23: SE10003N | J23: LOCOSC | K23: 45336 | L23: 669885E9 | M23: 37 | O23: 0 | P23: =O23 -> 0 | Q23: =AJ23 -> 0 | R23: =AK23 -> 0 | S23: =AL23 -> 0 | T23: =AM23 -> 0 | AJ23: =P23-Z23+AE23+U23 -> 0 | AK23: =Q23-AA23+AF23+V23 -> 0 | AL23: =R23-AB23+AG23+W23 -> 0 | AM23: =S23-AC23+AH23+X23 -> 0 | AN23: =T23-AD23+AI23+Y23 -> 0 | AP23: =AN23 -> 0
A24: =+A23+1 -> 19 | B24: BALANZA ANALITICA CAPACIDAD DE 210 g x 10 mg | C24: N/A | D24: ELECTRONIC BALANCE | E24: SE-2085A | F24: 210 g x 10 mg | G24: #VALUE! | I24: SE2085A | J24: LOCOSC | K24: 45336 | L24: 669885E9 | M24: 38 | O24: 0 | P24: =O24 -> 0 | Q24: =AJ24 -> 0 | R24: =AK24 -> 0 | S24: =AL24 -> 0 | T24: =AM24 -> 0 | AJ24: =P24-Z24+AE24+U24 -> 0 | AK24: =Q24-AA24+AF24+V24 -> 0 | AL24: =R24-AB24+AG24+W24 -> 0 | AM24: =S24-AC24+AH24+X24 -> 0 | AN24: =T24-AD24+AI24+Y24 -> 0 | AP24: =AN24 -> 0
A25: =+A24+1 -> 20 | B25: BALANZA DE LABORATORIO CAPACIDAD 420 x 0.001g LUNA | C25: No.1 | E25: SE-LPB423E | F25: 420 x 0.001 g | G25: #VALUE! | I25: LPB423E | J25: ADAM | K25: 45454 | L25: 34687-035292 | M25: 76 | O25: 0 | P25: =O25 -> 0 | Q25: =AJ25 -> 0 | R25: =AK25 -> 0 | S25: =AL25 -> 0 | T25: =AM25 -> 0 | AJ25: =P25-Z25+AE25+U25 -> 0 | AK25: =Q25-AA25+AF25+V25 -> 0 | AL25: =R25-AB25+AG25+W25 -> 0 | AM25: =S25-AC25+AH25+X25 -> 0 | AN25: =T25-AD25+AI25+Y25 -> 0 | AP25: =AN25 -> 0
A26: =+A25+1 -> 21 | B26: BÁSCULA DE MESA | C26: No. 1 | D26: BRECKNELL | E26: SE-7680W | F26: 3 x 0.005 kg | G26: #VALUE! | H26: 2800 | I26: SE-LP7680-3Kg | J26: LOCOSC | K26: 45574 | L26: LP3211240 | M26: 71 | O26: 8 | P26: =O26 -> 8 | Q26: =AJ26 -> 8 | R26: =AK26 -> 8 | S26: =AL26 -> 8 | T26: =AM26 -> 8 | AJ26: =P26-Z26+AE26+U26 -> 8 | AK26: =Q26-AA26+AF26+V26 -> 8 | AL26: =R26-AB26+AG26+W26 -> 8 | AM26: =S26-AC26+AH26+X26 -> 8 | AN26: =T26-AD26+AI26+Y26 -> 8 | AP26: =AN26 -> 8
A27: =+A26+1 -> 22 | B27: BÁSCULA DE MESA | C27: No. 1 | D27: BRECKNELL | E27: SE-7680W | F27: 6 x 0.001 kg | G27: #VALUE! | H27: 2800 | I27: SE-LP7680-6Kg | J27: LOCOSC | K27: 45574 | L27: LP3211240 | M27: 71 | O27: 10 | P27: =O27 -> 10 | Q27: =AJ27 -> 10 | R27: =AK27 -> 10 | S27: =AL27 -> 10 | T27: =AM27 -> 10 | AJ27: =P27-Z27+AE27+U27 -> 10 | AK27: =Q27-AA27+AF27+V27 -> 10 | AL27: =R27-AB27+AG27+W27 -> 10 | AM27: =S27-AC27+AH27+X27 -> 10 | AN27: =T27-AD27+AI27+Y27 -> 10 | AP27: =AN27 -> 10
A28: =+A27+1 -> 23 | B28: BÁSCULA DE MESA | C28: No. 1 | D28: BRECKNELL | E28: SE-7680W | F28: 15 x 0.002 kg | G28: #VALUE! | H28: 2800 | I28: SE-LP7680-15Kg | J28: LOCOSC | K28: 45574 | L28: LP3211240 | M28: 71 | N28: 1-RESTAURANTE NEREA// 1 BASCULA PPAPIS BBQ S: 23032003005 | O28: 8 | P28: =O28 -> 8 | Q28: =AJ28 -> 8 | R28: =AK28 -> 7 | S28: =AL28 -> 7 | T28: =AM28 -> 7 | AA28: 1 | AD28: 1 | AJ28: =P28-Z28+AE28+U28 -> 8 | AK28: =Q28-AA28+AF28+V28 -> 7 | AL28: =R28-AB28+AG28+W28 -> 7 | AM28: =S28-AC28+AH28+X28 -> 7 | AN28: =T28-AD28+AI28+Y28 -> 6 | AP28: =AN28 -> 6 | AQ28: 4147989008 | AR28: 257// 313-PPAPIS | AS28: W:4596-NEREA
A29: =+A28+1 -> 24 | B29: BASCULA DE MESA MODELO SE-7680W | C29: No. 1 | D29: BRECKNELL | E29: SE-7680W | F29: 30 x 0.005 kg | G29: #VALUE! | H29: 3000 | I29: SE-LP7680-30kg | J29: LOCOSC | K29: 45107 | L29: LP230224-1 | M29: 390 | O29: 5 | P29: =O29 -> 5 | Q29: =AJ29 -> 5 | R29: =AK29 -> 5 | S29: =AL29 -> 5 | T29: =AM29 -> 5 | AJ29: =P29-Z29+AE29+U29 -> 5 | AK29: =Q29-AA29+AF29+V29 -> 5 | AL29: =R29-AB29+AG29+W29 -> 5 | AM29: =S29-AC29+AH29+X29 -> 5 | AN29: =T29-AD29+AI29+Y29 -> 5 | AP29: =AN29 -> 5
A30: =+A29+1 -> 25 | B30: BALANZA ELECTRONIC BALANCE MODELO SE-2003CH DE 2000gx1mg | C30: N/A | D30: ELECTRONIC BALANCE | E30: SE-2003CH | F30: 200 x 1 mg | G30: #VALUE! | H30: 6300 | I30: SE-2003CH | J30: LOCOSC | K30: 45139 | L30: 781781092133 | M30: 419 | O30: 0 | P30: =O30 -> 0 | Q30: =AJ30 -> 0 | R30: =AK30 -> 0 | S30: =AL30 -> 0 | T30: =AM30 -> 0 | AJ30: =P30-Z30+AE30+U30 -> 0 | AK30: =Q30-AA30+AF30+V30 -> 0 | AL30: =R30-AB30+AG30+W30 -> 0 | AM30: =S30-AC30+AH30+X30 -> 0 | AN30: =T30-AD30+AI30+Y30 -> 0 | AP30: =AN30 -> 0
A31: =+A30+1 -> 26 | B31: BASES DE CELDA DE CARGA PARA CELDAS DE ACEROS DE GUATEMALA | C31: NO. 2 | D31: S/M | E31: S/M | G31: #VALUE! | K31: 45568 | M31: 62 | O31: 2 | P31: =O31 -> 2 | Q31: =AJ31 -> 2 | R31: =AK31 -> 2 | S31: =AL31 -> 2 | T31: =AM31 -> 2 | AJ31: =P31-Z31+AE31+U31 -> 2 | AK31: =Q31-AA31+AF31+V31 -> 2 | AL31: =R31-AB31+AG31+W31 -> 2 | AM31: =S31-AC31+AH31+X31 -> 2 | AN31: =T31-AD31+AI31+Y31 -> 2 | AP31: =AN31 -> 2
A32: =+A31+1 -> 27 | B32: BASCULA COLGANTE CAPACIDAD 5 t LP7650G | C32: NO.2 | D32: BRECKNELL | E32: SE-7650 | F32: 5 T | G32: #VALUE! | H32: 9500 | I32: SE-LP7650G-5T | J32: SIZEN | K32: 45666 | L32: LK24112701 | M32: 117 | N32: 1-ACEROS DE GUATEMALA | O32: 0 | P32: =O32 -> 0 | Q32: =AJ32 -> 2 | R32: =AK32 -> 1 | S32: =AL32 -> 1 | T32: =AM32 -> 1 | U32: 2 | AA32: 1 | AJ32: =P32-Z32+AE32+U32 -> 2 | AK32: =Q32-AA32+AF32+V32 -> 1 | AL32: =R32-AB32+AG32+W32 -> 1 | AM32: =S32-AC32+AH32+X32 -> 1 | AN32: =T32-AD32+AI32+Y32 -> 1 | AP32: =AN32 -> 1 | AQ32: 837175793 | AR32: 262 | AS32: E:4608-AG
A33: =+A32+1 -> 28 | B33: BASCULA COLGANTE CAPACIDAD 10 t LP7650G | C33: No. 2 | D33: BRECKNELL | E33: SE-7650 | F33: 10 t | G33: #VALUE! | H33: Q16,800.00 Consultar primero | I33: SE-LP7650G-10T | J33: LOCOSC | K33: 45107 | L33: LP230224-1 | M33: 393 | O33: 1 | P33: =O33 -> 1 | Q33: =AJ33 -> 1 | R33: =AK33 -> 1 | S33: =AL33 -> 1 | T33: =AM33 -> 1 | AJ33: =P33-Z33+AE33+U33 -> 1 | AK33: =Q33-AA33+AF33+V33 -> 1 | AL33: =R33-AB33+AG33+W33 -> 1 | AM33: =S33-AC33+AH33+X33 -> 1 | AN33: =T33-AD33+AI33+Y33 -> 1 | AP33: =AN33 -> 1
A34: =+A33+1 -> 29 | B34: BASCULA COLGANTE CAPACIDAD 300kg LP7652G | C34: No. 1 | D34: BRECKNELL | E34: SE-7652 | F34: 300 x 0.1 kg | G34: #VALUE! | H34: 650 | I34: SE-COLG-LP7652G | J34: LOCOSC | K34: 45107 | L34: LP230224-1 | M34: 389 | N34: 1-JACOBO VILLEDA//1-JACOBO | O34: 13 | P34: =O34 -> 13 | Q34: =AJ34 -> 13 | R34: =AK34 -> 12 | S34: =AL34 -> 11 | T34: =AM34 -> 11 | AA34: 1 | AB34: 1 | AJ34: =P34-Z34+AE34+U34 -> 13 | AK34: =Q34-AA34+AF34+V34 -> 12 | AL34: =R34-AB34+AG34+W34 -> 11 | AM34: =S34-AC34+AH34+X34 -> 11 | AN34: =T34-AD34+AI34+Y34 -> 11 | AP34: =AN34 -> 11 | AR34: 271//274 | AS34: E:4603-JACOBO//E:470-JACOBO
A35: =+A34+1 -> 30 | B35: BASCULA COLGANTE PANTALLA LED DE 5 DIGITOS | C35: No. 1 | D35: BRECKNELL | E35: SE-7561 | F35: 300 x 0.1 kg | G35: #VALUE! | H35: 1800 | I35: SE-LP7561E | J35: LOCOSC | K35: 44592 | N35: 1-CARLOS PEREZ | O35: 7 | P35: =O35 -> 7 | Q35: =AJ35 -> 7 | R35: =AK35 -> 7 | S35: =AL35 -> 6 | T35: =AM35 -> 6 | AB35: 1 | AJ35: =P35-Z35+AE35+U35 -> 7 | AK35: =Q35-AA35+AF35+V35 -> 7 | AL35: =R35-AB35+AG35+W35 -> 6 | AM35: =S35-AC35+AH35+X35 -> 6 | AN35: =T35-AD35+AI35+Y35 -> 6 | AP35: =AN35 -> 6 | AR35: 282 | AS35: E:4611-CARLOS
A36: =+A35+1 -> 31 | B36: BASCULA DE MESA CAPACIDAD 30kgx1g | C36: No. 1 | D36: ELECTRONIC BALANCE | E36: SE-WT300001X | F36: 30 kg x 1 g | G36: #VALUE! | H36: 3400 | I36: SE-WT300001X | J36: LOCOSC | K36: 45107 | L36: LP230224-1 | M36: 393 | O36: 4 | P36: =O36 -> 4 | Q36: =AJ36 -> 4 | R36: =AK36 -> 4 | S36: =AL36 -> 4 | T36: =AM36 -> 4 | AJ36: =P36-Z36+AE36+U36 -> 4 | AK36: =Q36-AA36+AF36+V36 -> 4 | AL36: =R36-AB36+AG36+W36 -> 4 | AM36: =S36-AC36+AH36+X36 -> 4 | AN36: =T36-AD36+AI36+Y36 -> 4 | AP36: =AN36 -> 4
A37: =+A36+1 -> 32 | B37: BASCULA DE MESA MODELO SE-Y2-208 CAPACIDAD 40kg X 5g | C37: No. 1 | D37: TECNO SCALE | E37: SE-Y2-208 | F37: 40 kg x 5 g | G37: #VALUE! | H37: 550 | I37: SE-Y2-208 | J37: LOCOSC | K37: 45328 | L37: LP230224-1 | M37: 32 | O37: 14 | P37: =O37 -> 14 | Q37: =AJ37 -> 14 | R37: =AK37 -> 14 | S37: =AL37 -> 14 | T37: =AM37 -> 14 | AJ37: =P37-Z37+AE37+U37 -> 14 | AK37: =Q37-AA37+AF37+V37 -> 14 | AL37: =R37-AB37+AG37+W37 -> 14 | AM37: =S37-AC37+AH37+X37 -> 14 | AN37: =T37-AD37+AI37+Y37 -> 14 | AP37: =AN37 -> 14
A38: =+A37+1 -> 33 | B38: BASCULA DE PISO ACERO INOXIDABLE CAPACIDAD 150kg DE 40X50 | C38: No. 1 | D38: BRECKNELL | E38: SE-7610W | F38: 150 x 0.02 kg | G38: #VALUE! | H38: 7500 | I38: SE-7510W-150kg | J38: LOCOSC | K38: 45107 | L38: LP230224-1 | M38: 392 | O38: 5 | P38: =O38 -> 5 | Q38: =AJ38 -> 5 | R38: =AK38 -> 5 | S38: =AL38 -> 5 | T38: =AM38 -> 5 | AJ38: =P38-Z38+AE38+U38 -> 5 | AK38: =Q38-AA38+AF38+V38 -> 5 | AL38: =R38-AB38+AG38+W38 -> 5 | AM38: =S38-AC38+AH38+X38 -> 5 | AN38: =T38-AD38+AI38+Y38 -> 5 | AO38: 1 | AP38: =AN38 -> 5
A39: =+A38+1 -> 34 | B39: BÁSCULA DE PISO SS ACERO INOXIDABLE CAPACIDAD 150 kg DE 60 x 60 cm | C39: NO. 1 | D39: BRECKNELL | E39: SE-7610WSS | F39: 150 x 0.02 kg | G39: #VALUE! | H39: 10800 | I39: SE7610W-SS-6060-150kg | J39: LOCOSC | K39: 45673 | L39: 240907-1 | M39: 126 | N39: SALE A DEMOSTRACION SERIE: 0241013005 | O39: 0 | P39: =O39 -> 0 | Q39: =AJ39 -> 0 | R39: =AK39 -> 0 | S39: =AL39 -> 5 | T39: =AM39 -> 5 | W39: 5 | AJ39: =P39-Z39+AE39+U39 -> 0 | AK39: =Q39-AA39+AF39+V39 -> 0 | AL39: =R39-AB39+AG39+W39 -> 5 | AM39: =S39-AC39+AH39+X39 -> 5 | AN39: =T39-AD39+AI39+Y39 -> 5 | AO39: 1 | AP39: =AN39 -> 5
A40: =+A39+1 -> 35 | B40: BASCULA DE PISO CAPACIDAD 30kg DE 40X40 | C40: No. 1 | D40: BRECKNELL | E40: SE-7610 | F40: 30 x 0.005 kg | G40: #VALUE! | H40: 2800 | I40: SE-LP7610-30kg | J40: LOCOSC | K40: 45574 | L40: LP3211240 | M40: 71 | O40: 8 | P40: =O40 -> 8 | Q40: =AJ40 -> 8 | R40: =AK40 -> 8 | S40: =AL40 -> 8 | T40: =AM40 -> 8 | AJ40: =P40-Z40+AE40+U40 -> 8 | AK40: =Q40-AA40+AF40+V40 -> 8 | AL40: =R40-AB40+AG40+W40 -> 8 | AM40: =S40-AC40+AH40+X40 -> 8 | AN40: =T40-AD40+AI40+Y40 -> 8 | AO40: 1 | AP40: =AN40 -> 8
A41: =+A40+1 -> 36 | B41: BASCULA DE PISO CAPACIDAD 60kg DE 40X50 | C41: No. 1 | D41: BRECKNELL | E41: SE-7610 | F41: 60 x 0.01 kg | G41: #VALUE! | H41: 2800 | I41: SE-LP7610-60kg | J41: LOCOSC | K41: 45574 | L41: LP3211240 | M41: 71 | O41: 2 | P41: =O41 -> 2 | Q41: =AJ41 -> 2 | R41: =AK41 -> 2 | S41: =AL41 -> 2 | T41: =AM41 -> 2 | AJ41: =P41-Z41+AE41+U41 -> 2 | AK41: =Q41-AA41+AF41+V41 -> 2 | AL41: =R41-AB41+AG41+W41 -> 2 | AM41: =S41-AC41+AH41+X41 -> 2 | AN41: =T41-AD41+AI41+Y41 -> 2 | AO41: 0 | AP41: =AN41 -> 2
A42: =+A41+1 -> 37 | B42: BASCULA DE PISO PLATAFORMA /ABS CAJA | C42: No. 1 | D42: BRECKNELL | E42: SE-LP7611 | F42: 600 x 0.5 kg | G42: #VALUE! | H42: 5500 | I42: SE7611J-5060-600kg | J42: LOCOSC | K42: 45673 | L42: 240907-1 | M42: 127 | O42: 5 | P42: =O42 -> 5 | Q42: =AJ42 -> 5 | R42: =AK42 -> 5 | S42: =AL42 -> 10 | T42: =AM42 -> 10 | W42: 5 | AJ42: =P42-Z42+AE42+U42 -> 5 | AK42: =Q42-AA42+AF42+V42 -> 5 | AL42: =R42-AB42+AG42+W42 -> 10 | AM42: =S42-AC42+AH42+X42 -> 10 | AN42: =T42-AD42+AI42+Y42 -> 10 | AO42: 1 | AP42: =AN42 -> 10
A43: =+A42+1 -> 38 | B43: BÁSCULA DE PLATAFORMA SE7611 DE 1 000 kg | C43: LAB | D43: BRECKNELL | E43: SE7611T | F43: 1 000 kg | G43: #VALUE! | I43: SE7611-1X1M-1T | J43: LOCOSC | K43: 45673 | L43: 240907-1 | M43: 128 | N43: SALE A DEMOSTRACIÓN SERIE: 241012010 | O43: 0 | P43: =O43 -> 0 | Q43: =AJ43 -> 0 | R43: =AK43 -> 0 | S43: =AL43 -> 10 | T43: =AM43 -> 10 | W43: 10 | AJ43: =P43-Z43+AE43+U43 -> 0 | AK43: =Q43-AA43+AF43+V43 -> 0 | AL43: =R43-AB43+AG43+W43 -> 10 | AM43: =S43-AC43+AH43+X43 -> 10 | AN43: =T43-AD43+AI43+Y43 -> 10 | AO43: 1 | AP43: =AN43 -> 10
A44: =+A43+1 -> 39 | B44: BASCULA ELECTRNICA SK 10 WP | C44: No. 1 | D44: AND | E44: SE-SK10WP | F44: 10 x 0.02 kg | G44: #VALUE! | H44: 2000 | I44: SE-BASELE-SK10KWP | J44: AND | K44: 44592 | O44: 1 | P44: =O44 -> 1 | Q44: =AJ44 -> 1 | R44: =AK44 -> 1 | S44: =AL44 -> 1 | T44: =AM44 -> 1 | AJ44: =P44-Z44+AE44+U44 -> 1 | AK44: =Q44-AA44+AF44+V44 -> 1 | AL44: =R44-AB44+AG44+W44 -> 1 | AM44: =S44-AC44+AH44+X44 -> 1 | AN44: =T44-AD44+AI44+Y44 -> 1 | AP44: =AN44 -> 1
A45: =+A44+1 -> 40 | B45: BASCULA ELECTRONICA 405 15 K | C45: No. 1 | D45: BRECKNELL | E45: SE-405 | F45: 15 x 0.002 kg | G45: #VALUE! | H45: 1500 | I45: SE-BASELE-405 | J45: BRECKNELL | K45: 44592 | O45: 1 | P45: =O45 -> 1 | Q45: =AJ45 -> 1 | R45: =AK45 -> 1 | S45: =AL45 -> 1 | T45: =AM45 -> 1 | AJ45: =P45-Z45+AE45+U45 -> 1 | AK45: =Q45-AA45+AF45+V45 -> 1 | AL45: =R45-AB45+AG45+W45 -> 1 | AM45: =S45-AC45+AH45+X45 -> 1 | AN45: =T45-AD45+AI45+Y45 -> 1 | AP45: =AN45 -> 1
A46: =+A45+1 -> 41 | B46: BASCULA ELECTRONICA C 3235 6 K | C46: No. 1 | D46: BRECKNELL | E46: SE-3235 | F46: 6 x 0.001 kg | G46: #VALUE! | H46: 3200 | I46: SE-BASELE-BRCK-C3235-6 | J46: BRECKNELL | K46: 44592 | O46: 0 | P46: =O46 -> 0 | Q46: =AJ46 -> 0 | R46: =AK46 -> 0 | S46: =AL46 -> 0 | T46: =AM46 -> 0 | AJ46: =P46-Z46+AE46+U46 -> 0 | AK46: =Q46-AA46+AF46+V46 -> 0 | AL46: =R46-AB46+AG46+W46 -> 0 | AM46: =S46-AC46+AH46+X46 -> 0 | AN46: =T46-AD46+AI46+Y46 -> 0 | AP46: =AN46 -> 0
A47: =+A46+1 -> 42 | B47: BASCULA ELECTRONICA C 3235 6 K (PARA DEMO) | C47: No. 1 | D47: BRECKNELL | E47: SE-3235 | F47: 6 x 0.001 kg | G47: #VALUE! | H47: 3200 | I47: SE-BASELE-BRCK-C3235-6-D | J47: BRECKNELL | K47: 44592 | O47: 1 | P47: =O47 -> 1 | Q47: =AJ47 -> 1 | R47: =AK47 -> 1 | S47: =AL47 -> 1 | T47: =AM47 -> 1 | AJ47: =P47-Z47+AE47+U47 -> 1 | AK47: =Q47-AA47+AF47+V47 -> 1 | AL47: =R47-AB47+AG47+W47 -> 1 | AM47: =S47-AC47+AH47+X47 -> 1 | AN47: =T47-AD47+AI47+Y47 -> 1 | AO47: 1 | AP47: =AN47 -> 1
A48: =+A47+1 -> 43 | B48: BASCULA ELECTRONICA COLGANTE BRECKNELL 45 K | C48: No. 1 | D48: BRECKNELL | E48: ELECTROSAMSON SE-ESN | F48: 45 x 0.05 kg | G48: #VALUE! | H48: 1725 | I48: SE-GE-BEC-ES-45K | J48: BRECKNELL | K48: 45138 | L48: 2130012 | M48: 417 | O48: 1 | P48: =O48 -> 1 | Q48: =AJ48 -> 1 | R48: =AK48 -> 1 | S48: =AL48 -> 1 | T48: =AM48 -> 1 | AJ48: =P48-Z48+AE48+U48 -> 1 | AK48: =Q48-AA48+AF48+V48 -> 1 | AL48: =R48-AB48+AG48+W48 -> 1 | AM48: =S48-AC48+AH48+X48 -> 1 | AN48: =T48-AD48+AI48+Y48 -> 1 | AP48: =AN48 -> 1
A49: =+A48+1 -> 44 | B49: BASCULA ELECTRONICA SK 10 KEG | C49: No. 1 | D49: AND | E49: SE-SK10KEG | F49: 10 x 0.005 kg | G49: #VALUE! | H49: 1500 | I49: SE-BASELE-SK10KEG | J49: AND | K49: 44592 | O49: 1 | P49: =O49 -> 1 | Q49: =AJ49 -> 1 | R49: =AK49 -> 1 | S49: =AL49 -> 1 | T49: =AM49 -> 1 | AJ49: =P49-Z49+AE49+U49 -> 1 | AK49: =Q49-AA49+AF49+V49 -> 1 | AL49: =R49-AB49+AG49+W49 -> 1 | AM49: =S49-AC49+AH49+X49 -> 1 | AN49: =T49-AD49+AI49+Y49 -> 1 | AP49: =AN49 -> 1
A50: =+A49+1 -> 45 | B50: BASCULA ELECTRONICA SK 20 KEG | C50: No. 1 | D50: AND | E50: SE-SK20KEG | F50: 20 x 0.1 kg | G50: #VALUE! | H50: 1500 | I50: SE-BASELE-SK20KEG | J50: AND | K50: 44592 | O50: 1 | P50: =O50 -> 1 | Q50: =AJ50 -> 1 | R50: =AK50 -> 1 | S50: =AL50 -> 1 | T50: =AM50 -> 1 | AJ50: =P50-Z50+AE50+U50 -> 1 | AK50: =Q50-AA50+AF50+V50 -> 1 | AL50: =R50-AB50+AG50+W50 -> 1 | AM50: =S50-AC50+AH50+X50 -> 1 | AN50: =T50-AD50+AI50+Y50 -> 1 | AP50: =AN50 -> 1
A51: =+A50+1 -> 46 | B51: BASCULA N1124-LL MECANICA MODELO SE-1124B | C51: N/A | D51: FAIRBANKS MORSE | E51: SE-1124B | F51: 1 200 x 0.5 lb | G51: #VALUE! | H51: 9800 | I51: SE-BASC-MECA | J51: SIDASA | K51: 45315 | L51: 3673178618 | M51: 11 | O51: 0 | P51: =O51 -> 0 | Q51: =AJ51 -> 0 | R51: =AK51 -> 0 | S51: =AL51 -> 0 | T51: =AM51 -> 0 | AJ51: =P51-Z51+AE51+U51 -> 0 | AK51: =Q51-AA51+AF51+V51 -> 0 | AL51: =R51-AB51+AG51+W51 -> 0 | AM51: =S51-AC51+AH51+X51 -> 0 | AN51: =T51-AD51+AI51+Y51 -> 0 | AP51: =AN51 -> 0
A52: =+A51+1 -> 47 | B52: BASCULA TMF-30kg | C52: No. 2 | D52: TM | E52: TMF | F52: 30 x 0.005 kg | G52: #VALUE! | H52: 4800 | I52: SE-BAS-TMF-30 | J52: LOCOSC | K52: 45107 | L52: LP230224-1 | M52: 393 | O52: 1 | P52: =O52 -> 1 | Q52: =AJ52 -> 1 | R52: =AK52 -> 1 | S52: =AL52 -> 1 | T52: =AM52 -> 1 | AJ52: =P52-Z52+AE52+U52 -> 1 | AK52: =Q52-AA52+AF52+V52 -> 1 | AL52: =R52-AB52+AG52+W52 -> 1 | AM52: =S52-AC52+AH52+X52 -> 1 | AN52: =T52-AD52+AI52+Y52 -> 1 | AP52: =AN52 -> 1
A53: =+A52+1 -> 48 | B53: BASCULA-TMF-15K | C53: No. 2 | D53: TM | F53: 15 x 0.001 kg | G53: #VALUE! | H53: 4800 | I53: SE-BASC-TMF | J53: LOCOSC | K53: 44592 | O53: 1 | P53: =O53 -> 1 | Q53: =AJ53 -> 1 | R53: =AK53 -> 1 | S53: =AL53 -> 1 | T53: =AM53 -> 1 | AJ53: =P53-Z53+AE53+U53 -> 1 | AK53: =Q53-AA53+AF53+V53 -> 1 | AL53: =R53-AB53+AG53+W53 -> 1 | AM53: =S53-AC53+AH53+X53 -> 1 | AN53: =T53-AD53+AI53+Y53 -> 1 | AP53: =AN53 -> 1
A54: =+A53+1 -> 49 | B54: BASCULA PESA EJES CON MARCO/INDICADOR LP7561 (SOLO MODULOS X2PADS) | C54: LAB | D54: TECNO SCALE | E54: SE-LP7662 | F54: 30 t | G54: #VALUE! | I54: SE7662-1530-30T*2PADS | J54: LOCOSC | K54: 45687 | L54: 240907-1 | M54: 144 | N54: 1-YEGUADA // 2 MODULOS PESA EJES PROPIEDAD DE DOS CERROS, SE INGRESAN POR QUE AUN NO SE HA HECHO LA ENTREGA | O54: 0 | P54: =O54 -> 0 | Q54: =AJ54 -> 0 | R54: =AK54 -> 0 | S54: =AL54 -> 2 | T54: =AM54 -> 2 | W54: 4 | AB54: 2 | AI54: 2 | AJ54: =P54-Z54+AE54+U54 -> 0 | AK54: =Q54-AA54+AF54+V54 -> 0 | AL54: =R54-AB54+AG54+W54 -> 2 | AM54: =S54-AC54+AH54+X54 -> 2 | AN54: =T54-AD54+AI54+Y54 -> 4 | AP54: =AN54 -> 4 | AR54: 285
A55: =+A54+1 -> 50 | B55: BASCULA PESA EJES/INDICADOR LP7561 | C55: No.1 | D55: TECNO SCALE | E55: SE-7662 | F55: 30T | G55: #VALUE! | I55: SE-7662-1530-30T*2 PADS | J55: LOCOSC | K55: 45566 | L55: LP240702-2 | M55: 68 | O55: 0 | P55: =O55 -> 0 | Q55: =AJ55 -> 0 | R55: =AK55 -> 0 | S55: =AL55 -> 0 | T55: =AM55 -> 0 | AJ55: =P55-Z55+AE55+U55 -> 0 | AK55: =Q55-AA55+AF55+V55 -> 0 | AL55: =R55-AB55+AG55+W55 -> 0 | AM55: =S55-AC55+AH55+X55 -> 0 | AN55: =T55-AD55+AI55+Y55 -> 0 | AP55: =AN55 -> 0
A56: =+A55+1 -> 51 | B56: BASCULA PESA ANIMAL (CERDOS) SE-7628A | C56: No.1 | D56: BRECKNELL | E56: SE-7628A | F56: 2 T | G56: #VALUE! | I56: SE-7628A-1215-2T | J56: LOCOSC | K56: 45566 | L56: LP240702-2 | M56: 75 | N56: 1-JOSE YAX | O56: 3 | P56: =O56 -> 3 | Q56: =AJ56 -> 2 | R56: =AK56 -> 2 | S56: =AL56 -> 2 | T56: =AM56 -> 2 | Z56: 1 | AJ56: =P56-Z56+AE56+U56 -> 2 | AK56: =Q56-AA56+AF56+V56 -> 2 | AL56: =R56-AB56+AG56+W56 -> 2 | AM56: =S56-AC56+AH56+X56 -> 2 | AN56: =T56-AD56+AI56+Y56 -> 2 | AP56: =AN56 -> 2 | AQ56: 900349960 | AR56: 252 | AS56: E:4590-JOSE
A57: =+A56+1 -> 52 | B57: BASCULA PESA ANIMAL (GANADO) SE-7628A | C57: No.1 | D57: BRECKNELL | E57: SE-7628A | F57: 1.5T | G57: #VALUE! | I57: SE-7628A-0923-1.5T | J57: LOCOSC | K57: 45566 | L57: LP240702-2 | M57: 75 | O57: 7 | P57: =O57 -> 7 | Q57: =AJ57 -> 7 | R57: =AK57 -> 7 | S57: =AL57 -> 7 | T57: =AM57 -> 7 | AJ57: =P57-Z57+AE57+U57 -> 7 | AK57: =Q57-AA57+AF57+V57 -> 7 | AL57: =R57-AB57+AG57+W57 -> 7 | AM57: =S57-AC57+AH57+X57 -> 7 | AN57: =T57-AD57+AI57+Y57 -> 7 | AP57: =AN57 -> 7
A58: =+A57+1 -> 53 | B58: BÁSCULA ARA BANDA DINAMICA INCLUYE 1 INDICADOR CON ARMARIO, 4 CELDAS DE CARGA TIPO S TSC 500 kg METTLER TOLEDO, 8 RODILLOS Y 1 ESTRUCTURA DE METAL | D58: TECNO SCALE | E58: SE-ICS-17A | F58: 2 T | J58: YORK | K58: 45687 | L58: 04YK01K602 | M58: 141 | N58: POR INDICACIÓN DE DOÑA KARLA SE INGRESA NUEVAMENTE BASCULA PARA BANDA DINAMICA DEBIDO A QUE NO SE RECIBIO EN BODEGA DE ACEROS DE GUATEMALA | O58: 0 | P58: =O58 -> 0 | Q58: =AJ58 -> 0 | R58: =AK58 -> 0 | S58: =AL58 -> 0 | T58: =AM58 -> 0 | AI58: 1 | AJ58: =P58-Z58+AE58+U58 -> 0 | AK58: =Q58-AA58+AF58+V58 -> 0 | AL58: =R58-AB58+AG58+W58 -> 0 | AM58: =S58-AC58+AH58+X58 -> 0 | AN58: =T58-AD58+AI58+Y58 -> 1 | AP58: =AN58 -> 1
A59: =+A58+1 -> 54 | AP59: =AN59 -> 0
A60: =+A59+1 -> 55 | B60: BATERIAS 4V4AH | C60: No. 2 | D60: S/M | E60: S/M | F60: 4V | G60: #VALUE! | H60: 300 | I60: SE-BAT4V | J60: LOCOSC | K60: 45107 | L60: LP230224-1 | M60: 387 | O60: 34 | P60: =O60 -> 34 | Q60: =AJ60 -> 34 | R60: =AK60 -> 34 | S60: =AL60 -> 34 | T60: =AM60 -> 34 | AA60: 3 | AC60: 8 | AD60: 4 | AF60: 3 | AH60: 8 | AI60: 4 | AJ60: =P60-Z60+AE60+U60 -> 34 | AK60: =Q60-AA60+AF60+V60 -> 34 | AL60: =R60-AB60+AG60+W60 -> 34 | AM60: =S60-AC60+AH60+X60 -> 34 | AN60: =T60-AD60+AI60+Y60 -> 34 | AP60: =AN60 -> 34
A61: =+A60+1 -> 56 | B61: BATERIAS 6V4AH | C61: No. 2 | D61: S/M | E61: S/M | F61: 6V | G61: #VALUE! | H61: 300 | I61: SE-BAT6V | J61: LOCOSC | K61: 45107 | L61: LP230224-1 | M61: 387 | N61: 2-JESUS LORENZANA/ 1-CESAR PINEDA//1-AG PARA BASCULA COLGANTE/1-PARA BASCULA COLGANTE LP7650G QUE QUEDA EN BODEGA// EN INVENTARIO FISICO HAY UN FALTANTE DE 1 BATERIA QUE NO TIENE BOLETA DE SALIDA, SE VERIFICO EN LAS SALIDAS PERO TODAS FUERON ENTREGADAS Y ASIGNADAS A QUIEN SE LES VENDIO// | O61: 58 | P61: =O61 -> 58 | Q61: =AJ61 -> 55 | R61: =AK61 -> 55 | S61: =AL61 -> 55 | T61: =AM61 -> 55 | Z61: 3 | AA61: 2 | AC61: 8 | AF61: 2 | AH61: 8 | AI61: 3 | AJ61: =P61-Z61+AE61+U61 -> 55 | AK61: =Q61-AA61+AF61+V61 -> 55 | AL61: =R61-AB61+AG61+W61 -> 55 | AM61: =S61-AC61+AH61+X61 -> 55 | AN61: =T61-AD61+AI61+Y61 -> 58 | AP61: =AN61 -> 58 | AQ61: 837175793 | AR61: 253//262//263 | AS61: E:-JESUS// E: CESAR//E:4608-AG//
A62: =+A61+1 -> 57 | B62: BATERIAS 6V8A NIPPON | C62: NO. 2 | E62: S/M | F62: 6V | M62: 72 | O62: 0 | P62: =O62 -> 0 | Q62: =AJ62 -> 0 | R62: =AK62 -> 0 | S62: =AL62 -> 0 | T62: =AM62 -> 0 | AJ62: =P62-Z62+AE62+U62 -> 0 | AK62: =Q62-AA62+AF62+V62 -> 0 | AL62: =R62-AB62+AG62+W62 -> 0 | AM62: =S62-AC62+AH62+X62 -> 0 | AN62: =T62-AD62+AI62+Y62 -> 0 | AP62: =AN62 -> 0
A63: =+A62+1 -> 58 | B63: BATERIAS 3.7V /2000MAH | C63: NO.2 | D63: S/M | E63: GDICR18650 | F63: 3.7V/2000mAH | G63: #VALUE! | I63: SE-BAT3V | J63: LOCOSC | K63: 45574 | L63: LP3211240 | M63: 75 | N63: 10 BATERIAS INSTALADAS EN INDICADORES E BODEGA MODELO SE7517 | O63: 35 | P63: =O63 -> 35 | Q63: =AJ63 -> 35 | R63: =AK63 -> 35 | S63: =AL63 -> 35 | T63: =AM63 -> 25 | AC63: 10 | AJ63: =P63-Z63+AE63+U63 -> 35 | AK63: =Q63-AA63+AF63+V63 -> 35 | AL63: =R63-AB63+AG63+W63 -> 35 | AM63: =S63-AC63+AH63+X63 -> 25 | AN63: =T63-AD63+AI63+Y63 -> 25 | AP63: =AN63 -> 25 | AR63: 293
A64: =+A63+1 -> 59 | B64: BATERIAS 3.7V /4000mAh | C64: NO.2 | D64: S/M | E64: LPB04050 152P | F64: 3.7V/4000mAh | G64: #VALUE! | I64: SE-BAT3V- | J64: LOCOSC | K64: 45574 | L64: LP3211240 | M64: 75 | O64: 45 | P64: =O64 -> 45 | Q64: =AJ64 -> 45 | R64: =AK64 -> 45 | S64: =AL64 -> 45 | T64: =AM64 -> 45 | AJ64: =P64-Z64+AE64+U64 -> 45 | AK64: =Q64-AA64+AF64+V64 -> 45 | AL64: =R64-AB64+AG64+W64 -> 45 | AM64: =S64-AC64+AH64+X64 -> 45 | AN64: =T64-AD64+AI64+Y64 -> 45 | AP64: =AN64 -> 45
A65: =+A64+1 -> 60 | B65: BATERIAS 6V/5Ah | C65: NO. 2 | D65: S/M | E65: DJW6-5.0 | F65: 6V/5mAH | G65: #VALUE! | I65: SE-BAT6V/5 | J65: LOCOSC | K65: 45673 | L65: 240907-1 | M65: 130 | O65: 0 | P65: =O65 -> 0 | Q65: =AJ65 -> 0 | R65: =AK65 -> 0 | S65: =AL65 -> 4 | T65: =AM65 -> 4 | W65: 4 | AJ65: =P65-Z65+AE65+U65 -> 0 | AK65: =Q65-AA65+AF65+V65 -> 0 | AL65: =R65-AB65+AG65+W65 -> 4 | AM65: =S65-AC65+AH65+X65 -> 4 | AN65: =T65-AD65+AI65+Y65 -> 4 | AP65: =AN65 -> 4
A66: =+A65+1 -> 61 | B66: BATERIAS 12V/7.0Ah PARA INDICADOR LP75819 | C66: NO. 2 | D66: S/M | E66: DJW12-7.0 | F66: 12V/7.0mAh | G66: #VALUE! | I66: SE-BAT12V/7 | J66: LOCOSC | K66: 45673 | L66: 240907-1 | M66: 131 | O66: 0 | P66: =O66 -> 0 | Q66: =AJ66 -> 0 | R66: =AK66 -> 0 | S66: =AL66 -> 10 | T66: =AM66 -> 10 | W66: 10 | AJ66: =P66-Z66+AE66+U66 -> 0 | AK66: =Q66-AA66+AF66+V66 -> 0 | AL66: =R66-AB66+AG66+W66 -> 10 | AM66: =S66-AC66+AH66+X66 -> 10 | AN66: =T66-AD66+AI66+Y66 -> 10 | AP66: =AN66 -> 10
A67: =+A66+1 -> 62 | B67: CABLE CELDA DE CARGA MTX (6 PINES) | C67: No. 2 | D67: METTLER TOLEDO | E67: MTX | G67: #VALUE! | I67: SE-CABLE-MTX | K67: 44592 | O67: 0 | P67: =O67 -> 0 | Q67: =AJ67 -> 0 | R67: =AK67 -> 0 | S67: =AL67 -> 0 | T67: =AM67 -> 0 | AJ67: =P67-Z67+AE67+U67 -> 0 | AK67: =Q67-AA67+AF67+V67 -> 0 | AL67: =R67-AB67+AG67+W67 -> 0 | AM67: =S67-AC67+AH67+X67 -> 0 | AN67: =T67-AD67+AI67+Y67 -> 0 | AP67: =AN67 -> 0
A68: =+A67+1 -> 63 | B68: CABLE CELDA DE CARGA PDX (5 PINES) | C68: No. 2 | D68: METTLER TOLEDO | E68: PDX | G68: #VALUE! | I68: SE-CABLE-PDX | K68: 44592 | O68: 0 | P68: =O68 -> 0 | Q68: =AJ68 -> 0 | R68: =AK68 -> 0 | S68: =AL68 -> 0 | T68: =AM68 -> 0 | AJ68: =P68-Z68+AE68+U68 -> 0 | AK68: =Q68-AA68+AF68+V68 -> 0 | AL68: =R68-AB68+AG68+W68 -> 0 | AM68: =S68-AC68+AH68+X68 -> 0 | AN68: =T68-AD68+AI68+Y68 -> 0 | AP68: =AN68 -> 0
A69: =+A68+1 -> 64 | B69: CABLE PARA BATERIA DE INDICADOR DIGITAL MODELO SE-7517 ROJO Y NEGRO | C69: No.2 | E69: SE-7517BA | I69: SE-CAB-7517BA | J69: LOCOSC | K69: 45279 | M69: 481 | O69: 12 | P69: =O69 -> 12 | Q69: =AJ69 -> 12 | R69: =AK69 -> 12 | S69: =AL69 -> 12 | T69: =AM69 -> 12 | AJ69: =P69-Z69+AE69+U69 -> 12 | AK69: =Q69-AA69+AF69+V69 -> 12 | AL69: =R69-AB69+AG69+W69 -> 12 | AM69: =S69-AC69+AH69+X69 -> 12 | AN69: =T69-AD69+AI69+Y69 -> 12 | AP69: =AN69 -> 12
A70: =+A69+1 -> 65 | B70: CABLE PARA INDICADOR LP7581P CON CONECTOR (CABLE ROJO Y NEGRO) | C70: NO. 2 | D70: S/M | E70: S/M | F70: S/C | G70: #VALUE! | I70: SE-CABLE-LP7581P | J70: LOCOSC | K70: 45673 | L70: 240907-1 | M70: 130 | N70: SE RECTIFICA DEBIDO A QUE 11 CABLES SON LOS QUE INGRESARON | O70: 0 | P70: =O70 -> 0 | Q70: =AJ70 -> 0 | R70: =AK70 -> 0 | S70: =AL70 -> 11 | T70: =AM70 -> 11 | W70: 11 | AJ70: =P70-Z70+AE70+U70 -> 0 | AK70: =Q70-AA70+AF70+V70 -> 0 | AL70: 11 | AM70: =S70-AC70+AH70+X70 -> 11 | AN70: =T70-AD70+AI70+Y70 -> 11 | AP70: =AN70 -> 11
A71: =+A70+1 -> 66 | B71: CAJA PLASTICA IP 67 | C71: No. 2 | G71: #VALUE! | I71: SE-CAJ-IP67 | O71: 3 | P71: =O71 -> 3 | Q71: =AJ71 -> 3 | R71: =AK71 -> 3 | S71: =AL71 -> 3 | T71: =AM71 -> 3 | AJ71: =P71-Z71+AE71+U71 -> 3 | AK71: =Q71-AA71+AF71+V71 -> 3 | AL71: =R71-AB71+AG71+W71 -> 3 | AM71: =S71-AC71+AH71+X71 -> 3 | AN71: =T71-AD71+AI71+Y71 -> 3 | AP71: =AN71 -> 3
A72: =+A71+1 -> 67 | B72: CAJA SUMA | C72: No. 2 | D72: S/M | E72: SE-LP7312 | F72: 4 CANALES | G72: #VALUE! | H72: 1500 | I72: SE-CAJA-SUMA LP7312-A2-4 | J72: LOCOSC | K72: 45687 | L72: LP230224-1 | M72: 145 | N72: 1-CACHACEROS-1JOSE TRIGUEROS// ALDO SOTO// INGRESAN 1 SERIE: 2304260009//INGRESA CAJA QUE SACO DON ALDO CON BASE QUEBRADA PARA REPONER | O72: 7 | P72: =O72 -> 7 | Q72: =AJ72 -> 7 | R72: =AK72 -> 7 | S72: =AL72 -> 6 | T72: =AM72 -> 5 | W72: 1 | AB72: 2 | AC72: 1 | AI72: 1 | AJ72: =P72-Z72+AE72+U72 -> 7 | AK72: =Q72-AA72+AF72+V72 -> 7 | AL72: =R72-AB72+AG72+W72 -> 6 | AM72: =S72-AC72+AH72+X72 -> 5 | AN72: =T72-AD72+AI72+Y72 -> 6 | AO72: 1 SOLO CAJA | AP72: =AN72 -> 6 | AR72: 275//299/ BOLETA DE INGRESO 140//BOLETA DE INGRESO 145
A73: =+A72+1 -> 68 | B73: CAJA SUMA 4 CANALES TOTAL COMP STOCK 1007 | C73: No. 2 | D73: TOTAL COMP | E73: S-45 1250 | I73: SE-CAJA-1250-5-SS | J73: TOTAL COMP | K73: 45062 | M73: 352 | O73: 0 | P73: =O73 -> 0 | Q73: =AJ73 -> 0 | R73: =AK73 -> 0 | S73: =AL73 -> 0 | T73: =AM73 -> 0 | AJ73: =P73-Z73+AE73+U73 -> 0 | AK73: =Q73-AA73+AF73+V73 -> 0 | AL73: =R73-AB73+AG73+W73 -> 0 | AM73: =S73-AC73+AH73+X73 -> 0 | AN73: =T73-AD73+AI73+Y73 -> 0 | AP73: =AN73 -> 0
A74: =+A73+1 -> 69 | B74: CAJA SUMA ACERO INOX 4 CANALES 50063-0066 TORNILLOS | C74: No. 2 | D74: BRECKNELL | E74: 50063-0066 TORNILLOS | G74: #VALUE! | H74: 5500 | I74: SE-CAJASUM-4C | J74: BRECKNELL | K74: 45391 | L74: 2187074-001 | M74: 55 | N74: 2-YEGUADA | O74: 3 | P74: =O74 -> 3 | Q74: =AJ74 -> 3 | R74: =AK74 -> 3 | S74: =AL74 -> 1 | T74: =AM74 -> 1 | AB74: 2 | AJ74: =P74-Z74+AE74+U74 -> 3 | AK74: =Q74-AA74+AF74+V74 -> 3 | AL74: =R74-AB74+AG74+W74 -> 1 | AM74: =S74-AC74+AH74+X74 -> 1 | AN74: =T74-AD74+AI74+Y74 -> 1 | AP74: =AN74 -> 1 | AR74: 285
A75: =+A74+1 -> 70 | B75: CAJA SUMA ACERO INOX 4 CANALES GRAPA AWT15-501062 06 CAMIONERAS | C75: No. 2 | D75: AVERY WEIGH TRONIX | E75: AWT15-501062 06 | G75: #VALUE! | H75: 5500 | I75: SE-CAJASUM-4C-GRA | J75: AVERY WEIGH TRONIX | K75: 45013 | L75: 2103556 | M75: 321 | O75: 6 | P75: =O75 -> 6 | Q75: =AJ75 -> 6 | R75: =AK75 -> 6 | S75: =AL75 -> 6 | T75: =AM75 -> 6 | AJ75: =P75-Z75+AE75+U75 -> 6 | AK75: =Q75-AA75+AF75+V75 -> 6 | AL75: =R75-AB75+AG75+W75 -> 6 | AM75: =S75-AC75+AH75+X75 -> 6 | AN75: =T75-AD75+AI75+Y75 -> 6 | AP75: =AN75 -> 6
A76: =+A75+1 -> 71 | B76: CAJA SUMA ACERO INOXIDABLE | C76: No. 2 | D76: LOCOSC | E76: SE-LP7310 | F76: 4 CANALES | G76: #VALUE! | H76: 2500 | I76: SE-LP7310-S2-4 | J76: LOCOSC | K76: 45328 | L76: LP230224-1 | M76: 32 | O76: 13 | P76: =O76 -> 13 | Q76: =AJ76 -> 13 | R76: =AK76 -> 13 | S76: =AL76 -> 13 | T76: =AM76 -> 13 | AJ76: =P76-Z76+AE76+U76 -> 13 | AK76: =Q76-AA76+AF76+V76 -> 13 | AL76: =R76-AB76+AG76+W76 -> 13 | AM76: =S76-AC76+AH76+X76 -> 13 | AN76: =T76-AD76+AI76+Y76 -> 13 | AP76: =AN76 -> 13
A77: =+A76+1 -> 72 | B77: CAJA SUMA ACERO INOXIDABLE | C77: NO. 2 | D77: BRECKNELL | E77: SE-7312-S2-4 | F77: 4 CANALES | G77: #VALUE! | I77: SE-7312-SS | J77: LOCOSC | K77: 45626 | L77: S/F | M77: 103 | N77: INGRESAN 2 SERIE: 240920018, 240920019 DE MODULOS PESA EJES YEGUADA | O77: 1 | P77: =O77 -> 1 | Q77: =AJ77 -> 1 | R77: =AK77 -> 1 | S77: =AL77 -> 1 | T77: =AM77 -> 3 | X77: 2 | AJ77: =P77-Z77+AE77+U77 -> 1 | AK77: =Q77-AA77+AF77+V77 -> 1 | AL77: =R77-AB77+AG77+W77 -> 1 | AM77: =S77-AC77+AH77+X77 -> 3 | AN77: =T77-AD77+AI77+Y77 -> 3 | AP77: =AN77 -> 3 | AR77: BOLETA INGRESO 138
A78: =+A77+1 -> 73 | B78: CAJA SUMA DE ACERO INOX CAMIONERA 12 CANALES | C78: No. 2 | D78: BRECKNELL | E78: IX-JXHG05-12-S | F78: 12 CANALES | G78: #VALUE! | I78: SE-CAJ-IX-JXHG05-12-S | J78: CNIC | K78: 45126 | L78: 2023015 | M78: 409 | O78: 0 | P78: =O78 -> 0 | Q78: =AJ78 -> 0 | R78: =AK78 -> 0 | S78: =AL78 -> 0 | T78: =AM78 -> 0 | AJ78: =P78-Z78+AE78+U78 -> 0 | AK78: =Q78-AA78+AF78+V78 -> 0 | AL78: =R78-AB78+AG78+W78 -> 0 | AM78: =S78-AC78+AH78+X78 -> 0 | AN78: =T78-AD78+AI78+Y78 -> 0 | AP78: =AN78 -> 0
A79: =+A78+1 -> 74 | B79: CAJA SUMA SS DE 10 CANALES (SOLO CAJA | C79: NO. 2 | D79: S/M | E79: S/M | F79: 10 CANALES | I79: S/C | K79: 45656 | L79: INGRESA DE SERVICIO EN AVICOLA GABY/BASCULAS PRECICELL | M79: 102 | O79: 1 | P79: =O79 -> 1 | Q79: =AJ79 -> 1 | R79: =AK79 -> 1 | S79: =AL79 -> 1 | T79: =AM79 -> 1 | AJ79: =P79-Z79+AE79+U79 -> 1 | AK79: =Q79-AA79+AF79+V79 -> 1 | AL79: =R79-AB79+AG79+W79 -> 1 | AM79: =S79-AC79+AH79+X79 -> 1 | AN79: =T79-AD79+AI79+Y79 -> 1 | AP79: =AN79 -> 1
A80: =+A79+1 -> 75 | B80: CALIBRADOR DIGITAL 0 - 150mm | C80: NO. 2 | D80: SUMIMET | E80: ACCUD 112-006-12 | F80: 0 a 150mm / 0 a 6 " | G80: #VALUE! | H80: 4200 | I80: SE-VD67 | J80: SUMINISTROS EN METROLOGIA | K80: 45670 | L80: 131207285 | M80: 124 | N80: 1-ACEROS DE GUATEMALA | O80: 0 | P80: =O80 -> 0 | Q80: =AJ80 -> 0 | R80: =AK80 -> 1 | S80: =AL80 -> 0 | T80: =AM80 -> 0 | V80: 1 | AB80: 1 | AJ80: =P80-Z80+AE80+U80 -> 0 | AK80: =Q80-AA80+AF80+V80 -> 1 | AL80: =R80-AB80+AG80+W80 -> 0 | AM80: =S80-AC80+AH80+X80 -> 0 | AN80: =T80-AD80+AI80+Y80 -> 0 | AP80: =AN80 -> 0 | AR80: 278 | AS80: E:4583-AG
A81: =+A80+1 -> 76 | B81: CALIBRADOR DIGITAL 0 a 300mm | C81: NO. 2 | D81: SUMIMET | E81: ACCUD 112-012-12 | F81: 0 a 300 mm / 0 a 12" | G81: #VALUE! | H81: 4200 | I81: SE-VD67 | J81: SUMINISTROS EN METROLOGIA | K81: 45670 | L81: 131207285 | M81: 124 | N81: 1-ACEROS DE GUATEMALA | O81: 0 | P81: =O81 -> 0 | Q81: =AJ81 -> 0 | R81: =AK81 -> 1 | S81: =AL81 -> 0 | T81: =AM81 -> 0 | V81: 1 | AB81: 1 | AJ81: =P81-Z81+AE81+U81 -> 0 | AK81: =Q81-AA81+AF81+V81 -> 1 | AL81: =R81-AB81+AG81+W81 -> 0 | AM81: =S81-AC81+AH81+X81 -> 0 | AN81: =T81-AD81+AI81+Y81 -> 0 | AP81: =AN81 -> 0 | AR81: 278 | AS81: E:4583-AG
A82: =+A81+1 -> 77 | B82: CARCASA DE INDICADOR SE-7517E | C82: No. 2 | D82: BRECKNELL | E82: SE-7517E | G82: #VALUE! | I82: SE-CARC-7517E | J82: LOCOSC | K82: 44592 | O82: 1 | P82: =O82 -> 1 | Q82: =AJ82 -> 1 | R82: =AK82 -> 1 | S82: =AL82 -> 1 | T82: =AM82 -> 1 | AJ82: =P82-Z82+AE82+U82 -> 1 | AK82: =Q82-AA82+AF82+V82 -> 1 | AL82: =R82-AB82+AG82+W82 -> 1 | AM82: =S82-AC82+AH82+X82 -> 1 | AN82: =T82-AD82+AI82+Y82 -> 1 | AP82: =AN82 -> 1
A83: =+A82+1 -> 78 | B83: CARCASA DE INDICADOR SE-7510 PARTE TRASERA CON BATERIA | C83: NO.2 | D83: BRECKNELL | E83: SE-7510 | I83: SE-CARC-7510/BAT | J83: LOCOSC | K83: 45574 | L83: LP3211240 | M83: 76 | N83: 2 INSTALADOS EN INDICADORES DE BODEGA | O83: 10 | P83: =O83 -> 10 | Q83: =AJ83 -> 10 | R83: =AK83 -> 10 | S83: =AL83 -> 8 | T83: =AM83 -> 8 | AB83: 2 | AJ83: =P83-Z83+AE83+U83 -> 10 | AK83: =Q83-AA83+AF83+V83 -> 10 | AL83: =R83-AB83+AG83+W83 -> 8 | AM83: =S83-AC83+AH83+X83 -> 8 | AN83: =T83-AD83+AI83+Y83 -> 8 | AP83: =AN83 -> 8 | AR83: 293
A84: =+A83+1 -> 79 | B84: CARRITO DE METAL PARA BASCULA 7611 | C84: Lab | D84: SOEXSA | E84: SE-7611 | G84: #VALUE! | I84: SE-CAR-BAS7611 | J84: LOCOSC | K84: 44592 | O84: 1 | P84: =O84 -> 1 | Q84: =AJ84 -> 1 | R84: =AK84 -> 1 | S84: =AL84 -> 1 | T84: =AM84 -> 1 | AJ84: =P84-Z84+AE84+U84 -> 1 | AK84: =Q84-AA84+AF84+V84 -> 1 | AL84: =R84-AB84+AG84+W84 -> 1 | AM84: =S84-AC84+AH84+X84 -> 1 | AN84: =T84-AD84+AI84+Y84 -> 1 | AP84: =AN84 -> 1
A85: =+A84+1 -> 80 | B85: CARTUCHO DE TINTA PARA IMPRESORA LP7561 | C85: NO. 2 | D85: PRINT-RITE | E85: EPSON ERC05 | I85: SE-ERC05 | J85: LOCOSC | K85: 45582 | M85: 81 | O85: 10 | P85: =O85 -> 10 | Q85: =AJ85 -> 10 | R85: =AK85 -> 10 | S85: =AL85 -> 10 | T85: =AM85 -> 10 | AJ85: =P85-Z85+AE85+U85 -> 10 | AK85: =Q85-AA85+AF85+V85 -> 10 | AL85: =R85-AB85+AG85+W85 -> 10 | AM85: =S85-AC85+AH85+X85 -> 10 | AN85: =T85-AD85+AI85+Y85 -> 10 | AP85: =AN85 -> 10
A86: =+A85+1 -> 81 | B86: CELDA DE CARGA TIPO BARRA LP7161 | C86: No. 2 | D86: S/M | E86: LP7161 | F86: 800 kg | G86: #VALUE! | H86: 2800 | I86: SE-CELBAR-LP7161-800KG | J86: LOCOSC | K86: 45325 | M86: 12 | N86: 1-CMI// 1ESAU SALAZAR | O86: 3 | P86: =O86 -> 3 | Q86: =AJ86 -> 2 | R86: =AK86 -> 2 | S86: =AL86 -> 2 | T86: =AM86 -> 1 | Z86: 1 | AC86: 1 | AJ86: =P86-Z86+AE86+U86 -> 2 | AK86: =Q86-AA86+AF86+V86 -> 2 | AL86: =R86-AB86+AG86+W86 -> 2 | AM86: =S86-AC86+AH86+X86 -> 1 | AN86: =T86-AD86+AI86+Y86 -> 1 | AP86: =AN86 -> 1 | AQ86: 1523862006 | AR86: 250//296 | AS86: E:4586-CMI
A87: =+A86+1 -> 82 | B87: CELDA DE CARGA BARRA 50K 65016-050E-NC-001F | C87: No. 2 | D87: BRECKNELL | E87: 65016-050E-NC-001F | F87: 50 k | G87: #VALUE! | H87: Q | I87: SE-CELBAR-65016-50 | J87: BRECKNELL | K87: 44592 | O87: 2 | P87: =O87 -> 2 | Q87: =AJ87 -> 2 | R87: =AK87 -> 2 | S87: =AL87 -> 2 | T87: =AM87 -> 2 | AJ87: =P87-Z87+AE87+U87 -> 2 | AK87: =Q87-AA87+AF87+V87 -> 2 | AL87: =R87-AB87+AG87+W87 -> 2 | AM87: =S87-AC87+AH87+X87 -> 2 | AN87: =T87-AD87+AI87+Y87 -> 2 | AP87: =AN87 -> 2
A88: =+A87+1 -> 83 | B88: CELDA DE CARGA 10 kg Total Comp | C88: No. 2 | D88: TOTAL COMP | E88: PSW-10KG 05500 | F88: 10k | G88: #VALUE! | I88: SE-CELCA-RL-10kg | J88: TOTAL COMP | K88: 44592 | O88: 1 | P88: =O88 -> 1 | Q88: =AJ88 -> 1 | R88: =AK88 -> 1 | S88: =AL88 -> 1 | T88: =AM88 -> 1 | AJ88: =P88-Z88+AE88+U88 -> 1 | AK88: =Q88-AA88+AF88+V88 -> 1 | AL88: =R88-AB88+AG88+W88 -> 1 | AM88: =S88-AC88+AH88+X88 -> 1 | AN88: =T88-AD88+AI88+Y88 -> 1 | AP88: =AN88 -> 1
A89: =+A88+1 -> 84 | B89: CELDA DE CARGA 20 KG MODELO SUP1-20KG | C89: No. 2 | D89: LOCOSC | E89: SUP-1-20KG | F89: 20 kg | J89: LOCOSC | K89: 45416 | M89: 59 | O89: 1 | P89: =O89 -> 1 | Q89: =AJ89 -> 1 | R89: =AK89 -> 1 | S89: =AL89 -> 1 | T89: =AM89 -> 1 | AJ89: =P89-Z89+AE89+U89 -> 1 | AK89: =Q89-AA89+AF89+V89 -> 1 | AL89: =R89-AB89+AG89+W89 -> 1 | AM89: =S89-AC89+AH89+X89 -> 1 | AN89: =T89-AD89+AI89+Y89 -> 1 | AP89: =AN89 -> 1
A90: =+A89+1 -> 85 | B90: CELDA DE CARGA 20K H8C-N5-20K-6YWB | C90: No. 2 | F90: 20 k | I90: SE-CELCA-20K | J90: LOCOSC | K90: 44592 | O90: 0 | P90: =O90 -> 0 | Q90: =AJ90 -> 0 | R90: =AK90 -> 0 | S90: =AL90 -> 0 | T90: =AM90 -> 0 | AJ90: =P90-Z90+AE90+U90 -> 0 | AK90: =Q90-AA90+AF90+V90 -> 0 | AL90: =R90-AB90+AG90+W90 -> 0 | AM90: =S90-AC90+AH90+X90 -> 0 | AN90: =T90-AD90+AI90+Y90 -> 0 | AP90: =AN90 -> 0
A91: =+A90+1 -> 86 | B91: CELDA DE CARGA 75 K LP7154 16mm DOBLE BRIDA CAMIONERO | C91: No. 2 | D91: SENSORTRONICS | E91: LP7154 | F91: 75 k | G91: #VALUE! | H91: 7500 | I91: SE7154-75klb-16m | J91: LOCOSC | K91: 45673 | L91: 240907-1 | M91: 129 | N91: 1-ACEROS DE GUATEMALA S:240407005//2 -SOEXSA NICARAGUA / IMSA CAMIONES | O91: 4 | P91: =O91 -> 4 | Q91: =AJ91 -> 3 | R91: =AK91 -> 1 | S91: =AL91 -> 16 | T91: =AM91 -> 16 | W91: 15 | Z91: 1 | AA91: 2 | AD91: 2 | AJ91: =P91-Z91+AE91+U91 -> 3 | AK91: =Q91-AA91+AF91+V91 -> 1 | AL91: =R91-AB91+AG91+W91 -> 16 | AM91: =S91-AC91+AH91+X91 -> 16 | AN91: =T91-AD91+AI91+Y91 -> 14 | AP91: =AN91 -> 14 | AQ91: 1968653618 | AR91: 251//259/317 | AS91: E:4572-AG//E:4592-SOEXSA
A92: =+A91+1 -> 87 | B92: CELDA DE CARGA BARRA ILE 150 K | C92: No. 2 | E92: ILE150 | F92: 150 kg | G92: #VALUE! | I92: SE-CELCA-150K | J92: LOCOSC | K92: 44592 | O92: 1 | P92: =O92 -> 1 | Q92: =AJ92 -> 1 | R92: =AK92 -> 1 | S92: =AL92 -> 1 | T92: =AM92 -> 1 | AJ92: =P92-Z92+AE92+U92 -> 1 | AK92: =Q92-AA92+AF92+V92 -> 1 | AL92: =R92-AB92+AG92+W92 -> 1 | AM92: =S92-AC92+AH92+X92 -> 1 | AN92: =T92-AD92+AI92+Y92 -> 1 | AP92: =AN92 -> 1
A93: =+A92+1 -> 88 | B93: CELDA DE CARGA BARRA 1 K (INCLUYE PATA) tecnipesa | C93: No. 2 | D93: BRECKNELL | E93: Tecnipesa | F93: 1 k | G93: #VALUE! | I93: SE-CELBAR-1 K | J93: BRECKNELL | K93: 44592 | O93: 2 | P93: =O93 -> 2 | Q93: =AJ93 -> 2 | R93: =AK93 -> 2 | S93: =AL93 -> 2 | T93: =AM93 -> 2 | AJ93: =P93-Z93+AE93+U93 -> 2 | AK93: =Q93-AA93+AF93+V93 -> 2 | AL93: =R93-AB93+AG93+W93 -> 2 | AM93: =S93-AC93+AH93+X93 -> 2 | AN93: =T93-AD93+AI93+Y93 -> 2 | AP93: =AN93 -> 2
A94: =+A93+1 -> 89 | B94: CELDA DE CARGA BARRA 10 K-SQB-10QHSS | C94: No. 2 | D94: BRECKNELL | E94: SQB-10QHSS | F94: 10 k | G94: #VALUE! | H94: 5200 | I94: SE-CELBAR-10K | J94: BRECKNELL | K94: 44592 | O94: 0 | P94: =O94 -> 0 | Q94: =AJ94 -> 0 | R94: =AK94 -> 0 | S94: =AL94 -> 0 | T94: =AM94 -> 0 | AJ94: =P94-Z94+AE94+U94 -> 0 | AK94: =Q94-AA94+AF94+V94 -> 0 | AL94: =R94-AB94+AG94+W94 -> 0 | AM94: =S94-AC94+AH94+X94 -> 0 | AN94: =T94-AD94+AI94+Y94 -> 0 | AP94: =AN94 -> 0
A95: =+A94+1 -> 90 | B95: CELDA DE CARGA BARRA 2KG | C95: No. 2 | D95: S/M | E95: HBM | F95: 2 kg | G95: #VALUE! | I95: SE-CELCA-2K | J95: LOCOSC | K95: 44592 | O95: 1 | P95: =O95 -> 1 | Q95: =AJ95 -> 1 | R95: =AK95 -> 1 | S95: =AL95 -> 1 | T95: =AM95 -> 1 | AJ95: =P95-Z95+AE95+U95 -> 1 | AK95: =Q95-AA95+AF95+V95 -> 1 | AL95: =R95-AB95+AG95+W95 -> 1 | AM95: =S95-AC95+AH95+X95 -> 1 | AN95: =T95-AD95+AI95+Y95 -> 1 | AP95: =AN95 -> 1
A96: =+A95+1 -> 91 | B96: BASCULA DE PISO PLATAFORMA /ABS ARMADAS DEMO | D96: BRECKNELL | E96: SE-LP7611 | F96: 600 x 0.5 kg | G96: #VALUE! | H96: 4500 | I96: SE-LP7611-DEMO | J96: LOCOSC | K96: 44592 | O96: 0 | P96: =O96 -> 0 | Q96: =AJ96 -> 0 | R96: =AK96 -> 0 | S96: =AL96 -> 0 | T96: =AM96 -> 0 | AJ96: =P96-Z96+AE96+U96 -> 0 | AK96: =Q96-AA96+AF96+V96 -> 0 | AL96: =R96-AB96+AG96+W96 -> 0 | AM96: =S96-AC96+AH96+X96 -> 0 | AN96: =T96-AD96+AI96+Y96 -> 0 | AP96: =AN96 -> 0
A97: =+A96+1 -> 92 | B97: CELDA DE CARGA BARRA 5 k 65016-005-NC-01F | C97: No. 2 | D97: SENSORTRONICS | E97: 65016-005-NC-01F | F97: 5 k | G97: #VALUE! | I97: SE-CELBAR-65061-5 | J97: BRECKNELL | K97: 44592 | O97: 0 | P97: =O97 -> 0 | Q97: =AJ97 -> 0 | R97: =AK97 -> 0 | S97: =AL97 -> 0 | T97: =AM97 -> 0 | AJ97: =P97-Z97+AE97+U97 -> 0 | AK97: =Q97-AA97+AF97+V97 -> 0 | AL97: =R97-AB97+AG97+W97 -> 0 | AM97: =S97-AC97+AH97+X97 -> 0 | AN97: =T97-AD97+AI97+Y97 -> 0 | AP97: =AN97 -> 0
A98: =+A97+1 -> 93 | B98: CELDA DE CARGA BARRA 5 K H8C-N5-5KSE-6YWB-SC-D27 ZEMIC | C98: No. 2 | D98: BRECKNELL | E98: H8C-N5-5KSE-6YWB-SC-D27 | F98: 5 k | G98: #VALUE! | I98: SE-CELBAR-5 K | J98: BRECKNELL | K98: 44592 | O98: 3 | P98: =O98 -> 3 | Q98: =AJ98 -> 3 | R98: =AK98 -> 3 | S98: =AL98 -> 3 | T98: =AM98 -> 3 | AJ98: =P98-Z98+AE98+U98 -> 3 | AK98: =Q98-AA98+AF98+V98 -> 3 | AL98: =R98-AB98+AG98+W98 -> 3 | AM98: =S98-AC98+AH98+X98 -> 3 | AN98: =T98-AD98+AI98+Y98 -> 3 | AP98: =AN98 -> 3
A99: =+A98+1 -> 94 | B99: CELDA DE CARGA BARRA 5 K PINTADA (USADAS) ZEMIC H8C-N5-5KSE-6YWB-SC-D2 | C99: No. 2 | D99: BRECKNELL | E99: H8C-N5-5KSE-6YWB-SC-D2 | F99: 5 k | G99: #VALUE! | I99: SE-CELBAR- 5 K U | J99: BRECKNELL | K99: 44592 | O99: 3 | P99: =O99 -> 3 | Q99: =AJ99 -> 3 | R99: =AK99 -> 3 | S99: =AL99 -> 3 | T99: =AM99 -> 3 | AJ99: =P99-Z99+AE99+U99 -> 3 | AK99: =Q99-AA99+AF99+V99 -> 3 | AL99: =R99-AB99+AG99+W99 -> 3 | AM99: =S99-AC99+AH99+X99 -> 3 | AN99: =T99-AD99+AI99+Y99 -> 3 | AP99: =AN99 -> 3
A100: =+A99+1 -> 95 | B100: CELDA DE CARGA BARRA 50 K 65061-050E-B1-00F | C100: No. 2 | D100: SENSORTRONICS | E100: 65061-050E-B1-00F | F100: 50 k | G100: #VALUE! | H100: Q | I100: SE-CELBAR-65061-50 | J100: VPG | K100: 45505 | L100: 2410004753 | M100: 17 | O100: 2 | P100: =O100 -> 2 | Q100: =AJ100 -> 2 | R100: =AK100 -> 2 | S100: =AL100 -> 2 | T100: =AM100 -> 2 | AJ100: =P100-Z100+AE100+U100 -> 2 | AK100: =Q100-AA100+AF100+V100 -> 2 | AL100: =R100-AB100+AG100+W100 -> 2 | AM100: =S100-AC100+AH100+X100 -> 2 | AN100: =T100-AD100+AI100+Y100 -> 2 | AP100: =AN100 -> 2
A101: =+A100+1 -> 96 | B101: CELDA DE CARGA BARRA 40 K 65061-040E-B1-01F | C101: No. 2 | D101: SENSORTRONICS | E101: 65061-040E-BI-01F | F101: 40 k | G101: #VALUE! | J101: VPG | K101: 45505 | L101: 2410004752 | M101: 17 | O101: 0 | P101: =O101 -> 0 | Q101: =AJ101 -> 0 | R101: =AK101 -> 0 | S101: =AL101 -> 0 | T101: =AM101 -> 0 | AJ101: =P101-Z101+AE101+U101 -> 0 | AK101: =Q101-AA101+AF101+V101 -> 0 | AL101: =R101-AB101+AG101+W101 -> 0 | AM101: =S101-AC101+AH101+X101 -> 0 | AN101: =T101-AD101+AI101+Y101 -> 0 | AP101: =AN101 -> 0
...

Sheet EQUIPO FEBRERO 2025  1
B1: SOLUCIONES EXACTAS, S.A. | AR1: Codigo: FO-SE-053 | AV1: Codigo: FO-SE-053
B3: LISTADO INVENTARIO BODEGAS FEBRERO | AK3: FEBRERO | AR3: Versión: 02 | AV3: Versión: 02
A4: No. | B4: PRODUCTO | C4: No. BODEGA | D4: MARCA | E4: MODELO | F4: CAPACIDAD | G4: IMAGEN | H4: PRECIO | I4: CODIGO INTERNO | J4: PROVEEDOR | K4: FECHA INGRESO BODEGA | L4: FACTURA No. PROVEEDOR | M4: BOLETA INGRESO BODEGA | N4: OBSERVACION | O4: VIENE MES ANTERIOR | P4: EXISTENCIA INICIO SEMANA | U4: INGRESO POR IMPORTACION O COMPRA | Z4: DESCARGA Y/O SALIDA | AE4: DEVOLUCIONES | AJ4: INICIO DE MES | AK4: EXISTENCIA POR SEMANA | AP4: DEMO | AQ4: TOTAL EXISTENCIA MENSUAL | AR4: FACTURA VENTA | AS4: BOLETA DE SALIDA | AT4: ENVIO | AU4: FIRMA ULTIMO INVENTARIO | AV4: FECHA ULTIMA REVISION
P5: 1 | Q5: 2 | R5: 3 | S5: 4 | T5: 5 | U5: 1 | V5: 2 | W5: 3 | X5: 4 | Y5: 5 | Z5: 1 | AA5: 2 | AB5: 3 | AC5: 4 | AD5: 5 | AE5: 1 | AF5: 2 | AG5: 3 | AH5: 4 | AI5: 5 | AK5: 1 | AL5: 2 | AM5: 3 | AN5: 4 | AO5: 5
A6: 1 | B6: ADAPTADOR PARA INDICADOR 9V1.2A MODELO: KEERDA | C6: No. 2 | D6: KEERDA | E6: DZ012ELL090120U | F6: 9V | G6: #VALUE! | H6: 395 | I6: SE-ADAT9V | J6: SIZEIN | K6: 45666 | L6: LK24112701 | M6: 118 | N6: ctl/ALCSA/PANTALEON SE AGREGO 1 DEBIDO EN EL CUADRE FISICO CORREPONDE DE 43 | O6: ='EQUIPO ENERO 2025'!AP6 -> 47 | P6: =O6 -> 47 | Q6: =AK6 -> 45 | R6: =AL6 -> 44 | S6: =AM6 -> 43 | T6: =AN6 -> 43 | Z6: 6 | AA6: 10 | AB6: 5 | AC6: 1 | AE6: 4 | AF6: 9 | AG6: 4 | AH6: 1 | AJ6: ='EQUIPO ENERO 2025'!AP6 -> 47 | AK6: =P6-Z6+AE6+U6 -> 45 | AL6: =Q6-AA6+AF6+V6 -> 44 | AM6: =R6-AB6+AG6+W6 -> 43 | AN6: =S6-AC6+AH6+X6 -> 43 | AO6: =T6-AD6+AI6+Y6 -> 43 | AQ6: =AO6 -> 43 | AS6: 320/327/335/338/332
A7: =A6+1 -> 2 | B7: ADAPTADOR GENERICO 9V 600 mA | C7: No.2 | D7: Byp | F7: 9v | K7: 45712 | M7: 162 | O7: ='EQUIPO ENERO 2025'!AP7 -> 0 | P7: =O7 -> 0 | Q7: =AK7 -> 0 | R7: =AL7 -> 0 | S7: =AM7 -> 10 | T7: =AN7 -> 10 | W7: 10 | AK7: =P7-Z7+AE7+U7 -> 0 | AL7: =Q7-AA7+AF7+V7 -> 0 | AM7: =R7-AB7+AG7+W7 -> 10 | AN7: =S7-AC7+AH7+X7 -> 10 | AO7: =T7-AD7+AI7+Y7 -> 10 | AQ7: =AO7 -> 10
A8: =A7+1 -> 3 | B8: ADAPTADORES GENERICOS 5 V 1 AMP AC/DC | C8: No. 2 | D8: BRECKNELL | E8: S/M | G8: #VALUE! | I8: SE-ADAP-1 AMP | J8: BRECKNELL | K8: 44592 | O8: ='EQUIPO ENERO 2025'!AP8 -> 2 | P8: =O8 -> 2 | Q8: =AK8 -> 2 | R8: =AL8 -> 2 | S8: =AM8 -> 2 | T8: =AN8 -> 2 | AJ8: ='EQUIPO ENERO 2025'!AP8 -> 2 | AK8: =P8-Z8+AE8+U8 -> 2 | AL8: =Q8-AA8+AF8+V8 -> 2 | AM8: =R8-AB8+AG8+W8 -> 2 | AN8: =S8-AC8+AH8+X8 -> 2 | AO8: =T8-AD8+AI8+Y8 -> 2 | AQ8: =AO8 -> 2
A9: =A8+1 -> 4 | B9: ADAPTADORES SBI 505 ORIGINAL AWT05-505896 | C9: No. 2 | D9: AVERY WEIGH TRONIX | E9: AWT05-505896 | G9: #VALUE! | H9: 550 | I9: SE-ADAP-SBI505 | J9: AVERY WEIGH TRONIX | K9: 44592 | O9: ='EQUIPO ENERO 2025'!AP9 -> 8 | P9: =O9 -> 8 | Q9: =AK9 -> 8 | R9: =AL9 -> 8 | S9: =AM9 -> 8 | T9: =AN9 -> 8 | AJ9: ='EQUIPO ENERO 2025'!AP9 -> 8 | AK9: =P9-Z9+AE9+U9 -> 8 | AL9: =Q9-AA9+AF9+V9 -> 8 | AM9: =R9-AB9+AG9+W9 -> 8 | AN9: =S9-AC9+AH9+X9 -> 8 | AO9: =T9-AD9+AI9+Y9 -> 8 | AQ9: =AO9 -> 8
A10: =A9+1 -> 5 | B10: ADAPTADOR BI 12T | C10: No. 2 | D10: BRECKNELL | E10: BI 12T | F10: 12t | G10: #VALUE! | I10: SE-ADAP-BI-12T | J10: BRECKNELL | K10: 44592 | O10: ='EQUIPO ENERO 2025'!AP10 -> 1 | P10: =O10 -> 1 | Q10: =AK10 -> 1 | R10: =AL10 -> 1 | S10: =AM10 -> 1 | T10: =AN10 -> 1 | AJ10: ='EQUIPO ENERO 2025'!AP10 -> 1 | AK10: =P10-Z10+AE10+U10 -> 1 | AL10: =Q10-AA10+AF10+V10 -> 1 | AM10: =R10-AB10+AG10+W10 -> 1 | AN10: =S10-AC10+AH10+X10 -> 1 | AO10: =T10-AD10+AI10+Y10 -> 1 | AQ10: =AO10 -> 1
A11: =A10+1 -> 6 | B11: ADAPTADOR DE MODULOS INALAMBRICOS SE-7660 | C11: No.2 | E11: SE-ADAPT-7660 | G11: #VALUE! | J11: LOCOSC | K11: 45464 | M11: 87 | O11: ='EQUIPO ENERO 2025'!AP11 -> 2 | P11: =O11 -> 2 | Q11: =AK11 -> 2 | R11: =AL11 -> 2 | S11: =AM11 -> 2 | T11: =AN11 -> 2 | AJ11: ='EQUIPO ENERO 2025'!AP11 -> 2 | AK11: =P11-Z11+AE11+U11 -> 2 | AL11: =Q11-AA11+AF11+V11 -> 2 | AM11: =R11-AB11+AG11+W11 -> 2 | AN11: =S11-AC11+AH11+X11 -> 2 | AO11: =T11-AD11+AI11+Y11 -> 2 | AQ11: =AO11 -> 2
A12: =A11+1 -> 7 | B12: ADAPTADOR DE CORRIENTE DE INDICADOR SE7517/ REPARADO DE CABLE | C12: NO.2 | D12: KEERDA | E12: DZ007AHL050100U | F12: 5.0V/1.0Ah | I12: SE-DZ007 | J12: LOCOSC | M12: 113 | O12: ='EQUIPO ENERO 2025'!AP12 -> 1 | P12: =O12 -> 1 | Q12: =AK12 -> 1 | R12: =AL12 -> 1 | S12: =AM12 -> 1 | T12: =AN12 -> 1 | AJ12: ='EQUIPO ENERO 2025'!AP12 -> 1 | AK12: =P12-Z12+AE12+U12 -> 1 | AL12: =Q12-AA12+AF12+V12 -> 1 | AM12: =R12-AB12+AG12+W12 -> 1 | AN12: =S12-AC12+AH12+X12 -> 1 | AO12: =T12-AD12+AI12+Y12 -> 1 | AQ12: =AO12 -> 1
A13: =A12+1 -> 8 | B13: ADAPTADORES DE CORRIENTE PARA MODULOS INALAMBRICOS SE-7519A | C13: NO.2 | D13: S/M | E13: ZF120A-0421000 | F13: 4.2V/10A | G13: #VALUE! | I13: SE-ADAP-A | J13: LOCOSC | K13: 45582 | M13: 81 | O13: ='EQUIPO ENERO 2025'!AP13 -> 2 | P13: =O13 -> 2 | Q13: =AK13 -> 2 | R13: =AL13 -> 2 | S13: =AM13 -> 2 | T13: =AN13 -> 2 | AJ13: ='EQUIPO ENERO 2025'!AP13 -> 2 | AK13: =P13-Z13+AE13+U13 -> 2 | AL13: =Q13-AA13+AF13+V13 -> 2 | AM13: =R13-AB13+AG13+W13 -> 2 | AN13: =S13-AC13+AH13+X13 -> 2 | AO13: =T13-AD13+AI13+Y13 -> 2 | AQ13: =AO13 -> 2
A14: =A13+1 -> 9 | B14: ARMARIOS ELECTRICOS ST4-420 | C14: No. 2 | D14: BRECKNELL | E14: ST4-420 | G14: #VALUE! | I14: SE-ARMAELEC | J14: BRECKNELL | K14: 44592 | O14: ='EQUIPO ENERO 2025'!AP14 -> 3 | P14: =O14 -> 3 | Q14: =AK14 -> 3 | R14: =AL14 -> 3 | S14: =AM14 -> 3 | T14: =AN14 -> 3 | AJ14: ='EQUIPO ENERO 2025'!AP14 -> 3 | AK14: =P14-Z14+AE14+U14 -> 3 | AL14: =Q14-AA14+AF14+V14 -> 3 | AM14: =R14-AB14+AG14+W14 -> 3 | AN14: =S14-AC14+AH14+X14 -> 3 | AO14: =T14-AD14+AI14+Y14 -> 3 | AQ14: =AO14 -> 3
A15: =A14+1 -> 10 | B15: ARGOLLAS PARA BÁSCULAS PESA EJES | C15: NO.2 | D15: S/M | E15: M-20 | F15: S/C | G15: #VALUE! | I15: SE-ARG-PPEJES | J15: LOCOSC | K15: 45673 | L15: 240907-1 | M15: 131 | O15: ='EQUIPO ENERO 2025'!AP15 -> 0 | P15: =O15 -> 0 | Q15: =AK15 -> 0 | R15: =AL15 -> 0 | S15: =AM15 -> 0 | T15: =AN15 -> 0 | AJ15: ='EQUIPO ENERO 2025'!AP15 -> 0 | AK15: =P15-Z15+AE15+U15 -> 0 | AL15: =Q15-AA15+AF15+V15 -> 0 | AM15: =R15-AB15+AG15+W15 -> 0 | AN15: =S15-AC15+AH15+X15 -> 0 | AO15: =T15-AD15+AI15+Y15 -> 0 | AQ15: =AO15 -> 0
A16: =A15+1 -> 11 | B16: BALANZA DE BOLSILLO CAPACIDAD DE 200x0.01g | C16: No. 1 | E16: HY-YH-J100120 | F16: 2 000 x 0.01 g | G16: #VALUE! | H16: 150 | I16: SE-FAB-GUA | K16: 44592 | O16: ='EQUIPO ENERO 2025'!AP16 -> 5 | P16: =O16 -> 5 | Q16: =AK16 -> 5 | R16: =AL16 -> 5 | S16: =AM16 -> 5 | T16: =AN16 -> 5 | AJ16: ='EQUIPO ENERO 2025'!AP16 -> 5 | AK16: =P16-Z16+AE16+U16 -> 5 | AL16: =Q16-AA16+AF16+V16 -> 5 | AM16: =R16-AB16+AG16+W16 -> 5 | AN16: =S16-AC16+AH16+X16 -> 5 | AO16: =T16-AD16+AI16+Y16 -> 5 | AQ16: =AO16 -> 5
A17: =A16+1 -> 12 | B17: BALANZA DE LABORATORIO 1 000 x0.01g | C17: N/A | D17: ELECTRONIC BALANCE | E17: SE10002K | F17: 1 000 x 0.01 g | G17: #VALUE! | H17: 9180 | I17: SE-WTB1002K | J17: LOCOSC | K17: 45316 | M17: 15 | O17: ='EQUIPO ENERO 2025'!AP17 -> 0 | P17: =O17 -> 0 | Q17: =AK17 -> 0 | R17: =AL17 -> 0 | S17: =AM17 -> 0 | T17: =AN17 -> 0 | AJ17: ='EQUIPO ENERO 2025'!AP17 -> 0 | AK17: =P17-Z17+AE17+U17 -> 0 | AL17: =Q17-AA17+AF17+V17 -> 0 | AM17: =R17-AB17+AG17+W17 -> 0 | AN17: =S17-AC17+AH17+X17 -> 0 | AO17: =T17-AD17+AI17+Y17 -> 0 | AQ17: =AO17 -> 0
A18: =A17+1 -> 13 | B18: BALANZA DE LABORATORIO 10000x0.1g | C18: No. 1 | D18: ELECTRONIC BALANCE | E18: SE-WT100001X | F18: 1 000 x 0.1 g | G18: #VALUE! | H18: 4600 | I18: SE-WT100001X | J18: LOCOSC | K18: 45216 | L18: 2015 | M18: 451 | O18: ='EQUIPO ENERO 2025'!AP18 -> 0 | P18: =O18 -> 0 | Q18: =AK18 -> 0 | R18: =AL18 -> 0 | S18: =AM18 -> 0 | T18: =AN18 -> 0 | AJ18: ='EQUIPO ENERO 2025'!AP18 -> 0 | AK18: =P18-Z18+AE18+U18 -> 0 | AL18: =Q18-AA18+AF18+V18 -> 0 | AM18: =R18-AB18+AG18+W18 -> 0 | AN18: =S18-AC18+AH18+X18 -> 0 | AO18: =T18-AD18+AI18+Y18 -> 0 | AQ18: =AO18 -> 0
A19: =A18+1 -> 14 | B19: BALANZA DE LABORATORIO 1500g x 0.5g | C19: N/A | D19: ELECTRONIC BALANCE | E19: SE-WT15002KF | F19: 1 500 x 0.05 kg | G19: #VALUE! | H19: 2800 | I19: SE-WT15002KF-5 | J19: LOCOSC | K19: 45107 | L19: LP230224-1 | M19: 393 | O19: ='EQUIPO ENERO 2025'!AP19 -> 5 | P19: =O19 -> 5 | Q19: =AK19 -> 5 | R19: =AL19 -> 5 | S19: =AM19 -> 5 | T19: =AN19 -> 5 | AJ19: ='EQUIPO ENERO 2025'!AP19 -> 5 | AK19: =P19-Z19+AE19+U19 -> 5 | AL19: =Q19-AA19+AF19+V19 -> 5 | AM19: =R19-AB19+AG19+W19 -> 5 | AN19: =S19-AC19+AH19+X19 -> 5 | AO19: =T19-AD19+AI19+Y19 -> 5 | AQ19: =AO19 -> 5
A20: =A19+1 -> 15 | B20: BALANZA DE LABORATORIO CAPACIDAD 15 kg x 0.1g | C20: No. 1 | D20: ELECTRONIC BALANCE | E20: SE150001XD | F20: 15 kg x 0.1 g | G20: #VALUE! | H20: 9180 | I20: SE-WT150001XD | J20: LOCOSC | K20: 45316 | M20: 15 | O20: ='EQUIPO ENERO 2025'!AP20 -> 0 | P20: =O20 -> 0 | Q20: =AK20 -> 0 | R20: =AL20 -> 0 | S20: =AM20 -> 0 | T20: =AN20 -> 0 | AJ20: ='EQUIPO ENERO 2025'!AP20 -> 0 | AK20: =P20-Z20+AE20+U20 -> 0 | AL20: =Q20-AA20+AF20+V20 -> 0 | AM20: =R20-AB20+AG20+W20 -> 0 | AN20: =S20-AC20+AH20+X20 -> 0 | AO20: =T20-AD20+AI20+Y20 -> 0 | AQ20: =AO20 -> 0
A21: =A20+1 -> 16 | B21: BALANZA DE LABORATORIO CAPACIDAD 300 g x 1 mg | C21: N/A | D21: ELECTRONIC BALANCE | E21: SE-3003GH | F21: 300 g x 1 mg | G21: #VALUE! | H21: 36300 | I21: SE3003GH | J21: LOCOSC | K21: 45299 | M21: 6 | O21: ='EQUIPO ENERO 2025'!AP21 -> 0 | P21: =O21 -> 0 | Q21: =AK21 -> 0 | R21: =AL21 -> 0 | S21: =AM21 -> 0 | T21: =AN21 -> 0 | AJ21: ='EQUIPO ENERO 2025'!AP21 -> 0 | AK21: =P21-Z21+AE21+U21 -> 0 | AL21: =Q21-AA21+AF21+V21 -> 0 | AM21: =R21-AB21+AG21+W21 -> 0 | AN21: =S21-AC21+AH21+X21 -> 0 | AO21: =T21-AD21+AI21+Y21 -> 0 | AQ21: =AO21 -> 0
A22: =A21+1 -> 17 | B22: BALANZA ANALITICA CAPACIDAD DE 5 000g x 0.01 g | C22: N/A | D22: ELECTRONIC BALANCE | E22: SE-5 0002CF | F22: 5 000 x 0.01 g | G22: #VALUE! | I22: SE50002CF | J22: LOCOSC | K22: 45336 | L22: 669885E9 | M22: 37 | O22: ='EQUIPO ENERO 2025'!AP22 -> 0 | P22: =O22 -> 0 | Q22: =AK22 -> 0 | R22: =AL22 -> 0 | S22: =AM22 -> 0 | T22: =AN22 -> 0 | AJ22: ='EQUIPO ENERO 2025'!AP22 -> 0 | AK22: =P22-Z22+AE22+U22 -> 0 | AL22: =Q22-AA22+AF22+V22 -> 0 | AM22: =R22-AB22+AG22+W22 -> 0 | AN22: =S22-AC22+AH22+X22 -> 0 | AO22: =T22-AD22+AI22+Y22 -> 0 | AQ22: =AO22 -> 0
A23: =A22+1 -> 18 | B23: BALANZA ANALITICA CAPACIDAD DE 1 000 g x 20 mg | C23: N/A | D23: ELECTRONIC BALANCE | E23: SE-10003N | F23: 1 000 g x 20 mg | G23: #VALUE! | I23: SE10003N | J23: LOCOSC | K23: 45336 | L23: 669885E9 | M23: 37 | O23: ='EQUIPO ENERO 2025'!AP23 -> 0 | P23: =O23 -> 0 | Q23: =AK23 -> 0 | R23: =AL23 -> 0 | S23: =AM23 -> 0 | T23: =AN23 -> 0 | AJ23: ='EQUIPO ENERO 2025'!AP23 -> 0 | AK23: =P23-Z23+AE23+U23 -> 0 | AL23: =Q23-AA23+AF23+V23 -> 0 | AM23: =R23-AB23+AG23+W23 -> 0 | AN23: =S23-AC23+AH23+X23 -> 0 | AO23: =T23-AD23+AI23+Y23 -> 0 | AQ23: =AO23 -> 0
A24: =A23+1 -> 19 | B24: BALANZA ANALITICA CAPACIDAD DE 210 g x 10 mg | C24: N/A | D24: ELECTRONIC BALANCE | E24: SE-2085A | F24: 210 g x 10 mg | G24: #VALUE! | I24: SE2085A | J24: LOCOSC | K24: 45336 | L24: 669885E9 | M24: 38 | O24: ='EQUIPO ENERO 2025'!AP24 -> 0 | P24: =O24 -> 0 | Q24: =AK24 -> 0 | R24: =AL24 -> 0 | S24: =AM24 -> 0 | T24: =AN24 -> 0 | AJ24: ='EQUIPO ENERO 2025'!AP24 -> 0 | AK24: =P24-Z24+AE24+U24 -> 0 | AL24: =Q24-AA24+AF24+V24 -> 0 | AM24: =R24-AB24+AG24+W24 -> 0 | AN24: =S24-AC24+AH24+X24 -> 0 | AO24: =T24-AD24+AI24+Y24 -> 0 | AQ24: =AO24 -> 0
A25: =A24+1 -> 20 | B25: BALANZA DE LABORATORIO CAPACIDAD 420 x 0.001g LUNA | C25: No.1 | E25: SE-LPB423E | F25: 420 x 0.001 g | G25: #VALUE! | I25: LPB423E | J25: ADAM | K25: 45454 | L25: 34687-035292 | M25: 76 | O25: ='EQUIPO ENERO 2025'!AP25 -> 0 | P25: =O25 -> 0 | Q25: =AK25 -> 0 | R25: =AL25 -> 0 | S25: =AM25 -> 0 | T25: =AN25 -> 0 | AJ25: ='EQUIPO ENERO 2025'!AP25 -> 0 | AK25: =P25-Z25+AE25+U25 -> 0 | AL25: =Q25-AA25+AF25+V25 -> 0 | AM25: =R25-AB25+AG25+W25 -> 0 | AN25: =S25-AC25+AH25+X25 -> 0 | AO25: =T25-AD25+AI25+Y25 -> 0 | AQ25: =AO25 -> 0
A26: =A25+1 -> 21 | B26: BÁSCULA DE MESA | C26: No. 1 | D26: BRECKNELL | E26: SE-7680W | F26: 3 x 0.005 kg | G26: #VALUE! | H26: 2800 | I26: SE-LP7680-3Kg | J26: LOCOSC | K26: 45574 | L26: LP3211240 | M26: 71 | O26: ='EQUIPO ENERO 2025'!AP26 -> 8 | P26: =O26 -> 8 | Q26: =AK26 -> 8 | R26: =AL26 -> 8 | S26: =AM26 -> 8 | T26: =AN26 -> 8 | AJ26: ='EQUIPO ENERO 2025'!AP26 -> 8 | AK26: =P26-Z26+AE26+U26 -> 8 | AL26: =Q26-AA26+AF26+V26 -> 8 | AM26: =R26-AB26+AG26+W26 -> 8 | AN26: =S26-AC26+AH26+X26 -> 8 | AO26: =T26-AD26+AI26+Y26 -> 8 | AQ26: =AO26 -> 8
A27: =A26+1 -> 22 | B27: BÁSCULA DE MESA | C27: No. 1 | D27: BRECKNELL | E27: SE-7680W | F27: 6 x 0.001 kg | G27: #VALUE! | H27: 2800 | I27: SE-LP7680-6Kg | J27: LOCOSC | K27: 45574 | L27: LP3211240 | M27: 71 | O27: ='EQUIPO ENERO 2025'!AP27 -> 10 | P27: =O27 -> 10 | Q27: =AK27 -> 10 | R27: =AL27 -> 10 | S27: =AM27 -> 10 | T27: =AN27 -> 10 | AJ27: ='EQUIPO ENERO 2025'!AP27 -> 10 | AK27: =P27-Z27+AE27+U27 -> 10 | AL27: =Q27-AA27+AF27+V27 -> 10 | AM27: =R27-AB27+AG27+W27 -> 10 | AN27: =S27-AC27+AH27+X27 -> 10 | AO27: =T27-AD27+AI27+Y27 -> 10 | AQ27: =AO27 -> 10
A28: =A27+1 -> 23 | B28: BÁSCULA DE MESA | C28: No. 1 | D28: BRECKNELL | E28: SE-7680W | F28: 15 x 0.002 kg | G28: #VALUE! | H28: 2800 | I28: SE-LP7680-15Kg | J28: LOCOSC | K28: 45574 | L28: LP3211240 | M28: 71 | O28: ='EQUIPO ENERO 2025'!AP28 -> 6 | P28: =O28 -> 6 | Q28: =AK28 -> 6 | R28: =AL28 -> 6 | S28: =AM28 -> 6 | T28: =AN28 -> 6 | AJ28: ='EQUIPO ENERO 2025'!AP28 -> 6 | AK28: =P28-Z28+AE28+U28 -> 6 | AL28: =Q28-AA28+AF28+V28 -> 6 | AM28: =R28-AB28+AG28+W28 -> 6 | AN28: =S28-AC28+AH28+X28 -> 6 | AO28: =T28-AD28+AI28+Y28 -> 6 | AQ28: =AO28 -> 6 | AS28: 337/PAPYS
A29: =A28+1 -> 24 | B29: BASCULA DE MESA MODELO SE-7680W | C29: No. 1 | D29: BRECKNELL | E29: SE-7680W | F29: 30 x 0.005 kg | G29: #VALUE! | H29: 3000 | I29: SE-LP7680-30kg | J29: LOCOSC | K29: 45107 | L29: LP230224-1 | M29: 390 | O29: ='EQUIPO ENERO 2025'!AP29 -> 5 | P29: =O29 -> 5 | Q29: =AK29 -> 5 | R29: =AL29 -> 5 | S29: =AM29 -> 5 | T29: =AN29 -> 5 | AJ29: ='EQUIPO ENERO 2025'!AP29 -> 5 | AK29: =P29-Z29+AE29+U29 -> 5 | AL29: =Q29-AA29+AF29+V29 -> 5 | AM29: =R29-AB29+AG29+W29 -> 5 | AN29: =S29-AC29+AH29+X29 -> 5 | AO29: =T29-AD29+AI29+Y29 -> 5 | AQ29: =AO29 -> 5
A30: =A29+1 -> 25 | B30: BALANZA ELECTRONIC BALANCE MODELO SE-2003CH DE 2000gx1mg | C30: N/A | D30: ELECTRONIC BALANCE | E30: SE-2003CH | F30: 200 x 1 mg | G30: #VALUE! | H30: 6300 | I30: SE-2003CH | J30: LOCOSC | K30: 45139 | L30: 781781092133 | M30: 419 | O30: ='EQUIPO ENERO 2025'!AP30 -> 0 | P30: =O30 -> 0 | Q30: =AK30 -> 0 | R30: =AL30 -> 0 | S30: =AM30 -> 0 | T30: =AN30 -> 0 | AJ30: ='EQUIPO ENERO 2025'!AP30 -> 0 | AK30: =P30-Z30+AE30+U30 -> 0 | AL30: =Q30-AA30+AF30+V30 -> 0 | AM30: =R30-AB30+AG30+W30 -> 0 | AN30: =S30-AC30+AH30+X30 -> 0 | AO30: =T30-AD30+AI30+Y30 -> 0 | AQ30: =AO30 -> 0
A31: =A30+1 -> 26 | B31: BASES DE CELDA DE CARGA PARA CELDAS DE ACEROS DE GUATEMALA | C31: NO. 2 | D31: S/M | E31: S/M | G31: #VALUE! | K31: 45568 | M31: 62 | O31: ='EQUIPO ENERO 2025'!AP31 -> 2 | P31: =O31 -> 2 | Q31: =AK31 -> 2 | R31: =AL31 -> 2 | S31: =AM31 -> 2 | T31: =AN31 -> 2 | AJ31: ='EQUIPO ENERO 2025'!AP31 -> 2 | AK31: =P31-Z31+AE31+U31 -> 2 | AL31: =Q31-AA31+AF31+V31 -> 2 | AM31: =R31-AB31+AG31+W31 -> 2 | AN31: =S31-AC31+AH31+X31 -> 2 | AO31: =T31-AD31+AI31+Y31 -> 2 | AQ31: =AO31 -> 2
A32: =A31+1 -> 27 | B32: BASCULA COLGANTE CAPACIDAD 5 t LP7650G | C32: NO.2 | D32: BRECKNELL | E32: SE-7650 | F32: 5 T | G32: #VALUE! | H32: 9500 | I32: SE-LP7650G-5T | J32: SIZEN | K32: 45666 | L32: LK24112701 | M32: 117 | O32: ='EQUIPO ENERO 2025'!AP32 -> 1 | P32: =O32 -> 1 | Q32: =AK32 -> 1 | R32: =AL32 -> 1 | S32: =AM32 -> 1 | T32: =AN32 -> 1 | AJ32: ='EQUIPO ENERO 2025'!AP32 -> 1 | AK32: =P32-Z32+AE32+U32 -> 1 | AL32: =Q32-AA32+AF32+V32 -> 1 | AM32: =R32-AB32+AG32+W32 -> 1 | AN32: =S32-AC32+AH32+X32 -> 1 | AO32: =T32-AD32+AI32+Y32 -> 1 | AQ32: =AO32 -> 1
A33: =A32+1 -> 28 | B33: BASCULA COLGANTE CAPACIDAD 10 t LP7650G | C33: No. 2 | D33: BRECKNELL | E33: SE-7650 | F33: 10 t | G33: #VALUE! | H33: Q16,800.00 Consultar primero | I33: SE-LP7650G-10T | J33: LOCOSC | K33: 45107 | L33: LP230224-1 | M33: 393 | O33: ='EQUIPO ENERO 2025'!AP33 -> 1 | P33: =O33 -> 1 | Q33: =AK33 -> 1 | R33: =AL33 -> 1 | S33: =AM33 -> 1 | T33: =AN33 -> 1 | AJ33: ='EQUIPO ENERO 2025'!AP33 -> 1 | AK33: =P33-Z33+AE33+U33 -> 1 | AL33: =Q33-AA33+AF33+V33 -> 1 | AM33: =R33-AB33+AG33+W33 -> 1 | AN33: =S33-AC33+AH33+X33 -> 1 | AO33: =T33-AD33+AI33+Y33 -> 1 | AQ33: =AO33 -> 1
A34: =A33+1 -> 29 | B34: BASCULA COLGANTE CAPACIDAD 300kg LP7652G | C34: No. 1 | D34: BRECKNELL | E34: SE-7652 | F34: 300 x 0.1 kg | G34: #VALUE! | H34: 650 | I34: SE-COLG-LP7652G | J34: LOCOSC | K34: 45107 | L34: LP230224-1 | M34: 389 | O34: ='EQUIPO ENERO 2025'!AP34 -> 11 | P34: =O34 -> 11 | Q34: =AK34 -> 11 | R34: =AL34 -> 11 | S34: =AM34 -> 11 | T34: =AN34 -> 11 | AJ34: ='EQUIPO ENERO 2025'!AP34 -> 11 | AK34: =P34-Z34+AE34+U34 -> 11 | AL34: =Q34-AA34+AF34+V34 -> 11 | AM34: =R34-AB34+AG34+W34 -> 11 | AN34: =S34-AC34+AH34+X34 -> 11 | AO34: =T34-AD34+AI34+Y34 -> 11 | AQ34: =AO34 -> 11
A35: =A34+1 -> 30 | B35: BASCULA COLGANTE PANTALLA LED DE 5 DIGITOS | C35: No. 1 | D35: BRECKNELL | E35: SE-7561 | F35: 300 x 0.1 kg | G35: #VALUE! | H35: 1800 | I35: SE-LP7561E | J35: LOCOSC | K35: 44592 | O35: ='EQUIPO ENERO 2025'!AP35 -> 6 | P35: =O35 -> 6 | Q35: =AK35 -> 6 | R35: =AL35 -> 6 | S35: =AM35 -> 6 | T35: =AN35 -> 6 | AJ35: ='EQUIPO ENERO 2025'!AP35 -> 6 | AK35: =P35-Z35+AE35+U35 -> 6 | AL35: =Q35-AA35+AF35+V35 -> 6 | AM35: =R35-AB35+AG35+W35 -> 6 | AN35: =S35-AC35+AH35+X35 -> 6 | AO35: =T35-AD35+AI35+Y35 -> 6 | AQ35: =AO35 -> 6
A36: =A35+1 -> 31 | B36: BASCULA DE MESA CAPACIDAD 30kgx1g | C36: No. 1 | D36: ELECTRONIC BALANCE | E36: SE-WT300001X | F36: 30 kg x 1 g | G36: #VALUE! | H36: 3400 | I36: SE-WT300001X | J36: LOCOSC | K36: 45107 | L36: LP230224-1 | M36: 393 | O36: ='EQUIPO ENERO 2025'!AP36 -> 4 | P36: =O36 -> 4 | Q36: =AK36 -> 4 | R36: =AL36 -> 4 | S36: =AM36 -> 4 | T36: =AN36 -> 4 | AJ36: ='EQUIPO ENERO 2025'!AP36 -> 4 | AK36: =P36-Z36+AE36+U36 -> 4 | AL36: =Q36-AA36+AF36+V36 -> 4 | AM36: =R36-AB36+AG36+W36 -> 4 | AN36: =S36-AC36+AH36+X36 -> 4 | AO36: =T36-AD36+AI36+Y36 -> 4 | AQ36: =AO36 -> 4
A37: =A36+1 -> 32 | B37: BASCULA DE MESA MODELO SE-Y2-208 CAPACIDAD 40kg X 5g | C37: No. 1 | D37: TECNO SCALE | E37: SE-Y2-208 | F37: 40 kg x 5 g | G37: #VALUE! | H37: 550 | I37: SE-Y2-208 | J37: LOCOSC | K37: 45328 | L37: LP230224-1 | M37: 32 | N37: AUTORIZADO POR WILLIAM SÁNCHEZ | O37: ='EQUIPO ENERO 2025'!AP37 -> 14 | P37: =O37 -> 14 | Q37: =AK37 -> 12 | R37: =AL37 -> 12 | S37: =AM37 -> 12 | T37: =AN37 -> 12 | Z37: 2 | AJ37: ='EQUIPO ENERO 2025'!AP37 -> 14 | AK37: =P37-Z37+AE37+U37 -> 12 | AL37: =Q37-AA37+AF37+V37 -> 12 | AM37: =R37-AB37+AG37+W37 -> 12 | AN37: =S37-AC37+AH37+X37 -> 12 | AO37: =T37-AD37+AI37+Y37 -> 12 | AQ37: =AO37 -> 12 | AR37: NO TIENE FUE CORTESIA | AS37: 319/ 320/COPASA
A38: =A37+1 -> 33 | B38: BASCULA DE PISO ACERO INOXIDABLE CAPACIDAD 150kg DE 40X50 | C38: No. 1 | D38: BRECKNELL | E38: SE-7610W | F38: 150 x 0.02 kg | G38: #VALUE! | H38: 7500 | I38: SE-7510W-150kg | J38: LOCOSC | K38: 45107 | L38: LP230224-1 | M38: 392 | N38: ACEROS | O38: ='EQUIPO ENERO 2025'!AP38 -> 5 | P38: =O38 -> 5 | Q38: =AK38 -> 5 | R38: =AL38 -> 5 | S38: =AM38 -> 5 | T38: =AN38 -> 5 | AA38: 1 | AF38: 1 | AJ38: ='EQUIPO ENERO 2025'!AP38 -> 5 | AK38: =P38-Z38+AE38+U38 -> 5 | AL38: =Q38-AA38+AF38+V38 -> 5 | AM38: =R38-AB38+AG38+W38 -> 5 | AN38: =S38-AC38+AH38+X38 -> 5 | AO38: =T38-AD38+AI38+Y38 -> 5 | AP38: 1 | AQ38: =AO38 -> 5 | AS38: 330
A39: =A38+1 -> 34 | B39: BÁSCULA DE PISO SS ACERO INOXIDABLE CAPACIDAD 150 kg DE 60 x 60 cm | C39: NO. 1 | D39: BRECKNELL | E39: SE-7610WSS | F39: 150 x 0.02 kg | G39: #VALUE! | H39: 10800 | I39: SE7610W-SS-6060-150kg | J39: LOCOSC | K39: 45673 | L39: 240907-1 | M39: 126 | O39: ='EQUIPO ENERO 2025'!AP39 -> 5 | P39: =O39 -> 5 | Q39: =AK39 -> 5 | R39: =AL39 -> 5 | S39: =AM39 -> 5 | T39: =AN39 -> 5 | AJ39: ='EQUIPO ENERO 2025'!AP39 -> 5 | AK39: =P39-Z39+AE39+U39 -> 5 | AL39: =Q39-AA39+AF39+V39 -> 5 | AM39: =R39-AB39+AG39+W39 -> 5 | AN39: =S39-AC39+AH39+X39 -> 5 | AO39: =T39-AD39+AI39+Y39 -> 5 | AP39: 1 | AQ39: =AO39 -> 5
A40: =A39+1 -> 35 | B40: BASCULA DE PISO CAPACIDAD 30kg DE 40X40 | C40: No. 1 | D40: BRECKNELL | E40: SE-7610 | F40: 30 x 0.005 kg | G40: #VALUE! | H40: 2800 | I40: SE-LP7610-30kg | J40: LOCOSC | K40: 45574 | L40: LP3211240 | M40: 71 | O40: ='EQUIPO ENERO 2025'!AP40 -> 8 | P40: =O40 -> 8 | Q40: =AK40 -> 8 | R40: =AL40 -> 8 | S40: =AM40 -> 8 | T40: =AN40 -> 8 | AJ40: ='EQUIPO ENERO 2025'!AP40 -> 8 | AK40: =P40-Z40+AE40+U40 -> 8 | AL40: =Q40-AA40+AF40+V40 -> 8 | AM40: =R40-AB40+AG40+W40 -> 8 | AN40: =S40-AC40+AH40+X40 -> 8 | AO40: =T40-AD40+AI40+Y40 -> 8 | AP40: 1 | AQ40: =AO40 -> 8
A41: =A40+1 -> 36 | B41: BASCULA DE PISO CAPACIDAD 60kg DE 40X50 | C41: No. 1 | D41: BRECKNELL | E41: SE-7610 | F41: 60 x 0.01 kg | G41: #VALUE! | H41: 2800 | I41: SE-LP7610-60kg | J41: LOCOSC | K41: 45574 | L41: LP3211240 | M41: 71 | O41: ='EQUIPO ENERO 2025'!AP41 -> 2 | P41: =O41 -> 2 | Q41: =AK41 -> 2 | R41: =AL41 -> 2 | S41: =AM41 -> 2 | T41: =AN41 -> 2 | AJ41: ='EQUIPO ENERO 2025'!AP41 -> 2 | AK41: =P41-Z41+AE41+U41 -> 2 | AL41: =Q41-AA41+AF41+V41 -> 2 | AM41: =R41-AB41+AG41+W41 -> 2 | AN41: =S41-AC41+AH41+X41 -> 2 | AO41: =T41-AD41+AI41+Y41 -> 2 | AP41: 0 | AQ41: =AO41 -> 2
A42: =A41+1 -> 37 | B42: BASCULA DE PISO PLATAFORMA /ABS CAJA | C42: No. 1 | D42: BRECKNELL | E42: SE-LP7611 | F42: 600 x 0.5 kg | G42: #VALUE! | H42: 5500 | I42: SE7611J-5060-600kg | J42: LOCOSC | K42: 45673 | L42: 240907-1 | M42: 127 | O42: ='EQUIPO ENERO 2025'!AP42 -> 10 | P42: =O42 -> 10 | Q42: =AK42 -> 10 | R42: =AL42 -> 10 | S42: =AM42 -> 10 | T42: =AN42 -> 10 | AJ42: ='EQUIPO ENERO 2025'!AP42 -> 10 | AK42: =P42-Z42+AE42+U42 -> 10 | AL42: =Q42-AA42+AF42+V42 -> 10 | AM42: =R42-AB42+AG42+W42 -> 10 | AN42: =S42-AC42+AH42+X42 -> 10 | AO42: =T42-AD42+AI42+Y42 -> 10 | AP42: 1 | AQ42: =AO42 -> 10
A43: =A42+1 -> 38 | B43: BÁSCULA DE PLATAFORMA SE7611 DE 1 000 kg | C43: LAB | D43: BRECKNELL | E43: SE7611T | F43: 1 000 kg | G43: #VALUE! | I43: SE7611-1X1M-1T | J43: LOCOSC | K43: 45673 | L43: 240907-1 | M43: 128 | N43: ACEROS | O43: ='EQUIPO ENERO 2025'!AP43 -> 10 | P43: =O43 -> 10 | Q43: =AK43 -> 10 | R43: =AL43 -> 10 | S43: =AM43 -> 10 | T43: =AN43 -> 10 | AA43: 1 | AF43: 1 | AJ43: ='EQUIPO ENERO 2025'!AP43 -> 10 | AK43: =P43-Z43+AE43+U43 -> 10 | AL43: =Q43-AA43+AF43+V43 -> 10 | AM43: =R43-AB43+AG43+W43 -> 10 | AN43: =S43-AC43+AH43+X43 -> 10 | AO43: =T43-AD43+AI43+Y43 -> 10 | AP43: 1 | AQ43: =AO43 -> 10 | AS43: 330
A44: =A43+1 -> 39 | B44: BASCULA ELECTRNICA SK 10 WP | C44: No. 1 | D44: AND | E44: SE-SK10WP | F44: 10 x 0.02 kg | G44: #VALUE! | H44: 2000 | I44: SE-BASELE-SK10KWP | J44: AND | K44: 44592 | O44: ='EQUIPO ENERO 2025'!AP44 -> 1 | P44: =O44 -> 1 | Q44: =AK44 -> 1 | R44: =AL44 -> 1 | S44: =AM44 -> 1 | T44: =AN44 -> 1 | AJ44: ='EQUIPO ENERO 2025'!AP44 -> 1 | AK44: =P44-Z44+AE44+U44 -> 1 | AL44: =Q44-AA44+AF44+V44 -> 1 | AM44: =R44-AB44+AG44+W44 -> 1 | AN44: =S44-AC44+AH44+X44 -> 1 | AO44: =T44-AD44+AI44+Y44 -> 1 | AQ44: =AO44 -> 1
A45: =A44+1 -> 40 | B45: BASCULA ELECTRONICA 405 15 K | C45: No. 1 | D45: BRECKNELL | E45: SE-405 | F45: 15 x 0.002 kg | G45: #VALUE! | H45: 1500 | I45: SE-BASELE-405 | J45: BRECKNELL | K45: 44592 | O45: ='EQUIPO ENERO 2025'!AP45 -> 1 | P45: =O45 -> 1 | Q45: =AK45 -> 1 | R45: =AL45 -> 1 | S45: =AM45 -> 1 | T45: =AN45 -> 1 | AJ45: ='EQUIPO ENERO 2025'!AP45 -> 1 | AK45: =P45-Z45+AE45+U45 -> 1 | AL45: =Q45-AA45+AF45+V45 -> 1 | AM45: =R45-AB45+AG45+W45 -> 1 | AN45: =S45-AC45+AH45+X45 -> 1 | AO45: =T45-AD45+AI45+Y45 -> 1 | AQ45: =AO45 -> 1
A46: =A45+1 -> 41 | B46: BASCULA ELECTRONICA C 3235 6 K | C46: No. 1 | D46: BRECKNELL | E46: SE-3235 | F46: 6 x 0.001 kg | G46: #VALUE! | H46: 3200 | I46: SE-BASELE-BRCK-C3235-6 | J46: BRECKNELL | K46: 44592 | O46: ='EQUIPO ENERO 2025'!AP46 -> 0 | P46: =O46 -> 0 | Q46: =AK46 -> 0 | R46: =AL46 -> 0 | S46: =AM46 -> 0 | T46: =AN46 -> 0 | AJ46: ='EQUIPO ENERO 2025'!AP46 -> 0 | AK46: =P46-Z46+AE46+U46 -> 0 | AL46: =Q46-AA46+AF46+V46 -> 0 | AM46: =R46-AB46+AG46+W46 -> 0 | AN46: =S46-AC46+AH46+X46 -> 0 | AO46: =T46-AD46+AI46+Y46 -> 0 | AQ46: =AO46 -> 0
A47: =A46+1 -> 42 | B47: BASCULA ELECTRONICA C 3235 6 K (PARA DEMO) | C47: No. 1 | D47: BRECKNELL | E47: SE-3235 | F47: 6 x 0.001 kg | G47: #VALUE! | H47: 3200 | I47: SE-BASELE-BRCK-C3235-6-D | J47: BRECKNELL | K47: 44592 | O47: ='EQUIPO ENERO 2025'!AP47 -> 1 | P47: =O47 -> 1 | Q47: =AK47 -> 1 | R47: =AL47 -> 1 | S47: =AM47 -> 1 | T47: =AN47 -> 1 | AJ47: ='EQUIPO ENERO 2025'!AP47 -> 1 | AK47: =P47-Z47+AE47+U47 -> 1 | AL47: =Q47-AA47+AF47+V47 -> 1 | AM47: =R47-AB47+AG47+W47 -> 1 | AN47: =S47-AC47+AH47+X47 -> 1 | AO47: =T47-AD47+AI47+Y47 -> 1 | AP47: 1 | AQ47: =AO47 -> 1
A48: =A47+1 -> 43 | B48: BASCULA ELECTRONICA COLGANTE BRECKNELL 45 K | C48: No. 1 | D48: BRECKNELL | E48: ELECTROSAMSON SE-ESN | F48: 45 x 0.05 kg | G48: #VALUE! | H48: 1725 | I48: SE-GE-BEC-ES-45K | J48: BRECKNELL | K48: 45693 | L48: 2130012 | M48: 153 | N48: IMSA/YEGUADA | O48: ='EQUIPO ENERO 2025'!AP48 -> 1 | P48: =O48 -> 1 | Q48: =AK48 -> 18 | R48: =AL48 -> 3 | S48: =AM48 -> 3 | T48: =AN48 -> 3 | U48: 20 | Z48: 3 | AA48: 15 | AJ48: ='EQUIPO ENERO 2025'!AP48 -> 1 | AK48: =P48-Z48+AE48+U48 -> 18 | AL48: =Q48-AA48+AF48+V48 -> 3 | AM48: =R48-AB48+AG48+W48 -> 3 | AN48: =S48-AC48+AH48+X48 -> 3 | AO48: =T48-AD48+AI48+Y48 -> 3 | AQ48: =AO48 -> 3 | AR48: 2774353240/1934771204 | AS48: 323/328
A49: =A48+1 -> 44 | B49: BASCULA ELECTRONICA SK 10 KEG | C49: No. 1 | D49: AND | E49: SE-SK10KEG | F49: 10 x 0.005 kg | G49: #VALUE! | H49: 1500 | I49: SE-BASELE-SK10KEG | J49: AND | K49: 44592 | O49: ='EQUIPO ENERO 2025'!AP49 -> 1 | P49: =O49 -> 1 | Q49: =AK49 -> 1 | R49: =AL49 -> 1 | S49: =AM49 -> 1 | T49: =AN49 -> 1 | AJ49: ='EQUIPO ENERO 2025'!AP49 -> 1 | AK49: =P49-Z49+AE49+U49 -> 1 | AL49: =Q49-AA49+AF49+V49 -> 1 | AM49: =R49-AB49+AG49+W49 -> 1 | AN49: =S49-AC49+AH49+X49 -> 1 | AO49: =T49-AD49+AI49+Y49 -> 1 | AQ49: =AO49 -> 1
A50: =A49+1 -> 45 | B50: BASCULA ELECTRONICA SK 20 KEG | C50: No. 1 | D50: AND | E50: SE-SK20KEG | F50: 20 x 0.1 kg | G50: #VALUE! | H50: 1500 | I50: SE-BASELE-SK20KEG | J50: AND | K50: 44592 | O50: ='EQUIPO ENERO 2025'!AP50 -> 1 | P50: =O50 -> 1 | Q50: =AK50 -> 1 | R50: =AL50 -> 1 | S50: =AM50 -> 1 | T50: =AN50 -> 1 | AJ50: ='EQUIPO ENERO 2025'!AP50 -> 1 | AK50: =P50-Z50+AE50+U50 -> 1 | AL50: =Q50-AA50+AF50+V50 -> 1 | AM50: =R50-AB50+AG50+W50 -> 1 | AN50: =S50-AC50+AH50+X50 -> 1 | AO50: =T50-AD50+AI50+Y50 -> 1 | AQ50: =AO50 -> 1
A51: =A50+1 -> 46 | B51: BASCULA N1124-LL MECANICA MODELO SE-1124B | C51: N/A | D51: FAIRBANKS MORSE | E51: SE-1124B | F51: 1 200 x 0.5 lb | G51: #VALUE! | H51: 9800 | I51: SE-BASC-MECA | J51: SIDASA | K51: 45315 | L51: 3673178618 | M51: 11 | O51: ='EQUIPO ENERO 2025'!AP51 -> 0 | P51: =O51 -> 0 | Q51: =AK51 -> 0 | R51: =AL51 -> 0 | S51: =AM51 -> 0 | T51: =AN51 -> 0 | AJ51: ='EQUIPO ENERO 2025'!AP51 -> 0 | AK51: =P51-Z51+AE51+U51 -> 0 | AL51: =Q51-AA51+AF51+V51 -> 0 | AM51: =R51-AB51+AG51+W51 -> 0 | AN51: =S51-AC51+AH51+X51 -> 0 | AO51: =T51-AD51+AI51+Y51 -> 0 | AQ51: =AO51 -> 0
A52: =A51+1 -> 47 | B52: BASCULA TMF-30kg | C52: No. 2 | D52: TM | E52: TMF | F52: 30 x 0.005 kg | G52: #VALUE! | H52: 4800 | I52: SE-BAS-TMF-30 | J52: LOCOSC | K52: 45107 | L52: LP230224-1 | M52: 393 | O52: ='EQUIPO ENERO 2025'!AP52 -> 1 | P52: =O52 -> 1 | Q52: =AK52 -> 1 | R52: =AL52 -> 1 | S52: =AM52 -> 1 | T52: =AN52 -> 1 | AJ52: ='EQUIPO ENERO 2025'!AP52 -> 1 | AK52: =P52-Z52+AE52+U52 -> 1 | AL52: =Q52-AA52+AF52+V52 -> 1 | AM52: =R52-AB52+AG52+W52 -> 1 | AN52: =S52-AC52+AH52+X52 -> 1 | AO52: =T52-AD52+AI52+Y52 -> 1 | AQ52: =AO52 -> 1
A53: =A52+1 -> 48 | B53: BASCULA-TMF-15K | C53: No. 2 | D53: TM | F53: 15 x 0.001 kg | G53: #VALUE! | H53: 4800 | I53: SE-BASC-TMF | J53: LOCOSC | K53: 44592 | O53: ='EQUIPO ENERO 2025'!AP53 -> 1 | P53: =O53 -> 1 | Q53: =AK53 -> 1 | R53: =AL53 -> 1 | S53: =AM53 -> 1 | T53: =AN53 -> 1 | AJ53: ='EQUIPO ENERO 2025'!AP53 -> 1 | AK53: =P53-Z53+AE53+U53 -> 1 | AL53: =Q53-AA53+AF53+V53 -> 1 | AM53: =R53-AB53+AG53+W53 -> 1 | AN53: =S53-AC53+AH53+X53 -> 1 | AO53: =T53-AD53+AI53+Y53 -> 1 | AQ53: =AO53 -> 1
A54: =A53+1 -> 49 | B54: BASCULA PESA EJES CON MARCO/INDICADOR LP7561 (SOLO MODULOS X2PADS) | C54: LAB | D54: TECNO SCALE | E54: SE-LP7662 | F54: 30 t | G54: #VALUE! | I54: SE7662-1530-30T*2PADS | J54: LOCOSC | K54: 45687 | L54: 240907-1 | M54: 144 | O54: ='EQUIPO ENERO 2025'!AP54 -> 4 | P54: =O54 -> 4 | Q54: =AK54 -> 4 | R54: =AL54 -> 4 | S54: =AM54 -> 4 | T54: =AN54 -> 4 | AJ54: ='EQUIPO ENERO 2025'!AP54 -> 4 | AK54: =P54-Z54+AE54+U54 -> 4 | AL54: =Q54-AA54+AF54+V54 -> 4 | AM54: =R54-AB54+AG54+W54 -> 4 | AN54: =S54-AC54+AH54+X54 -> 4 | AO54: =T54-AD54+AI54+Y54 -> 4 | AQ54: =AO54 -> 4
A55: =A54+1 -> 50 | B55: BASCULA PESA EJES/INDICADOR LP7561 | C55: No.1 | D55: TECNO SCALE | E55: SE-7662 | F55: 30T | G55: #VALUE! | I55: SE-7662-1530-30T*2 PADS | J55: LOCOSC | K55: 45566 | L55: LP240702-2 | M55: 68 | N55: INGRESADO POR ALDO SOTO EN ESTE MES DE JULIO 2025 | O55: ='EQUIPO ENERO 2025'!AP55 -> 0 | P55: =O55 -> 0 | Q55: =AK55 -> 1 | R55: =AL55 -> 1 | S55: =AM55 -> 1 | T55: =AN55 -> 1 | U55: 1 | AJ55: ='EQUIPO ENERO 2025'!AP55 -> 0 | AK55: =P55-Z55+AE55+U55 -> 1 | AL55: =Q55-AA55+AF55+V55 -> 1 | AM55: =R55-AB55+AG55+W55 -> 1 | AN55: =S55-AC55+AH55+X55 -> 1 | AO55: =T55-AD55+AI55+Y55 -> 1 | AQ55: =AO55 -> 1
A56: =A55+1 -> 51 | B56: BASCULA PESA ANIMAL (CERDOS) SE-7628A | C56: No.1 | D56: BRECKNELL | E56: SE-7628A | F56: 2 T | G56: #VALUE! | I56: SE-7628A-1215-2T | J56: LOCOSC | K56: 45566 | L56: LP240702-2 | M56: 75 | O56: ='EQUIPO ENERO 2025'!AP56 -> 2 | P56: =O56 -> 2 | Q56: =AK56 -> 2 | R56: =AL56 -> 2 | S56: =AM56 -> 2 | T56: =AN56 -> 2 | AJ56: ='EQUIPO ENERO 2025'!AP56 -> 2 | AK56: =P56-Z56+AE56+U56 -> 2 | AL56: =Q56-AA56+AF56+V56 -> 2 | AM56: =R56-AB56+AG56+W56 -> 2 | AN56: =S56-AC56+AH56+X56 -> 2 | AO56: =T56-AD56+AI56+Y56 -> 2 | AQ56: =AO56 -> 2
A57: =A56+1 -> 52 | B57: BASCULA PESA ANIMAL (GANADO) SE-7628A | C57: No.1 | D57: BRECKNELL | E57: SE-7628A | F57: 1.5T | G57: #VALUE! | I57: SE-7628A-0923-1.5T | J57: LOCOSC | K57: 45566 | L57: LP240702-2 | M57: 75 | O57: ='EQUIPO ENERO 2025'!AP57 -> 7 | P57: =O57 -> 7 | Q57: =AK57 -> 7 | R57: =AL57 -> 7 | S57: =AM57 -> 7 | T57: =AN57 -> 7 | AJ57: ='EQUIPO ENERO 2025'!AP57 -> 7 | AK57: =P57-Z57+AE57+U57 -> 7 | AL57: =Q57-AA57+AF57+V57 -> 7 | AM57: =R57-AB57+AG57+W57 -> 7 | AN57: =S57-AC57+AH57+X57 -> 7 | AO57: =T57-AD57+AI57+Y57 -> 7 | AQ57: =AO57 -> 7
A58: =A57+1 -> 53 | B58: BÁSCULA BANDA DINAMICA INCLUYE 1 INDICADOR CON ARMARIO, 4 CELDAS DE CARGA TIPO S TSC 500 kg METTLER TOLEDO, 8 RODILLOS Y 1 ESTRUCTURA DE METAL | D58: TECNO SCALE | E58: SE-ICS-17A | F58: 2 T | J58: YORK | K58: 45687 | L58: 04YK01K602 | M58: 141 | O58: ='EQUIPO ENERO 2025'!AP58 -> 1 | P58: =O58 -> 1 | Q58: =AK58 -> 1 | R58: =AL58 -> 1 | S58: =AM58 -> 1 | T58: =AN58 -> 1 | AJ58: ='EQUIPO ENERO 2025'!AP58 -> 1 | AK58: =P58-Z58+AE58+U58 -> 1 | AL58: =Q58-AA58+AF58+V58 -> 1 | AM58: =R58-AB58+AG58+W58 -> 1 | AN58: =S58-AC58+AH58+X58 -> 1 | AO58: =T58-AD58+AI58+Y58 -> 1 | AQ58: =AO58 -> 1
A59: =A58+1 -> 54 | B59: BÁSCULA CAMIONERA 50 T | D59: REVUELTA / AVERY | E59: ZM405 | F59: 50 T | K59: 45689 | M59: 151 | N59: SE COMPRO LOCAL/BETHEL | O59: ='EQUIPO ENERO 2025'!AP59 -> 0 | P59: =O59 -> 0 | Q59: =AK59 -> 1 | R59: =AL59 -> 1 | S59: =AM59 -> 1 | T59: =AN59 -> 1 | U59: 1 | AJ59: ='EQUIPO ENERO 2025'!AP60 -> 34 | AK59: =P59-Z59+AE59+U59 -> 1 | AL59: =Q59-AA59+AF59+V59 -> 1 | AM59: =R59-AB59+AG59+W59 -> 1 | AN59: =S59-AC59+AH59+X59 -> 1 | AO59: =T59-AD59+AI59+Y59 -> 1 | AQ59: =AO59 -> 1
A60: =A59+1 -> 55 | B60: BATERIAS 4V4AH | C60: No. 2 | D60: S/M | E60: S/M | F60: 4V | G60: #VALUE! | H60: 300 | I60: SE-BAT4V | J60: LOCOSC | K60: 45107 | L60: LP230224-1 | M60: 387 | N60: ACEROS DE GUATEMALA | O60: ='EQUIPO ENERO 2025'!AP60 -> 34 | P60: =O60 -> 34 | Q60: =AK60 -> 34 | R60: =AL60 -> 34 | S60: =AM60 -> 32 | T60: =AN60 -> 32 | Z60: 3 | AB60: 2 | AE60: 3 | AJ60: ='EQUIPO ENERO 2025'!AP60 -> 34 | AK60: =P60-Z60+AE60+U60 -> 34 | AL60: =Q60-AA60+AF60+V60 -> 34 | AM60: =R60-AB60+AG60+W60 -> 32 | AN60: =S60-AC60+AH60+X60 -> 32 | AO60: =T60-AD60+AI60+Y60 -> 32 | AQ60: =AO60 -> 32 | AS60: 342/342
A61: =A60+1 -> 56 | B61: BATERIAS 6V4AH | C61: No. 2 | D61: S/M | E61: S/M | F61: 6V | G61: #VALUE! | H61: 300 | I61: SE-BAT6V | J61: LOCOSC | K61: 45107 | L61: LP230224-1 | M61: 387 | N61: ARROCERA LOS CORRALES/HERNÁN GALVAN/PROCLEAN | O61: ='EQUIPO ENERO 2025'!AP61 -> 58 | P61: =O61 -> 58 | Q61: =AK61 -> 57 | R61: =AL61 -> 57 | S61: =AM61 -> 54 | T61: =AN61 -> 53 | Z61: 4 | AA61: 4 | AB61: 6 | AC61: 1 | AE61: 3 | AF61: 4 | AG61: 3 | AJ61: ='EQUIPO ENERO 2025'!AP61 -> 58 | AK61: =P61-Z61+AE61+U61 -> 57 | AL61: =Q61-AA61+AF61+V61 -> 57 | AM61: =R61-AB61+AG61+W61 -> 54 | AN61: =S61-AC61+AH61+X61 -> 53 | AO61: =T61-AD61+AI61+Y61 -> 53 | AQ61: =AO61 -> 53 | AS61: 322/327/332/338/340/349
A62: =A61+1 -> 57 | B62: BATERIAS 6V8A NIPPON | C62: NO. 2 | E62: S/M | F62: 6V | M62: 72 | O62: ='EQUIPO ENERO 2025'!AP62 -> 0 | P62: =O62 -> 0 | Q62: =AK62 -> 0 | R62: =AL62 -> 0 | S62: =AM62 -> 0 | T62: =AN62 -> 0 | AJ62: ='EQUIPO ENERO 2025'!AP62 -> 0 | AK62: =P62-Z62+AE62+U62 -> 0 | AL62: =Q62-AA62+AF62+V62 -> 0 | AM62: =R62-AB62+AG62+W62 -> 0 | AN62: =S62-AC62+AH62+X62 -> 0 | AO62: =T62-AD62+AI62+Y62 -> 0 | AQ62: =AO62 -> 0
A63: =A62+1 -> 58 | B63: BATERIAS 3.7V /2000MAH | C63: NO.2 | D63: S/M | E63: GDICR18650 | F63: 3.7V/2000mAH | G63: #VALUE! | I63: SE-BAT3V | J63: LOCOSC | K63: 45574 | L63: LP3211240 | M63: 75 | O63: ='EQUIPO ENERO 2025'!AP63 -> 25 | P63: =O63 -> 25 | Q63: =AK63 -> 24 | R63: =AL63 -> 24 | S63: =AM63 -> 24 | T63: =AN63 -> 24 | Z63: 2 | AE63: 1 | AJ63: ='EQUIPO ENERO 2025'!AP63 -> 25 | AK63: =P63-Z63+AE63+U63 -> 24 | AL63: =Q63-AA63+AF63+V63 -> 24 | AM63: =R63-AB63+AG63+W63 -> 24 | AN63: =S63-AC63+AH63+X63 -> 24 | AO63: =T63-AD63+AI63+Y63 -> 24 | AQ63: =AO63 -> 24 | AS63: 320/COPASA
A64: =A63+1 -> 59 | B64: BATERIAS 3.7V /4000mAh | C64: NO.2 | D64: S/M | E64: LPB04050 152P | F64: 3.7V/4000mAh | G64: #VALUE! | I64: SE-BAT3V- | J64: LOCOSC | K64: 45574 | L64: LP3211240 | M64: 75 | O64: ='EQUIPO ENERO 2025'!AP64 -> 45 | P64: =O64 -> 45 | Q64: =AK64 -> 45 | R64: =AL64 -> 45 | S64: =AM64 -> 45 | T64: =AN64 -> 45 | AJ64: ='EQUIPO ENERO 2025'!AP64 -> 45 | AK64: =P64-Z64+AE64+U64 -> 45 | AL64: =Q64-AA64+AF64+V64 -> 45 | AM64: =R64-AB64+AG64+W64 -> 45 | AN64: =S64-AC64+AH64+X64 -> 45 | AO64: =T64-AD64+AI64+Y64 -> 45 | AQ64: =AO64 -> 45
A65: =A64+1 -> 60 | B65: BATERIAS 6V/5Ah | C65: NO. 2 | D65: S/M | E65: DJW6-5.0 | F65: 6V/5mAH | G65: #VALUE! | I65: SE-BAT6V/5 | J65: LOCOSC | K65: 45673 | L65: 240907-1 | M65: 130 | N65: ARROCERA LOS CORRALES INSTALADA EN BASCULAS | O65: ='EQUIPO ENERO 2025'!AP65 -> 4 | P65: =O65 -> 4 | Q65: =AK65 -> 4 | R65: =AL65 -> 2 | S65: =AM65 -> 2 | T65: =AN65 -> 2 | Z65: 3 | AA65: 2 | AE65: 3 | AJ65: ='EQUIPO ENERO 2025'!AP65 -> 4 | AK65: =P65-Z65+AE65+U65 -> 4 | AL65: =Q65-AA65+AF65+V65 -> 2 | AM65: =R65-AB65+AG65+W65 -> 2 | AN65: =S65-AC65+AH65+X65 -> 2 | AO65: =T65-AD65+AI65+Y65 -> 2 | AQ65: =AO65 -> 2 | AR65: 3956690624 | AS65: 338
A66: =A65+1 -> 61 | B66: BATERIAS 12V/7.0Ah PARA INDICADOR LP75819 | C66: NO. 2 | D66: S/M | E66: DJW12-7.0 | F66: 12V/7.0mAh | G66: #VALUE! | I66: SE-BAT12V/7 | J66: LOCOSC | K66: 45673 | L66: 240907-1 | M66: 131 | O66: ='EQUIPO ENERO 2025'!AP66 -> 10 | P66: =O66 -> 10 | Q66: =AK66 -> 10 | R66: =AL66 -> 10 | S66: =AM66 -> 10 | T66: =AN66 -> 10 | AJ66: ='EQUIPO ENERO 2025'!AP66 -> 10 | AK66: =P66-Z66+AE66+U66 -> 10 | AL66: =Q66-AA66+AF66+V66 -> 10 | AM66: =R66-AB66+AG66+W66 -> 10 | AN66: =S66-AC66+AH66+X66 -> 10 | AO66: =T66-AD66+AI66+Y66 -> 10 | AQ66: =AO66 -> 10
A67: =A66+1 -> 62 | B67: CABLE CELDA DE CARGA MTX (6 PINES) | C67: No. 2 | D67: METTLER TOLEDO | E67: MTX | G67: #VALUE! | I67: SE-CABLE-MTX | K67: 44592 | O67: ='EQUIPO ENERO 2025'!AP67 -> 0 | P67: =O67 -> 0 | Q67: =AK67 -> 0 | R67: =AL67 -> 0 | S67: =AM67 -> 0 | T67: =AN67 -> 0 | AJ67: ='EQUIPO ENERO 2025'!AP67 -> 0 | AK67: =P67-Z67+AE67+U67 -> 0 | AL67: =Q67-AA67+AF67+V67 -> 0 | AM67: =R67-AB67+AG67+W67 -> 0 | AN67: =S67-AC67+AH67+X67 -> 0 | AO67: =T67-AD67+AI67+Y67 -> 0 | AQ67: =AO67 -> 0
A68: =A67+1 -> 63 | B68: CABLE CELDA DE CARGA PDX (5 PINES) | C68: No. 2 | D68: METTLER TOLEDO | E68: PDX | G68: #VALUE! | I68: SE-CABLE-PDX | K68: 44592 | O68: ='EQUIPO ENERO 2025'!AP68 -> 0 | P68: =O68 -> 0 | Q68: =AK68 -> 0 | R68: =AL68 -> 0 | S68: =AM68 -> 0 | T68: =AN68 -> 0 | AJ68: ='EQUIPO ENERO 2025'!AP68 -> 0 | AK68: =P68-Z68+AE68+U68 -> 0 | AL68: =Q68-AA68+AF68+V68 -> 0 | AM68: =R68-AB68+AG68+W68 -> 0 | AN68: =S68-AC68+AH68+X68 -> 0 | AO68: =T68-AD68+AI68+Y68 -> 0 | AQ68: =AO68 -> 0
A69: =A68+1 -> 64 | B69: CABLE PARA BATERIA DE INDICADOR DIGITAL MODELO SE-7517 ROJO Y NEGRO | C69: No.2 | E69: SE-7517BA | I69: SE-CAB-7517BA | J69: LOCOSC | K69: 45279 | M69: 481 | O69: ='EQUIPO ENERO 2025'!AP69 -> 12 | P69: =O69 -> 12 | Q69: =AK69 -> 12 | R69: =AL69 -> 12 | S69: =AM69 -> 12 | T69: =AN69 -> 12 | AJ69: ='EQUIPO ENERO 2025'!AP69 -> 12 | AK69: =P69-Z69+AE69+U69 -> 12 | AL69: =Q69-AA69+AF69+V69 -> 12 | AM69: =R69-AB69+AG69+W69 -> 12 | AN69: =S69-AC69+AH69+X69 -> 12 | AO69: =T69-AD69+AI69+Y69 -> 12 | AQ69: =AO69 -> 12
A70: =A69+1 -> 65 | B70: CABLE PARA INDICADOR LP7581P CON CONECTOR (CABLE ROJO Y NEGRO) | C70: NO. 2 | D70: S/M | E70: S/M | F70: S/C | G70: #VALUE! | I70: SE-CABLE-LP7581P | J70: LOCOSC | K70: 45673 | L70: 240907-1 | M70: 130 | O70: ='EQUIPO ENERO 2025'!AP70 -> 11 | P70: =O70 -> 11 | Q70: =AK70 -> 11 | R70: =AL70 -> 11 | S70: =AM70 -> 11 | T70: =AN70 -> 11 | AJ70: ='EQUIPO ENERO 2025'!AP70 -> 11 | AK70: =P70-Z70+AE70+U70 -> 11 | AL70: =Q70-AA70+AF70+V70 -> 11 | AM70: 11 | AN70: =S70-AC70+AH70+X70 -> 11 | AO70: =T70-AD70+AI70+Y70 -> 11 | AQ70: =AO70 -> 11
A71: =A70+1 -> 66 | B71: CAJA PLASTICA IP 67 | C71: No. 2 | G71: #VALUE! | I71: SE-CAJ-IP67 | O71: ='EQUIPO ENERO 2025'!AP71 -> 3 | P71: =O71 -> 3 | Q71: =AK71 -> 3 | R71: =AL71 -> 3 | S71: =AM71 -> 3 | T71: =AN71 -> 3 | AJ71: ='EQUIPO ENERO 2025'!AP71 -> 3 | AK71: =P71-Z71+AE71+U71 -> 3 | AL71: =Q71-AA71+AF71+V71 -> 3 | AM71: =R71-AB71+AG71+W71 -> 3 | AN71: =S71-AC71+AH71+X71 -> 3 | AO71: =T71-AD71+AI71+Y71 -> 3 | AQ71: =AO71 -> 3
A72: =A71+1 -> 67 | B72: CAJA SUMA | C72: No. 2 | D72: S/M | E72: SE-LP7312 | F72: 4 CANALES | G72: #VALUE! | H72: 1500 | I72: SE-CAJA-SUMA LP7312-A2-4 | J72: LOCOSC | K72: 45687 | L72: LP230224-1 | M72: 145 | N72: MAYALATEX | O72: ='EQUIPO ENERO 2025'!AP72 -> 6 | P72: =O72 -> 6 | Q72: =AK72 -> 6 | R72: =AL72 -> 6 | S72: =AM72 -> 6 | T72: =AN72 -> 6 | Z72: 4 | AE72: 4 | AJ72: ='EQUIPO ENERO 2025'!AP72 -> 6 | AK72: =P72-Z72+AE72+U72 -> 6 | AL72: =Q72-AA72+AF72+V72 -> 6 | AM72: =R72-AB72+AG72+W72 -> 6 | AN72: =S72-AC72+AH72+X72 -> 6 | AO72: =T72-AD72+AI72+Y72 -> 6 | AP72: 1 SOLO CAJA | AQ72: =AO72 -> 6 | AS72: 325
A73: =A72+1 -> 68 | B73: CAJA SUMA 4 CANALES TOTAL COMP STOCK 1007 | C73: No. 2 | D73: TOTAL COMP | E73: S-45 1250 | I73: SE-CAJA-1250-5-SS | J73: TOTAL COMP | K73: 45062 | M73: 352 | O73: ='EQUIPO ENERO 2025'!AP73 -> 0 | P73: =O73 -> 0 | Q73: =AK73 -> 0 | R73: =AL73 -> 0 | S73: =AM73 -> 0 | T73: =AN73 -> 0 | AJ73: ='EQUIPO ENERO 2025'!AP73 -> 0 | AK73: =P73-Z73+AE73+U73 -> 0 | AL73: =Q73-AA73+AF73+V73 -> 0 | AM73: =R73-AB73+AG73+W73 -> 0 | AN73: =S73-AC73+AH73+X73 -> 0 | AO73: =T73-AD73+AI73+Y73 -> 0 | AQ73: =AO73 -> 0
A74: =A73+1 -> 69 | B74: CAJA SUMA ACERO INOX 4 CANALES 50063-0066 TORNILLOS | C74: No. 2 | D74: BRECKNELL | E74: 50063-0066 TORNILLOS | G74: #VALUE! | H74: 5500 | I74: SE-CAJASUM-4C | J74: BRECKNELL | K74: 45391 | L74: 2187074-001 | M74: 55 | O74: ='EQUIPO ENERO 2025'!AP74 -> 1 | P74: =O74 -> 1 | Q74: =AK74 -> 1 | R74: =AL74 -> 1 | S74: =AM74 -> 1 | T74: =AN74 -> 1 | AJ74: ='EQUIPO ENERO 2025'!AP74 -> 1 | AK74: =P74-Z74+AE74+U74 -> 1 | AL74: =Q74-AA74+AF74+V74 -> 1 | AM74: =R74-AB74+AG74+W74 -> 1 | AN74: =S74-AC74+AH74+X74 -> 1 | AO74: =T74-AD74+AI74+Y74 -> 1 | AQ74: =AO74 -> 1
A75: =A74+1 -> 70 | B75: CAJA SUMA ACERO INOX 4 CANALES GRAPA AWT15-501062 06 CAMIONERAS | C75: No. 2 | D75: AVERY WEIGH TRONIX | E75: AWT15-501062 06 | G75: #VALUE! | H75: 5500 | I75: SE-CAJASUM-4C-GRA | J75: AVERY WEIGH TRONIX | K75: 45013 | L75: 2103556 | M75: 321 | O75: ='EQUIPO ENERO 2025'!AP75 -> 6 | P75: =O75 -> 6 | Q75: =AK75 -> 6 | R75: =AL75 -> 6 | S75: =AM75 -> 6 | T75: =AN75 -> 6 | AJ75: ='EQUIPO ENERO 2025'!AP75 -> 6 | AK75: =P75-Z75+AE75+U75 -> 6 | AL75: =Q75-AA75+AF75+V75 -> 6 | AM75: =R75-AB75+AG75+W75 -> 6 | AN75: =S75-AC75+AH75+X75 -> 6 | AO75: =T75-AD75+AI75+Y75 -> 6 | AQ75: =AO75 -> 6
A76: =A75+1 -> 71 | B76: CAJA SUMA ACERO INOXIDABLE | C76: No. 2 | D76: LOCOSC | E76: SE-LP7310 | F76: 4 CANALES | G76: #VALUE! | H76: 2500 | I76: SE-LP7310-S2-4 | J76: LOCOSC | K76: 45328 | L76: LP230224-1 | M76: 32 | N76: ACEROS CESTA/banda | O76: ='EQUIPO ENERO 2025'!AP76 -> 13 | P76: =O76 -> 13 | Q76: =AK76 -> 12 | R76: =AL76 -> 12 | S76: =AM76 -> 12 | T76: =AN76 -> 12 | Z76: 1 | AJ76: ='EQUIPO ENERO 2025'!AP76 -> 13 | AK76: =P76-Z76+AE76+U76 -> 12 | AL76: =Q76-AA76+AF76+V76 -> 12 | AM76: =R76-AB76+AG76+W76 -> 12 | AN76: =S76-AC76+AH76+X76 -> 12 | AO76: =T76-AD76+AI76+Y76 -> 12 | AQ76: =AO76 -> 12 | AS76: 324
A77: =A76+1 -> 72 | B77: CAJA SUMA ACERO INOXIDABLE | C77: NO. 2 | D77: BRECKNELL | E77: SE-7312-S2-4 | F77: 4 CANALES | G77: #VALUE! | I77: SE-7312-SS | J77: LOCOSC | K77: 45626 | L77: S/F | M77: 103 | O77: ='EQUIPO ENERO 2025'!AP77 -> 3 | P77: =O77 -> 3 | Q77: =AK77 -> 3 | R77: =AL77 -> 3 | S77: =AM77 -> 3 | T77: =AN77 -> 3 | AA77: 2 | AF77: 2 | AJ77: ='EQUIPO ENERO 2025'!AP77 -> 3 | AK77: =P77-Z77+AE77+U77 -> 3 | AL77: =Q77-AA77+AF77+V77 -> 3 | AM77: =R77-AB77+AG77+W77 -> 3 | AN77: =S77-AC77+AH77+X77 -> 3 | AO77: =T77-AD77+AI77+Y77 -> 3 | AQ77: =AO77 -> 3
A78: =A77+1 -> 73 | B78: CAJA SUMA DE ACERO INOX CAMIONERA 12 CANALES | C78: No. 2 | D78: BRECKNELL | E78: IX-JXHG05-12-S | F78: 12 CANALES | G78: #VALUE! | I78: SE-CAJ-IX-JXHG05-12-S | J78: CNIC | K78: 45126 | L78: 2023015 | M78: 409 | O78: ='EQUIPO ENERO 2025'!AP78 -> 0 | P78: =O78 -> 0 | Q78: =AK78 -> 0 | R78: =AL78 -> 0 | S78: =AM78 -> 0 | T78: =AN78 -> 0 | AJ78: ='EQUIPO ENERO 2025'!AP78 -> 0 | AK78: =P78-Z78+AE78+U78 -> 0 | AL78: =Q78-AA78+AF78+V78 -> 0 | AM78: =R78-AB78+AG78+W78 -> 0 | AN78: =S78-AC78+AH78+X78 -> 0 | AO78: =T78-AD78+AI78+Y78 -> 0 | AQ78: =AO78 -> 0
A79: =A78+1 -> 74 | B79: CAJA SUMA SS DE 10 CANALES (SOLO CAJA | C79: NO. 2 | D79: S/M | E79: S/M | F79: 10 CANALES | I79: S/C | K79: 45656 | L79: INGRESA DE SERVICIO EN AVICOLA GABY/BASCULAS PRECICELL | M79: 102 | O79: ='EQUIPO ENERO 2025'!AP79 -> 1 | P79: =O79 -> 1 | Q79: =AK79 -> 1 | R79: =AL79 -> 1 | S79: =AM79 -> 1 | T79: =AN79 -> 1 | AJ79: ='EQUIPO ENERO 2025'!AP79 -> 1 | AK79: =P79-Z79+AE79+U79 -> 1 | AL79: =Q79-AA79+AF79+V79 -> 1 | AM79: =R79-AB79+AG79+W79 -> 1 | AN79: =S79-AC79+AH79+X79 -> 1 | AO79: =T79-AD79+AI79+Y79 -> 1 | AQ79: =AO79 -> 1
A80: =A79+1 -> 75 | B80: CALIBRADOR DIGITAL 0 - 150mm | C80: NO. 2 | D80: SUMIMET | E80: ACCUD 112-006-12 | F80: 0 a 150mm / 0 a 6 " | G80: #VALUE! | H80: 4200 | I80: SE-VD67 | J80: SUMINISTROS EN METROLOGIA | K80: 45670 | L80: 131207285 | M80: 124 | O80: ='EQUIPO ENERO 2025'!AP80 -> 0 | P80: =O80 -> 0 | Q80: =AK80 -> 0 | R80: =AL80 -> 0 | S80: =AM80 -> 0 | T80: =AN80 -> 0 | AJ80: ='EQUIPO ENERO 2025'!AP80 -> 0 | AK80: =P80-Z80+AE80+U80 -> 0 | AL80: =Q80-AA80+AF80+V80 -> 0 | AM80: =R80-AB80+AG80+W80 -> 0 | AN80: =S80-AC80+AH80+X80 -> 0 | AO80: =T80-AD80+AI80+Y80 -> 0 | AQ80: =AO80 -> 0
A81: =A80+1 -> 76 | B81: CALIBRADOR DIGITAL 0 a 300mm | C81: NO. 2 | D81: SUMIMET | E81: ACCUD 112-012-12 | F81: 0 a 300 mm / 0 a 12" | G81: #VALUE! | H81: 4200 | I81: SE-VD67 | J81: SUMINISTROS EN METROLOGIA | K81: 45670 | L81: 131207285 | M81: 124 | O81: ='EQUIPO ENERO 2025'!AP81 -> 0 | P81: =O81 -> 0 | Q81: =AK81 -> 0 | R81: =AL81 -> 0 | S81: =AM81 -> 0 | T81: =AN81 -> 0 | AJ81: ='EQUIPO ENERO 2025'!AP81 -> 0 | AK81: =P81-Z81+AE81+U81 -> 0 | AL81: =Q81-AA81+AF81+V81 -> 0 | AM81: =R81-AB81+AG81+W81 -> 0 | AN81: =S81-AC81+AH81+X81 -> 0 | AO81: =T81-AD81+AI81+Y81 -> 0 | AQ81: =AO81 -> 0
A82: =A81+1 -> 77 | B82: CARCASA DE INDICADOR SE-7517E | C82: No. 2 | D82: BRECKNELL | E82: SE-7517E | G82: #VALUE! | I82: SE-CARC-7517E | J82: LOCOSC | K82: 44592 | O82: ='EQUIPO ENERO 2025'!AP82 -> 1 | P82: =O82 -> 1 | Q82: =AK82 -> 1 | R82: =AL82 -> 1 | S82: =AM82 -> 1 | T82: =AN82 -> 1 | AJ82: ='EQUIPO ENERO 2025'!AP82 -> 1 | AK82: =P82-Z82+AE82+U82 -> 1 | AL82: =Q82-AA82+AF82+V82 -> 1 | AM82: =R82-AB82+AG82+W82 -> 1 | AN82: =S82-AC82+AH82+X82 -> 1 | AO82: =T82-AD82+AI82+Y82 -> 1 | AQ82: =AO82 -> 1
A83: =A82+1 -> 78 | B83: CARCASA DE INDICADOR SE-7510 PARTE TRASERA CON BATERIA | C83: NO.2 | D83: BRECKNELL | E83: SE-7510 | I83: SE-CARC-7510/BAT | J83: LOCOSC | K83: 45574 | L83: LP3211240 | M83: 76 | O83: ='EQUIPO ENERO 2025'!AP83 -> 8 | P83: =O83 -> 8 | Q83: =AK83 -> 8 | R83: =AL83 -> 8 | S83: =AM83 -> 8 | T83: =AN83 -> 8 | AJ83: ='EQUIPO ENERO 2025'!AP83 -> 8 | AK83: =P83-Z83+AE83+U83 -> 8 | AL83: =Q83-AA83+AF83+V83 -> 8 | AM83: =R83-AB83+AG83+W83 -> 8 | AN83: =S83-AC83+AH83+X83 -> 8 | AO83: =T83-AD83+AI83+Y83 -> 8 | AQ83: =AO83 -> 8
A84: =A83+1 -> 79 | B84: CARRITO DE METAL PARA BASCULA 7611 | C84: Lab | D84: SOEXSA | E84: SE-7611 | G84: #VALUE! | I84: SE-CAR-BAS7611 | J84: LOCOSC | K84: 44592 | O84: ='EQUIPO ENERO 2025'!AP84 -> 1 | P84: =O84 -> 1 | Q84: =AK84 -> 1 | R84: =AL84 -> 1 | S84: =AM84 -> 1 | T84: =AN84 -> 1 | AJ84: ='EQUIPO ENERO 2025'!AP84 -> 1 | AK84: =P84-Z84+AE84+U84 -> 1 | AL84: =Q84-AA84+AF84+V84 -> 1 | AM84: =R84-AB84+AG84+W84 -> 1 | AN84: =S84-AC84+AH84+X84 -> 1 | AO84: =T84-AD84+AI84+Y84 -> 1 | AQ84: =AO84 -> 1
A85: =A84+1 -> 80 | B85: CARTUCHO DE TINTA PARA IMPRESORA LP7561 | C85: NO. 2 | D85: PRINT-RITE | E85: EPSON ERC05 | I85: SE-ERC05 | J85: LOCOSC | K85: 45582 | M85: 81 | O85: ='EQUIPO ENERO 2025'!AP85 -> 10 | P85: =O85 -> 10 | Q85: =AK85 -> 10 | R85: =AL85 -> 10 | S85: =AM85 -> 10 | T85: =AN85 -> 10 | AJ85: ='EQUIPO ENERO 2025'!AP85 -> 10 | AK85: =P85-Z85+AE85+U85 -> 10 | AL85: =Q85-AA85+AF85+V85 -> 10 | AM85: =R85-AB85+AG85+W85 -> 10 | AN85: =S85-AC85+AH85+X85 -> 10 | AO85: =T85-AD85+AI85+Y85 -> 10 | AQ85: =AO85 -> 10
A86: =A85+1 -> 81 | B86: CELDA DE CARGA TIPO BARRA LP7161 | C86: No. 2 | D86: S/M | E86: LP7161 | F86: 800 kg | G86: #VALUE! | H86: 2800 | I86: SE-CELBAR-LP7161-800KG | J86: LOCOSC | K86: 45325 | M86: 12 | O86: ='EQUIPO ENERO 2025'!AP86 -> 1 | P86: =O86 -> 1 | Q86: =AK86 -> 1 | R86: =AL86 -> 1 | S86: =AM86 -> 1 | T86: =AN86 -> 1 | AJ86: ='EQUIPO ENERO 2025'!AP86 -> 1 | AK86: =P86-Z86+AE86+U86 -> 1 | AL86: =Q86-AA86+AF86+V86 -> 1 | AM86: =R86-AB86+AG86+W86 -> 1 | AN86: =S86-AC86+AH86+X86 -> 1 | AO86: =T86-AD86+AI86+Y86 -> 1 | AQ86: =AO86 -> 1
A87: =A86+1 -> 82 | B87: CELDA DE CARGA BARRA 50K 65016-050E-NC-001F | C87: No. 2 | D87: BRECKNELL | E87: 65016-050E-NC-001F | F87: 50 k | G87: #VALUE! | H87: Q | I87: SE-CELBAR-65016-50 | J87: BRECKNELL | K87: 44592 | O87: ='EQUIPO ENERO 2025'!AP87 -> 2 | P87: =O87 -> 2 | Q87: =AK87 -> 2 | R87: =AL87 -> 2 | S87: =AM87 -> 2 | T87: =AN87 -> 2 | AJ87: ='EQUIPO ENERO 2025'!AP87 -> 2 | AK87: =P87-Z87+AE87+U87 -> 2 | AL87: =Q87-AA87+AF87+V87 -> 2 | AM87: =R87-AB87+AG87+W87 -> 2 | AN87: =S87-AC87+AH87+X87 -> 2 | AO87: =T87-AD87+AI87+Y87 -> 2 | AQ87: =AO87 -> 2
A88: =A87+1 -> 83 | B88: CELDA DE CARGA 10 kg Total Comp | C88: No. 2 | D88: TOTAL COMP | E88: PSW-10KG 05500 | F88: 10k | G88: #VALUE! | I88: SE-CELCA-RL-10kg | J88: TOTAL COMP | K88: 44592 | O88: ='EQUIPO ENERO 2025'!AP88 -> 1 | P88: =O88 -> 1 | Q88: =AK88 -> 1 | R88: =AL88 -> 1 | S88: =AM88 -> 1 | T88: =AN88 -> 1 | AJ88: ='EQUIPO ENERO 2025'!AP88 -> 1 | AK88: =P88-Z88+AE88+U88 -> 1 | AL88: =Q88-AA88+AF88+V88 -> 1 | AM88: =R88-AB88+AG88+W88 -> 1 | AN88: =S88-AC88+AH88+X88 -> 1 | AO88: =T88-AD88+AI88+Y88 -> 1 | AQ88: =AO88 -> 1
A89: =A88+1 -> 84 | B89: CELDA DE CARGA 20 KG MODELO SUP1-20KG | C89: No. 2 | D89: LOCOSC | E89: SUP-1-20KG | F89: 20 kg | J89: LOCOSC | K89: 45416 | M89: 59 | O89: ='EQUIPO ENERO 2025'!AP89 -> 1 | P89: =O89 -> 1 | Q89: =AK89 -> 1 | R89: =AL89 -> 1 | S89: =AM89 -> 1 | T89: =AN89 -> 1 | AJ89: ='EQUIPO ENERO 2025'!AP89 -> 1 | AK89: =P89-Z89+AE89+U89 -> 1 | AL89: =Q89-AA89+AF89+V89 -> 1 | AM89: =R89-AB89+AG89+W89 -> 1 | AN89: =S89-AC89+AH89+X89 -> 1 | AO89: =T89-AD89+AI89+Y89 -> 1 | AQ89: =AO89 -> 1
A90: =A89+1 -> 85 | B90: CELDA DE CARGA 20K H8C-N5-20K-6YWB | C90: No. 2 | F90: 20 k | I90: SE-CELCA-20K | J90: LOCOSC | K90: 44592 | O90: ='EQUIPO ENERO 2025'!AP90 -> 0 | P90: =O90 -> 0 | Q90: =AK90 -> 0 | R90: =AL90 -> 0 | S90: =AM90 -> 0 | T90: =AN90 -> 0 | AJ90: ='EQUIPO ENERO 2025'!AP90 -> 0 | AK90: =P90-Z90+AE90+U90 -> 0 | AL90: =Q90-AA90+AF90+V90 -> 0 | AM90: =R90-AB90+AG90+W90 -> 0 | AN90: =S90-AC90+AH90+X90 -> 0 | AO90: =T90-AD90+AI90+Y90 -> 0 | AQ90: =AO90 -> 0
A91: =A90+1 -> 86 | B91: CELDA DE CARGA 75 K LP7154 16mm DOBLE BRIDA CAMIONERO | C91: No. 2 | D91: SENSORTRONICS | E91: LP7154 | F91: 75 k | G91: #VALUE! | H91: 7500 | I91: SE7154-75klb-16m | J91: LOCOSC | K91: 45673 | L91: 240907-1 | M91: 129 | N91: ACEROS CESTA/banda | O91: ='EQUIPO ENERO 2025'!AP91 -> 14 | P91: =O91 -> 14 | Q91: =AK91 -> 13 | R91: =AL91 -> 13 | S91: =AM91 -> 13 | T91: =AN91 -> 13 | Z91: 3 | AE91: 2 | AJ91: ='EQUIPO ENERO 2025'!AP91 -> 14 | AK91: =P91-Z91+AE91+U91 -> 13 | AL91: =Q91-AA91+AF91+V91 -> 13 | AM91: =R91-AB91+AG91+W91 -> 13 | AN91: =S91-AC91+AH91+X91 -> 13 | AO91: =T91-AD91+AI91+Y91 -> 13 | AQ91: =AO91 -> 13 | AS91: 324/329
A92: =A91+1 -> 87 | B92: CELDA DE CARGA BARRA ILE 150 K | C92: No. 2 | E92: ILE150 | F92: 150 kg | G92: #VALUE! | I92: SE-CELCA-150K | J92: LOCOSC | K92: 44592 | N92: SOEXSA NICARAGUA | O92: ='EQUIPO ENERO 2025'!AP92 -> 1 | P92: =O92 -> 1 | Q92: =AK92 -> 0 | R92: =AL92 -> 0 | S92: =AM92 -> 0 | T92: =AN92 -> 0 | Z92: 1 | AJ92: ='EQUIPO ENERO 2025'!AP92 -> 1 | AK92: =P92-Z92+AE92+U92 -> 0 | AL92: =Q92-AA92+AF92+V92 -> 0 | AM92: =R92-AB92+AG92+W92 -> 0 | AN92: =S92-AC92+AH92+X92 -> 0 | AO92: =T92-AD92+AI92+Y92 -> 0 | AQ92: =AO92 -> 0
A93: =A92+1 -> 88 | B93: CELDA DE CARGA BARRA 1 K (INCLUYE PATA) tecnipesa | C93: No. 2 | D93: BRECKNELL | E93: Tecnipesa | F93: 1 k | G93: #VALUE! | I93: SE-CELBAR-1 K | J93: BRECKNELL | K93: 44592 | O93: ='EQUIPO ENERO 2025'!AP93 -> 2 | P93: =O93 -> 2 | Q93: =AK93 -> 2 | R93: =AL93 -> 2 | S93: =AM93 -> 2 | T93: =AN93 -> 2 | AJ93: ='EQUIPO ENERO 2025'!AP93 -> 2 | AK93: =P93-Z93+AE93+U93 -> 2 | AL93: =Q93-AA93+AF93+V93 -> 2 | AM93: =R93-AB93+AG93+W93 -> 2 | AN93: =S93-AC93+AH93+X93 -> 2 | AO93: =T93-AD93+AI93+Y93 -> 2 | AQ93: =AO93 -> 2
A94: =A93+1 -> 89 | B94: CELDA DE CARGA BARRA 10 K-SQB-10QHSS | C94: No. 2 | D94: BRECKNELL | E94: SQB-10QHSS | F94: 10 k | G94: #VALUE! | H94: 5200 | I94: SE-CELBAR-10K | J94: BRECKNELL | K94: 44592 | O94: ='EQUIPO ENERO 2025'!AP94 -> 0 | P94: =O94 -> 0 | Q94: =AK94 -> 0 | R94: =AL94 -> 0 | S94: =AM94 -> 0 | T94: =AN94 -> 0 | AJ94: ='EQUIPO ENERO 2025'!AP94 -> 0 | AK94: =P94-Z94+AE94+U94 -> 0 | AL94: =Q94-AA94+AF94+V94 -> 0 | AM94: =R94-AB94+AG94+W94 -> 0 | AN94: =S94-AC94+AH94+X94 -> 0 | AO94: =T94-AD94+AI94+Y94 -> 0 | AQ94: =AO94 -> 0
A95: =A94+1 -> 90 | B95: CELDA DE CARGA BARRA 2KG | C95: No. 2 | D95: S/M | E95: HBM | F95: 2 kg | G95: #VALUE! | I95: SE-CELCA-2K | J95: LOCOSC | K95: 44592 | O95: ='EQUIPO ENERO 2025'!AP95 -> 1 | P95: =O95 -> 1 | Q95: =AK95 -> 1 | R95: =AL95 -> 1 | S95: =AM95 -> 1 | T95: =AN95 -> 1 | AJ95: ='EQUIPO ENERO 2025'!AP95 -> 1 | AK95: =P95-Z95+AE95+U95 -> 1 | AL95: =Q95-AA95+AF95+V95 -> 1 | AM95: =R95-AB95+AG95+W95 -> 1 | AN95: =S95-AC95+AH95+X95 -> 1 | AO95: =T95-AD95+AI95+Y95 -> 1 | AQ95: =AO95 -> 1
A96: =A95+1 -> 91 | B96: BASCULA DE PISO PLATAFORMA /ABS ARMADAS DEMO | D96: BRECKNELL | E96: SE-LP7611 | F96: 600 x 0.5 kg | G96: #VALUE! | H96: 4500 | I96: SE-LP7611-DEMO | J96: LOCOSC | K96: 44592 | O96: ='EQUIPO ENERO 2025'!AP96 -> 0 | P96: =O96 -> 0 | Q96: =AK96 -> 0 | R96: =AL96 -> 0 | S96: =AM96 -> 0 | T96: =AN96 -> 0 | AJ96: ='EQUIPO ENERO 2025'!AP96 -> 0 | AK96: =P96-Z96+AE96+U96 -> 0 | AL96: =Q96-AA96+AF96+V96 -> 0 | AM96: =R96-AB96+AG96+W96 -> 0 | AN96: =S96-AC96+AH96+X96 -> 0 | AO96: =T96-AD96+AI96+Y96 -> 0 | AQ96: =AO96 -> 0
A97: =A96+1 -> 92 | B97: CELDA DE CARGA BARRA 5 k 65016-005-NC-01F | C97: No. 2 | D97: SENSORTRONICS | E97: 65016-005-NC-01F | F97: 5 k | G97: #VALUE! | I97: SE-CELBAR-65061-5 | J97: BRECKNELL | K97: 44592 | O97: ='EQUIPO ENERO 2025'!AP97 -> 0 | P97: =O97 -> 0 | Q97: =AK97 -> 0 | R97: =AL97 -> 0 | S97: =AM97 -> 0 | T97: =AN97 -> 0 | AJ97: ='EQUIPO ENERO 2025'!AP97 -> 0 | AK97: =P97-Z97+AE97+U97 -> 0 | AL97: =Q97-AA97+AF97+V97 -> 0 | AM97: =R97-AB97+AG97+W97 -> 0 | AN97: =S97-AC97+AH97+X97 -> 0 | AO97: =T97-AD97+AI97+Y97 -> 0 | AQ97: =AO97 -> 0
A98: =A97+1 -> 93 | B98: CELDA DE CARGA BARRA 5 K H8C-N5-5KSE-6YWB-SC-D27 ZEMIC | C98: No. 2 | D98: BRECKNELL | E98: H8C-N5-5KSE-6YWB-SC-D27 | F98: 5 k | G98: #VALUE! | I98: SE-CELBAR-5 K | J98: BRECKNELL | K98: 44592 | O98: ='EQUIPO ENERO 2025'!AP98 -> 3 | P98: =O98 -> 3 | Q98: =AK98 -> 3 | R98: =AL98 -> 3 | S98: =AM98 -> 3 | T98: =AN98 -> 3 | AJ98: ='EQUIPO ENERO 2025'!AP98 -> 3 | AK98: =P98-Z98+AE98+U98 -> 3 | AL98: =Q98-AA98+AF98+V98 -> 3 | AM98: =R98-AB98+AG98+W98 -> 3 | AN98: =S98-AC98+AH98+X98 -> 3 | AO98: =T98-AD98+AI98+Y98 -> 3 | AQ98: =AO98 -> 3
A99: =A98+1 -> 94 | B99: CELDA DE CARGA BARRA 5 K PINTADA (USADAS) ZEMIC H8C-N5-5KSE-6YWB-SC-D2 | C99: No. 2 | D99: BRECKNELL | E99: H8C-N5-5KSE-6YWB-SC-D2 | F99: 5 k | G99: #VALUE! | I99: SE-CELBAR- 5 K U | J99: BRECKNELL | K99: 44592 | O99: ='EQUIPO ENERO 2025'!AP99 -> 3 | P99: =O99 -> 3 | Q99: =AK99 -> 3 | R99: =AL99 -> 3 | S99: =AM99 -> 3 | T99: =AN99 -> 3 | AJ99: ='EQUIPO ENERO 2025'!AP99 -> 3 | AK99: =P99-Z99+AE99+U99 -> 3 | AL99: =Q99-AA99+AF99+V99 -> 3 | AM99: =R99-AB99+AG99+W99 -> 3 | AN99: =S99-AC99+AH99+X99 -> 3 | AO99: =T99-AD99+AI99+Y99 -> 3 | AQ99: =AO99 -> 3
A100: =A99+1 -> 95 | B100: CELDA DE CARGA BARRA 50 K 65061-050E-B1-00F | C100: No. 2 | D100: SENSORTRONICS | E100: 65061-050E-B1-00F | F100: 50 k | G100: #VALUE! | H100: Q | I100: SE-CELBAR-65061-50 | J100: VPG | K100: 45505 | L100: 2410004753 | M100: 17 | O100: ='EQUIPO ENERO 2025'!AP100 -> 2 | P100: =O100 -> 2 | Q100: =AK100 -> 2 | R100: =AL100 -> 2 | S100: =AM100 -> 2 | T100: =AN100 -> 2 | AJ100: ='EQUIPO ENERO 2025'!AP100 -> 2 | AK100: =P100-Z100+AE100+U100 -> 2 | AL100: =Q100-AA100+AF100+V100 -> 2 | AM100: =R100-AB100+AG100+W100 -> 2 | AN100: =S100-AC100+AH100+X100 -> 2 | AO100: =T100-AD100+AI100+Y100 -> 2 | AQ100: =AO100 -> 2
A101: =A100+1 -> 96 | B101: CELDA DE CARGA BARRA 40 K 65061-040E-B1-01F | C101: No. 2 | D101: SENSORTRONICS | E101: 65061-040E-BI-01F | F101: 40 k | G101: #VALUE! | J101: VPG | K101: 45505 | L101: 2410004752 | M101: 17 | N101: AGREGADO POR ALDO SOTO | O101: ='EQUIPO ENERO 2025'!AP101 -> 0 | P101: =O101 -> 0 | Q101: =AK101 -> 0 | R101: =AL101 -> 1 | S101: =AM101 -> 1 | T101: =AN101 -> 1 | V101: 1 | AJ101: ='EQUIPO ENERO 2025'!AP101 -> 0 | AK101: =P101-Z101+AE101+U101 -> 0 | AL101: =Q101-AA101+AF101+V101 -> 1 | AM101: =R101-AB101+AG101+W101 -> 1 | AN101: =S101-AC101+AH101+X101 -> 1 | AO101: =T101-AD101+AI101+Y101 -> 1 | AQ101: =AO101 -> 1
...

Sheet EQUIPO MARZO 2025  1
B1: SOLUCIONES EXACTAS, S.A. | AR1: Codigo: FO-SE-053 | AV1: Codigo: FO-SE-053
B3: LISTADO INVENTARIO BODEGAS FEBRERO | AI3: MAR | AK3: MARZO | AR3: Versión: 02 | AV3: Versión: 02
A4: No. | B4: PRODUCTO | C4: No. BODEGA | D4: MARCA | E4: MODELO | F4: CAPACIDAD | G4: IMAGEN | H4: PRECIO | I4: CODIGO INTERNO | J4: PROVEEDOR | K4: FECHA INGRESO BODEGA | L4: FACTURA No. PROVEEDOR | M4: BOLETA INGRESO BODEGA | N4: OBSERVACION | O4: VIENE MES ANTERIOR | P4: EXISTENCIA INICIO SEMANA | U4: INGRESO POR IMPORTACION O COMPRA | Z4: DESCARGA Y/O SALIDA | AE4: DEVOLUCIONES | AJ4: INICIO DE MES | AK4: EXISTENCIA POR SEMANA | AP4: DEMO | AQ4: TOTAL EXISTENCIA MENSUAL | AR4: FACTURA VENTA | AS4: BOLETA DE SALIDA | AT4: ENVIO | AU4: FIRMA ULTIMO INVENTARIO | AV4: FECHA ULTIMA REVISION
P5: 1 | Q5: 2 | R5: 3 | S5: 4 | T5: 5 | U5: 1 | V5: 2 | W5: 3 | X5: 4 | Y5: 5 | Z5: 1 | AA5: 2 | AB5: 3 | AC5: 4 | AD5: 5 | AE5: 1 | AF5: 2 | AG5: 3 | AH5: 4 | AI5: 5 | AK5: 1 | AL5: 2 | AM5: 3 | AN5: 4 | AO5: 5
A6: 1 | B6: ADAPTADOR PARA INDICADOR 9V1.2A MODELO: KEERDA | C6: No. 2 | D6: KEERDA | E6: DZ012ELL090120U | F6: 9V | G6: #VALUE! | H6: 395 | I6: SE-ADAT9V | J6: SIZEIN | K6: 45666 | L6: LK24112701 | M6: 118 | O6: ='EQUIPO FEBRERO 2025 1'!AQ6 -> 43 | P6: =O6 -> 43 | Q6: =AK6 -> 43 | R6: =AL6 -> 43 | S6: =AM6 -> 43 | T6: =AN6 -> 43 | Z6: 2 | AE6: 2 | AJ6: ='EQUIPO ENERO 2025'!AP6 -> 47 | AK6: =P6-Z6+AE6+U6 -> 43 | AL6: =Q6-AA6+AF6+V6 -> 43 | AM6: =R6-AB6+AG6+W6 -> 43 | AN6: =S6-AC6+AH6+X6 -> 43 | AO6: =T6-AD6+AI6+Y6 -> 43 | AQ6: =AO6 -> 43 | AS6: 363
A7: =A6+1 -> 2 | B7: ADAPTADOR GENERICO 9V 600 mA | C7: No.2 | D7: Byp | F7: 9v | K7: 45712 | M7: 162 | O7: ='EQUIPO FEBRERO 2025 1'!AQ7 -> 10 | P7: =O7 -> 10 | Q7: =AK7 -> 9 | R7: =AL7 -> 9 | S7: =AM7 -> 9 | T7: =AN7 -> 9 | Z7: 1 | AK7: =P7-Z7+AE7+U7 -> 9 | AL7: =Q7-AA7+AF7+V7 -> 9 | AM7: =R7-AB7+AG7+W7 -> 9 | AN7: =S7-AC7+AH7+X7 -> 9 | AO7: =T7-AD7+AI7+Y7 -> 9 | AQ7: =AO7 -> 9 | AS7: 351
A8: =A7+1 -> 3 | B8: ADAPTADORES GENERICOS 5 V 1 AMP AC/DC | C8: No. 2 | D8: BRECKNELL | E8: S/M | G8: #VALUE! | I8: SE-ADAP-1 AMP | J8: BRECKNELL | K8: 44592 | O8: ='EQUIPO FEBRERO 2025 1'!AQ8 -> 2 | P8: =O8 -> 2 | Q8: =AK8 -> 2 | R8: =AL8 -> 2 | S8: =AM8 -> 2 | T8: =AN8 -> 2 | AJ8: ='EQUIPO ENERO 2025'!AP8 -> 2 | AK8: =P8-Z8+AE8+U8 -> 2 | AL8: =Q8-AA8+AF8+V8 -> 2 | AM8: =R8-AB8+AG8+W8 -> 2 | AN8: =S8-AC8+AH8+X8 -> 2 | AO8: =T8-AD8+AI8+Y8 -> 2 | AQ8: =AO8 -> 2
A9: =A8+1 -> 4 | B9: ADAPTADORES SBI 505 ORIGINAL AWT05-505896 | C9: No. 2 | D9: AVERY WEIGH TRONIX | E9: AWT05-505896 | G9: #VALUE! | H9: 550 | I9: SE-ADAP-SBI505 | J9: AVERY WEIGH TRONIX | K9: 44592 | O9: ='EQUIPO FEBRERO 2025 1'!AQ9 -> 8 | P9: =O9 -> 8 | Q9: =AK9 -> 8 | R9: =AL9 -> 8 | S9: =AM9 -> 8 | T9: =AN9 -> 8 | AJ9: ='EQUIPO ENERO 2025'!AP9 -> 8 | AK9: =P9-Z9+AE9+U9 -> 8 | AL9: =Q9-AA9+AF9+V9 -> 8 | AM9: =R9-AB9+AG9+W9 -> 8 | AN9: =S9-AC9+AH9+X9 -> 8 | AO9: =T9-AD9+AI9+Y9 -> 8 | AQ9: =AO9 -> 8
A10: =A9+1 -> 5 | B10: ADAPTADOR BI 12T | C10: No. 2 | D10: BRECKNELL | E10: BI 12T | F10: 12t | G10: #VALUE! | I10: SE-ADAP-BI-12T | J10: BRECKNELL | K10: 44592 | O10: ='EQUIPO FEBRERO 2025 1'!AQ10 -> 1 | P10: =O10 -> 1 | Q10: =AK10 -> 1 | R10: =AL10 -> 1 | S10: =AM10 -> 1 | T10: =AN10 -> 1 | AJ10: ='EQUIPO ENERO 2025'!AP10 -> 1 | AK10: =P10-Z10+AE10+U10 -> 1 | AL10: =Q10-AA10+AF10+V10 -> 1 | AM10: =R10-AB10+AG10+W10 -> 1 | AN10: =S10-AC10+AH10+X10 -> 1 | AO10: =T10-AD10+AI10+Y10 -> 1 | AQ10: =AO10 -> 1
A11: =A10+1 -> 6 | B11: ADAPTADOR DE MODULOS INALAMBRICOS SE-7660 | C11: No.2 | E11: SE-ADAPT-7660 | G11: #VALUE! | J11: LOCOSC | K11: 45464 | M11: 87 | O11: ='EQUIPO FEBRERO 2025 1'!AQ11 -> 2 | P11: =O11 -> 2 | Q11: =AK11 -> 2 | R11: =AL11 -> 2 | S11: =AM11 -> 2 | T11: =AN11 -> 2 | AJ11: ='EQUIPO ENERO 2025'!AP11 -> 2 | AK11: =P11-Z11+AE11+U11 -> 2 | AL11: =Q11-AA11+AF11+V11 -> 2 | AM11: =R11-AB11+AG11+W11 -> 2 | AN11: =S11-AC11+AH11+X11 -> 2 | AO11: =T11-AD11+AI11+Y11 -> 2 | AQ11: =AO11 -> 2
A12: =A11+1 -> 7 | B12: ADAPTADOR DE CORRIENTE DE INDICADOR SE7517/ REPARADO DE CABLE | C12: NO.2 | D12: KEERDA | E12: DZ007AHL050100U | F12: 5.0V/1.0Ah | I12: SE-DZ007 | J12: LOCOSC | M12: 113 | O12: ='EQUIPO FEBRERO 2025 1'!AQ12 -> 1 | P12: =O12 -> 1 | Q12: =AK12 -> 1 | R12: =AL12 -> 1 | S12: =AM12 -> 1 | T12: =AN12 -> 1 | AJ12: ='EQUIPO ENERO 2025'!AP12 -> 1 | AK12: =P12-Z12+AE12+U12 -> 1 | AL12: =Q12-AA12+AF12+V12 -> 1 | AM12: =R12-AB12+AG12+W12 -> 1 | AN12: =S12-AC12+AH12+X12 -> 1 | AO12: =T12-AD12+AI12+Y12 -> 1 | AQ12: =AO12 -> 1
A13: =A12+1 -> 8 | B13: ADAPTADORES DE CORRIENTE PARA MODULOS INALAMBRICOS SE-7519A | C13: NO.2 | D13: S/M | E13: ZF120A-0421000 | F13: 4.2V/10A | G13: #VALUE! | I13: SE-ADAP-A | J13: LOCOSC | K13: 45582 | M13: 81 | O13: ='EQUIPO FEBRERO 2025 1'!AQ13 -> 2 | P13: =O13 -> 2 | Q13: =AK13 -> 2 | R13: =AL13 -> 2 | S13: =AM13 -> 2 | T13: =AN13 -> 2 | AJ13: ='EQUIPO ENERO 2025'!AP13 -> 2 | AK13: =P13-Z13+AE13+U13 -> 2 | AL13: =Q13-AA13+AF13+V13 -> 2 | AM13: =R13-AB13+AG13+W13 -> 2 | AN13: =S13-AC13+AH13+X13 -> 2 | AO13: =T13-AD13+AI13+Y13 -> 2 | AQ13: =AO13 -> 2
A14: =A13+1 -> 9 | B14: ARMARIOS ELECTRICOS ST4-420 | C14: No. 2 | D14: BRECKNELL | E14: ST4-420 | G14: #VALUE! | I14: SE-ARMAELEC | J14: BRECKNELL | K14: 44592 | O14: ='EQUIPO FEBRERO 2025 1'!AQ14 -> 3 | P14: =O14 -> 3 | Q14: =AK14 -> 3 | R14: =AL14 -> 3 | S14: =AM14 -> 3 | T14: =AN14 -> 3 | AJ14: ='EQUIPO ENERO 2025'!AP14 -> 3 | AK14: =P14-Z14+AE14+U14 -> 3 | AL14: =Q14-AA14+AF14+V14 -> 3 | AM14: =R14-AB14+AG14+W14 -> 3 | AN14: =S14-AC14+AH14+X14 -> 3 | AO14: =T14-AD14+AI14+Y14 -> 3 | AQ14: =AO14 -> 3
A15: =A14+1 -> 10 | B15: ARGOLLAS PARA BÁSCULAS PESA EJES | C15: NO.2 | D15: S/M | E15: M-20 | F15: S/C | G15: #VALUE! | I15: SE-ARG-PPEJES | J15: LOCOSC | K15: 45673 | L15: 240907-1 | M15: 131 | O15: ='EQUIPO FEBRERO 2025 1'!AQ15 -> 0 | P15: =O15 -> 0 | Q15: =AK15 -> 0 | R15: =AL15 -> 0 | S15: =AM15 -> 0 | T15: =AN15 -> 0 | AJ15: ='EQUIPO ENERO 2025'!AP15 -> 0 | AK15: =P15-Z15+AE15+U15 -> 0 | AL15: =Q15-AA15+AF15+V15 -> 0 | AM15: =R15-AB15+AG15+W15 -> 0 | AN15: =S15-AC15+AH15+X15 -> 0 | AO15: =T15-AD15+AI15+Y15 -> 0 | AQ15: =AO15 -> 0
A16: =A15+1 -> 11 | B16: BALANZA DE BOLSILLO CAPACIDAD DE 200x0.01g | C16: No. 1 | E16: HY-YH-J100120 | F16: 2 000 x 0.01 g | G16: #VALUE! | H16: 150 | I16: SE-FAB-GUA | K16: 44592 | O16: ='EQUIPO FEBRERO 2025 1'!AQ16 -> 5 | P16: =O16 -> 5 | Q16: =AK16 -> 5 | R16: =AL16 -> 5 | S16: =AM16 -> 5 | T16: =AN16 -> 5 | AJ16: ='EQUIPO ENERO 2025'!AP16 -> 5 | AK16: =P16-Z16+AE16+U16 -> 5 | AL16: =Q16-AA16+AF16+V16 -> 5 | AM16: =R16-AB16+AG16+W16 -> 5 | AN16: =S16-AC16+AH16+X16 -> 5 | AO16: =T16-AD16+AI16+Y16 -> 5 | AQ16: =AO16 -> 5
A17: =A16+1 -> 12 | B17: BALANZA DE LABORATORIO 1 000 x0.01g | C17: N/A | D17: ELECTRONIC BALANCE | E17: SE10002K | F17: 1 000 x 0.01 g | G17: #VALUE! | H17: 9180 | I17: SE-WTB1002K | J17: LOCOSC | K17: 45316 | M17: 15 | O17: ='EQUIPO FEBRERO 2025 1'!AQ17 -> 0 | P17: =O17 -> 0 | Q17: =AK17 -> 0 | R17: =AL17 -> 0 | S17: =AM17 -> 0 | T17: =AN17 -> 0 | AJ17: ='EQUIPO ENERO 2025'!AP17 -> 0 | AK17: =P17-Z17+AE17+U17 -> 0 | AL17: =Q17-AA17+AF17+V17 -> 0 | AM17: =R17-AB17+AG17+W17 -> 0 | AN17: =S17-AC17+AH17+X17 -> 0 | AO17: =T17-AD17+AI17+Y17 -> 0 | AQ17: =AO17 -> 0
A18: =A17+1 -> 13 | B18: BALANZA DE LABORATORIO 10000x0.1g | C18: No. 1 | D18: ELECTRONIC BALANCE | E18: SE-WT100001X | F18: 1 000 x 0.1 g | G18: #VALUE! | H18: 4600 | I18: SE-WT100001X | J18: LOCOSC | K18: 45216 | L18: 2015 | M18: 451 | O18: ='EQUIPO FEBRERO 2025 1'!AQ18 -> 0 | P18: =O18 -> 0 | Q18: =AK18 -> 0 | R18: =AL18 -> 0 | S18: =AM18 -> 0 | T18: =AN18 -> 0 | AJ18: ='EQUIPO ENERO 2025'!AP18 -> 0 | AK18: =P18-Z18+AE18+U18 -> 0 | AL18: =Q18-AA18+AF18+V18 -> 0 | AM18: =R18-AB18+AG18+W18 -> 0 | AN18: =S18-AC18+AH18+X18 -> 0 | AO18: =T18-AD18+AI18+Y18 -> 0 | AQ18: =AO18 -> 0
A19: =A18+1 -> 14 | B19: BALANZA DE LABORATORIO 1500g x 0.5g | C19: N/A | D19: ELECTRONIC BALANCE | E19: SE-WT15002KF | F19: 1 500 x 0.05 kg | G19: #VALUE! | H19: 2800 | I19: SE-WT15002KF-5 | J19: LOCOSC | K19: 45107 | L19: LP230224-1 | M19: 393 | O19: ='EQUIPO FEBRERO 2025 1'!AQ19 -> 5 | P19: =O19 -> 5 | Q19: =AK19 -> 5 | R19: =AL19 -> 5 | S19: =AM19 -> 5 | T19: =AN19 -> 5 | AJ19: ='EQUIPO ENERO 2025'!AP19 -> 5 | AK19: =P19-Z19+AE19+U19 -> 5 | AL19: =Q19-AA19+AF19+V19 -> 5 | AM19: =R19-AB19+AG19+W19 -> 5 | AN19: =S19-AC19+AH19+X19 -> 5 | AO19: =T19-AD19+AI19+Y19 -> 5 | AQ19: =AO19 -> 5
A20: =A19+1 -> 15 | B20: BALANZA DE LABORATORIO CAPACIDAD 15 kg x 0.1g | C20: No. 1 | D20: ELECTRONIC BALANCE | E20: SE150001XD | F20: 15 kg x 0.1 g | G20: #VALUE! | H20: 9180 | I20: SE-WT150001XD | J20: LOCOSC | K20: 45316 | M20: 15 | O20: ='EQUIPO FEBRERO 2025 1'!AQ20 -> 0 | P20: =O20 -> 0 | Q20: =AK20 -> 0 | R20: =AL20 -> 0 | S20: =AM20 -> 0 | T20: =AN20 -> 0 | AJ20: ='EQUIPO ENERO 2025'!AP20 -> 0 | AK20: =P20-Z20+AE20+U20 -> 0 | AL20: =Q20-AA20+AF20+V20 -> 0 | AM20: =R20-AB20+AG20+W20 -> 0 | AN20: =S20-AC20+AH20+X20 -> 0 | AO20: =T20-AD20+AI20+Y20 -> 0 | AQ20: =AO20 -> 0
A21: =A20+1 -> 16 | B21: BALANZA DE LABORATORIO CAPACIDAD 300 g x 1 mg | C21: N/A | D21: ELECTRONIC BALANCE | E21: SE-3003GH | F21: 300 g x 1 mg | G21: #VALUE! | H21: 36300 | I21: SE3003GH | J21: LOCOSC | K21: 45299 | M21: 6 | O21: ='EQUIPO FEBRERO 2025 1'!AQ21 -> 0 | P21: =O21 -> 0 | Q21: =AK21 -> 0 | R21: =AL21 -> 0 | S21: =AM21 -> 0 | T21: =AN21 -> 0 | AJ21: ='EQUIPO ENERO 2025'!AP21 -> 0 | AK21: =P21-Z21+AE21+U21 -> 0 | AL21: =Q21-AA21+AF21+V21 -> 0 | AM21: =R21-AB21+AG21+W21 -> 0 | AN21: =S21-AC21+AH21+X21 -> 0 | AO21: =T21-AD21+AI21+Y21 -> 0 | AQ21: =AO21 -> 0
A22: =A21+1 -> 17 | B22: BALANZA ANALITICA CAPACIDAD DE 5 000g x 0.01 g | C22: N/A | D22: ELECTRONIC BALANCE | E22: SE-5 0002CF | F22: 5 000 x 0.01 g | G22: #VALUE! | I22: SE50002CF | J22: LOCOSC | K22: 45336 | L22: 669885E9 | M22: 37 | O22: ='EQUIPO FEBRERO 2025 1'!AQ22 -> 0 | P22: =O22 -> 0 | Q22: =AK22 -> 0 | R22: =AL22 -> 0 | S22: =AM22 -> 0 | T22: =AN22 -> 0 | AJ22: ='EQUIPO ENERO 2025'!AP22 -> 0 | AK22: =P22-Z22+AE22+U22 -> 0 | AL22: =Q22-AA22+AF22+V22 -> 0 | AM22: =R22-AB22+AG22+W22 -> 0 | AN22: =S22-AC22+AH22+X22 -> 0 | AO22: =T22-AD22+AI22+Y22 -> 0 | AQ22: =AO22 -> 0
A23: =A22+1 -> 18 | B23: BALANZA ANALITICA CAPACIDAD DE 1 000 g x 20 mg | C23: N/A | D23: ELECTRONIC BALANCE | E23: SE-10003N | F23: 1 000 g x 20 mg | G23: #VALUE! | I23: SE10003N | J23: LOCOSC | K23: 45336 | L23: 669885E9 | M23: 37 | O23: ='EQUIPO FEBRERO 2025 1'!AQ23 -> 0 | P23: =O23 -> 0 | Q23: =AK23 -> 0 | R23: =AL23 -> 0 | S23: =AM23 -> 0 | T23: =AN23 -> 0 | AJ23: ='EQUIPO ENERO 2025'!AP23 -> 0 | AK23: =P23-Z23+AE23+U23 -> 0 | AL23: =Q23-AA23+AF23+V23 -> 0 | AM23: =R23-AB23+AG23+W23 -> 0 | AN23: =S23-AC23+AH23+X23 -> 0 | AO23: =T23-AD23+AI23+Y23 -> 0 | AQ23: =AO23 -> 0
A24: =A23+1 -> 19 | B24: BALANZA ANALITICA CAPACIDAD DE 210 g x 10 mg | C24: N/A | D24: ELECTRONIC BALANCE | E24: SE-2085A | F24: 210 g x 10 mg | G24: #VALUE! | I24: SE2085A | J24: LOCOSC | K24: 45336 | L24: 669885E9 | M24: 38 | O24: ='EQUIPO FEBRERO 2025 1'!AQ24 -> 0 | P24: =O24 -> 0 | Q24: =AK24 -> 0 | R24: =AL24 -> 0 | S24: =AM24 -> 0 | T24: =AN24 -> 0 | AJ24: ='EQUIPO ENERO 2025'!AP24 -> 0 | AK24: =P24-Z24+AE24+U24 -> 0 | AL24: =Q24-AA24+AF24+V24 -> 0 | AM24: =R24-AB24+AG24+W24 -> 0 | AN24: =S24-AC24+AH24+X24 -> 0 | AO24: =T24-AD24+AI24+Y24 -> 0 | AQ24: =AO24 -> 0
A25: =A24+1 -> 20 | B25: BALANZA DE LABORATORIO CAPACIDAD 420 x 0.001g LUNA | C25: No.1 | E25: SE-LPB423E | F25: 420 x 0.001 g | G25: #VALUE! | I25: LPB423E | J25: ADAM | K25: 45454 | L25: 34687-035292 | M25: 76 | O25: ='EQUIPO FEBRERO 2025 1'!AQ25 -> 0 | P25: =O25 -> 0 | Q25: =AK25 -> 0 | R25: =AL25 -> 0 | S25: =AM25 -> 0 | T25: =AN25 -> 0 | AJ25: ='EQUIPO ENERO 2025'!AP25 -> 0 | AK25: =P25-Z25+AE25+U25 -> 0 | AL25: =Q25-AA25+AF25+V25 -> 0 | AM25: =R25-AB25+AG25+W25 -> 0 | AN25: =S25-AC25+AH25+X25 -> 0 | AO25: =T25-AD25+AI25+Y25 -> 0 | AQ25: =AO25 -> 0
A26: =A25+1 -> 21 | B26: BÁSCULA DE MESA | C26: No. 1 | D26: BRECKNELL | E26: SE-7680W | F26: 3 x 0.005 kg | G26: #VALUE! | H26: 2800 | I26: SE-LP7680-3Kg | J26: LOCOSC | K26: 45574 | L26: LP3211240 | M26: 71 | O26: ='EQUIPO FEBRERO 2025 1'!AQ26 -> 8 | P26: =O26 -> 8 | Q26: =AK26 -> 8 | R26: =AL26 -> 8 | S26: =AM26 -> 8 | T26: =AN26 -> 8 | Z26: 1 | AE26: 1 | AJ26: ='EQUIPO ENERO 2025'!AP26 -> 8 | AK26: =P26-Z26+AE26+U26 -> 8 | AL26: =Q26-AA26+AF26+V26 -> 8 | AM26: =R26-AB26+AG26+W26 -> 8 | AN26: =S26-AC26+AH26+X26 -> 8 | AO26: =T26-AD26+AI26+Y26 -> 8 | AQ26: =AO26 -> 8 | AS26: 362
A27: =A26+1 -> 22 | B27: BÁSCULA DE MESA | C27: No. 1 | D27: BRECKNELL | E27: SE-7680W | F27: 6 x 0.001 kg | G27: #VALUE! | H27: 2800 | I27: SE-LP7680-6Kg | J27: LOCOSC | K27: 45574 | L27: LP3211240 | M27: 71 | O27: ='EQUIPO FEBRERO 2025 1'!AQ27 -> 10 | P27: =O27 -> 10 | Q27: =AK27 -> 10 | R27: =AL27 -> 10 | S27: =AM27 -> 10 | T27: =AN27 -> 10 | AJ27: ='EQUIPO ENERO 2025'!AP27 -> 10 | AK27: =P27-Z27+AE27+U27 -> 10 | AL27: =Q27-AA27+AF27+V27 -> 10 | AM27: =R27-AB27+AG27+W27 -> 10 | AN27: =S27-AC27+AH27+X27 -> 10 | AO27: =T27-AD27+AI27+Y27 -> 10 | AQ27: =AO27 -> 10
A28: =A27+1 -> 23 | B28: BÁSCULA DE MESA | C28: No. 1 | D28: BRECKNELL | E28: SE-7680W | F28: 15 x 0.002 kg | G28: #VALUE! | H28: 2800 | I28: SE-LP7680-15Kg | J28: LOCOSC | K28: 45574 | L28: LP3211240 | M28: 71 | O28: ='EQUIPO FEBRERO 2025 1'!AQ28 -> 6 | P28: =O28 -> 6 | Q28: =AK28 -> 6 | R28: =AL28 -> 6 | S28: =AM28 -> 6 | T28: =AN28 -> 6 | AJ28: ='EQUIPO ENERO 2025'!AP28 -> 6 | AK28: =P28-Z28+AE28+U28 -> 6 | AL28: =Q28-AA28+AF28+V28 -> 6 | AM28: =R28-AB28+AG28+W28 -> 6 | AN28: =S28-AC28+AH28+X28 -> 6 | AO28: =T28-AD28+AI28+Y28 -> 6 | AQ28: =AO28 -> 6 | AS28: 337/PAPYS
A29: =A28+1 -> 24 | B29: BASCULA DE MESA MODELO SE-7680W | C29: No. 1 | D29: BRECKNELL | E29: SE-7680W | F29: 30 x 0.005 kg | G29: #VALUE! | H29: 3000 | I29: SE-LP7680-30kg | J29: LOCOSC | K29: 45107 | L29: LP230224-1 | M29: 390 | O29: ='EQUIPO FEBRERO 2025 1'!AQ29 -> 5 | P29: =O29 -> 5 | Q29: =AK29 -> 5 | R29: =AL29 -> 5 | S29: =AM29 -> 5 | T29: =AN29 -> 5 | AJ29: ='EQUIPO ENERO 2025'!AP29 -> 5 | AK29: =P29-Z29+AE29+U29 -> 5 | AL29: =Q29-AA29+AF29+V29 -> 5 | AM29: =R29-AB29+AG29+W29 -> 5 | AN29: =S29-AC29+AH29+X29 -> 5 | AO29: =T29-AD29+AI29+Y29 -> 5 | AQ29: =AO29 -> 5
A30: =A29+1 -> 25 | B30: BALANZA ELECTRONIC BALANCE MODELO SE-2003CH DE 2000gx1mg | C30: N/A | D30: ELECTRONIC BALANCE | E30: SE-2003CH | F30: 200 x 1 mg | G30: #VALUE! | H30: 6300 | I30: SE-2003CH | J30: LOCOSC | K30: 45139 | L30: 781781092133 | M30: 419 | O30: ='EQUIPO FEBRERO 2025 1'!AQ30 -> 0 | P30: =O30 -> 0 | Q30: =AK30 -> 0 | R30: =AL30 -> 0 | S30: =AM30 -> 0 | T30: =AN30 -> 0 | AJ30: ='EQUIPO ENERO 2025'!AP30 -> 0 | AK30: =P30-Z30+AE30+U30 -> 0 | AL30: =Q30-AA30+AF30+V30 -> 0 | AM30: =R30-AB30+AG30+W30 -> 0 | AN30: =S30-AC30+AH30+X30 -> 0 | AO30: =T30-AD30+AI30+Y30 -> 0 | AQ30: =AO30 -> 0
A31: =A30+1 -> 26 | B31: BASES DE CELDA DE CARGA PARA CELDAS DE ACEROS DE GUATEMALA | C31: NO. 2 | D31: S/M | E31: S/M | G31: #VALUE! | K31: 45568 | M31: 62 | O31: ='EQUIPO FEBRERO 2025 1'!AQ31 -> 2 | P31: =O31 -> 2 | Q31: =AK31 -> 2 | R31: =AL31 -> 2 | S31: =AM31 -> 2 | T31: =AN31 -> 2 | AJ31: ='EQUIPO ENERO 2025'!AP31 -> 2 | AK31: =P31-Z31+AE31+U31 -> 2 | AL31: =Q31-AA31+AF31+V31 -> 2 | AM31: =R31-AB31+AG31+W31 -> 2 | AN31: =S31-AC31+AH31+X31 -> 2 | AO31: =T31-AD31+AI31+Y31 -> 2 | AQ31: =AO31 -> 2
A32: =A31+1 -> 27 | B32: BASCULA COLGANTE CAPACIDAD 5 t LP7650G | C32: NO.2 | D32: BRECKNELL | E32: SE-7650 | F32: 5 T | G32: #VALUE! | H32: 9500 | I32: SE-LP7650G-5T | J32: SIZEN | K32: 45666 | L32: LK24112701 | M32: 117 | O32: ='EQUIPO FEBRERO 2025 1'!AQ32 -> 1 | P32: =O32 -> 1 | Q32: =AK32 -> 1 | R32: =AL32 -> 1 | S32: =AM32 -> 1 | T32: =AN32 -> 1 | AJ32: ='EQUIPO ENERO 2025'!AP32 -> 1 | AK32: =P32-Z32+AE32+U32 -> 1 | AL32: =Q32-AA32+AF32+V32 -> 1 | AM32: =R32-AB32+AG32+W32 -> 1 | AN32: =S32-AC32+AH32+X32 -> 1 | AO32: =T32-AD32+AI32+Y32 -> 1 | AQ32: =AO32 -> 1
A33: =A32+1 -> 28 | B33: BASCULA COLGANTE CAPACIDAD 10 t LP7650G | C33: No. 2 | D33: BRECKNELL | E33: SE-7650 | F33: 10 t | G33: #VALUE! | H33: Q16,800.00 Consultar primero | I33: SE-LP7650G-10T | J33: LOCOSC | K33: 45107 | L33: LP230224-1 | M33: 393 | O33: ='EQUIPO FEBRERO 2025 1'!AQ33 -> 1 | P33: =O33 -> 1 | Q33: =AK33 -> 1 | R33: =AL33 -> 1 | S33: =AM33 -> 1 | T33: =AN33 -> 1 | AJ33: ='EQUIPO ENERO 2025'!AP33 -> 1 | AK33: =P33-Z33+AE33+U33 -> 1 | AL33: =Q33-AA33+AF33+V33 -> 1 | AM33: =R33-AB33+AG33+W33 -> 1 | AN33: =S33-AC33+AH33+X33 -> 1 | AO33: =T33-AD33+AI33+Y33 -> 1 | AQ33: =AO33 -> 1
A34: =A33+1 -> 29 | B34: BASCULA COLGANTE CAPACIDAD 300kg LP7652G | C34: No. 1 | D34: BRECKNELL | E34: SE-7652 | F34: 300 x 0.1 kg | G34: #VALUE! | H34: 650 | I34: SE-COLG-LP7652G | J34: LOCOSC | K34: 45107 | L34: LP230224-1 | M34: 389 | O34: ='EQUIPO FEBRERO 2025 1'!AQ34 -> 11 | P34: =O34 -> 11 | Q34: =AK34 -> 11 | R34: =AL34 -> 11 | S34: =AM34 -> 11 | T34: =AN34 -> 11 | AJ34: ='EQUIPO ENERO 2025'!AP34 -> 11 | AK34: =P34-Z34+AE34+U34 -> 11 | AL34: =Q34-AA34+AF34+V34 -> 11 | AM34: =R34-AB34+AG34+W34 -> 11 | AN34: =S34-AC34+AH34+X34 -> 11 | AO34: =T34-AD34+AI34+Y34 -> 11 | AQ34: =AO34 -> 11
A35: =A34+1 -> 30 | B35: BASCULA COLGANTE PANTALLA LED DE 5 DIGITOS | C35: No. 1 | D35: BRECKNELL | E35: SE-7561 | F35: 300 x 0.1 kg | G35: #VALUE! | H35: 1800 | I35: SE-LP7561E | J35: LOCOSC | K35: 44592 | O35: ='EQUIPO FEBRERO 2025 1'!AQ35 -> 6 | P35: =O35 -> 6 | Q35: =AK35 -> 6 | R35: =AL35 -> 6 | S35: =AM35 -> 6 | T35: =AN35 -> 6 | AJ35: ='EQUIPO ENERO 2025'!AP35 -> 6 | AK35: =P35-Z35+AE35+U35 -> 6 | AL35: =Q35-AA35+AF35+V35 -> 6 | AM35: =R35-AB35+AG35+W35 -> 6 | AN35: =S35-AC35+AH35+X35 -> 6 | AO35: =T35-AD35+AI35+Y35 -> 6 | AQ35: =AO35 -> 6
A36: =A35+1 -> 31 | B36: BASCULA DE MESA CAPACIDAD 30kgx1g | C36: No. 1 | D36: ELECTRONIC BALANCE | E36: SE-WT300001X | F36: 30 kg x 1 g | G36: #VALUE! | H36: 3400 | I36: SE-WT300001X | J36: LOCOSC | K36: 45107 | L36: LP230224-1 | M36: 393 | O36: ='EQUIPO FEBRERO 2025 1'!AQ36 -> 4 | P36: =O36 -> 4 | Q36: =AK36 -> 4 | R36: =AL36 -> 4 | S36: =AM36 -> 4 | T36: =AN36 -> 4 | AJ36: ='EQUIPO ENERO 2025'!AP36 -> 4 | AK36: =P36-Z36+AE36+U36 -> 4 | AL36: =Q36-AA36+AF36+V36 -> 4 | AM36: =R36-AB36+AG36+W36 -> 4 | AN36: =S36-AC36+AH36+X36 -> 4 | AO36: =T36-AD36+AI36+Y36 -> 4 | AQ36: =AO36 -> 4
A37: =A36+1 -> 32 | B37: BASCULA DE MESA MODELO SE-Y2-208 CAPACIDAD 40kg X 5g | C37: No. 1 | D37: TECNO SCALE | E37: SE-Y2-208 | F37: 40 kg x 5 g | G37: #VALUE! | H37: 550 | I37: SE-Y2-208 | J37: LOCOSC | K37: 45328 | L37: LP230224-1 | M37: 32 | N37: AUTORIZADO POR WILLIAM SÁNCHEZ | O37: ='EQUIPO FEBRERO 2025 1'!AQ37 -> 12 | P37: =O37 -> 12 | Q37: =AK37 -> 12 | R37: =AL37 -> 12 | S37: =AM37 -> 12 | T37: =AN37 -> 12 | Z37: 12 | AE37: 12 | AJ37: ='EQUIPO ENERO 2025'!AP37 -> 14 | AK37: =P37-Z37+AE37+U37 -> 12 | AL37: =Q37-AA37+AF37+V37 -> 12 | AM37: =R37-AB37+AG37+W37 -> 12 | AN37: =S37-AC37+AH37+X37 -> 12 | AO37: =T37-AD37+AI37+Y37 -> 12 | AQ37: =AO37 -> 12
A38: =A37+1 -> 33 | B38: BASCULA DE PISO ACERO INOXIDABLE CAPACIDAD 150kg DE 40X50 | C38: No. 1 | D38: BRECKNELL | E38: SE-7610W | F38: 150 x 0.02 kg | G38: #VALUE! | H38: 7500 | I38: SE-7510W-150kg | J38: LOCOSC | K38: 45107 | L38: LP230224-1 | M38: 392 | N38: ACEROS | O38: ='EQUIPO FEBRERO 2025 1'!AQ38 -> 5 | P38: =O38 -> 5 | Q38: =AK38 -> 5 | R38: =AL38 -> 5 | S38: =AM38 -> 5 | T38: =AN38 -> 5 | AJ38: ='EQUIPO ENERO 2025'!AP38 -> 5 | AK38: =P38-Z38+AE38+U38 -> 5 | AL38: =Q38-AA38+AF38+V38 -> 5 | AM38: =R38-AB38+AG38+W38 -> 5 | AN38: =S38-AC38+AH38+X38 -> 5 | AO38: =T38-AD38+AI38+Y38 -> 5 | AP38: 1 | AQ38: =AO38 -> 5
A39: =A38+1 -> 34 | B39: BÁSCULA DE PISO SS ACERO INOXIDABLE CAPACIDAD 150 kg DE 60 x 60 cm | C39: NO. 1 | D39: BRECKNELL | E39: SE-7610WSS | F39: 150 x 0.02 kg | G39: #VALUE! | H39: 10800 | I39: SE7610W-SS-6060-150kg | J39: LOCOSC | K39: 45673 | L39: 240907-1 | M39: 126 | O39: ='EQUIPO FEBRERO 2025 1'!AQ39 -> 5 | P39: =O39 -> 5 | Q39: =AK39 -> 5 | R39: =AL39 -> 5 | S39: =AM39 -> 5 | T39: =AN39 -> 5 | AJ39: ='EQUIPO ENERO 2025'!AP39 -> 5 | AK39: =P39-Z39+AE39+U39 -> 5 | AL39: =Q39-AA39+AF39+V39 -> 5 | AM39: =R39-AB39+AG39+W39 -> 5 | AN39: =S39-AC39+AH39+X39 -> 5 | AO39: =T39-AD39+AI39+Y39 -> 5 | AP39: 1 | AQ39: =AO39 -> 5
A40: =A39+1 -> 35 | B40: BASCULA DE PISO CAPACIDAD 30kg DE 40X40 | C40: No. 1 | D40: BRECKNELL | E40: SE-7610 | F40: 30 x 0.005 kg | G40: #VALUE! | H40: 2800 | I40: SE-LP7610-30kg | J40: LOCOSC | K40: 45574 | L40: LP3211240 | M40: 71 | N40: ALCSA AE0230329005/ SERIALES 240421001 Y 240421002 MAYALATEX | O40: ='EQUIPO FEBRERO 2025 1'!AQ40 -> 8 | P40: =O40 -> 8 | Q40: =AK40 -> 8 | R40: =AL40 -> 8 | S40: =AM40 -> 6 | T40: =AN40 -> 6 | Z40: 1 | AB40: 2 | AE40: 1 | AJ40: ='EQUIPO ENERO 2025'!AP40 -> 8 | AK40: =P40-Z40+AE40+U40 -> 8 | AL40: =Q40-AA40+AF40+V40 -> 8 | AM40: =R40-AB40+AG40+W40 -> 6 | AN40: =S40-AC40+AH40+X40 -> 6 | AO40: =T40-AD40+AI40+Y40 -> 6 | AP40: 1 | AQ40: =AO40 -> 6 | AR40: 1125270060 | AS40: 357/369
A41: =A40+1 -> 36 | B41: BASCULA DE PISO CAPACIDAD 60kg DE 40X50 | C41: No. 1 | D41: BRECKNELL | E41: SE-7610 | F41: 60 x 0.01 kg | G41: #VALUE! | H41: 2800 | I41: SE-LP7610-60kg | J41: LOCOSC | K41: 45574 | L41: LP3211240 | M41: 71 | O41: ='EQUIPO FEBRERO 2025 1'!AQ41 -> 2 | P41: =O41 -> 2 | Q41: =AK41 -> 2 | R41: =AL41 -> 2 | S41: =AM41 -> 2 | T41: =AN41 -> 2 | AJ41: ='EQUIPO ENERO 2025'!AP41 -> 2 | AK41: =P41-Z41+AE41+U41 -> 2 | AL41: =Q41-AA41+AF41+V41 -> 2 | AM41: =R41-AB41+AG41+W41 -> 2 | AN41: =S41-AC41+AH41+X41 -> 2 | AO41: =T41-AD41+AI41+Y41 -> 2 | AP41: 0 | AQ41: =AO41 -> 2
A42: =A41+1 -> 37 | B42: BASCULA DE PISO PLATAFORMA /ABS CAJA | C42: No. 1 | D42: BRECKNELL | E42: SE-LP7611 | F42: 600 x 0.5 kg | G42: #VALUE! | H42: 5500 | I42: SE7611J-5060-600kg | J42: LOCOSC | K42: 45673 | L42: 240907-1 | M42: 127 | N42: AG SERIE 241012005 | O42: ='EQUIPO FEBRERO 2025 1'!AQ42 -> 10 | P42: =O42 -> 10 | Q42: =AK42 -> 9 | R42: =AL42 -> 9 | S42: =AM42 -> 9 | T42: =AN42 -> 9 | Z42: 2 | AE42: 1 | AJ42: ='EQUIPO ENERO 2025'!AP42 -> 10 | AK42: =P42-Z42+AE42+U42 -> 9 | AL42: =Q42-AA42+AF42+V42 -> 9 | AM42: =R42-AB42+AG42+W42 -> 9 | AN42: =S42-AC42+AH42+X42 -> 9 | AO42: =T42-AD42+AI42+Y42 -> 9 | AP42: 1 | AQ42: =AO42 -> 9 | AR42: 1898398354 | AS42: 356/358
A43: =A42+1 -> 38 | B43: BÁSCULA DE PLATAFORMA SE7611 DE 1 000 kg | C43: LAB | D43: BRECKNELL | E43: SE7611T | F43: 1 000 kg | G43: #VALUE! | I43: SE7611-1X1M-1T | J43: LOCOSC | K43: 45673 | L43: 240907-1 | M43: 128 | O43: ='EQUIPO FEBRERO 2025 1'!AQ43 -> 10 | P43: =O43 -> 10 | Q43: =AK43 -> 10 | R43: =AL43 -> 10 | S43: =AM43 -> 10 | T43: =AN43 -> 10 | AJ43: ='EQUIPO ENERO 2025'!AP43 -> 10 | AK43: =P43-Z43+AE43+U43 -> 10 | AL43: =Q43-AA43+AF43+V43 -> 10 | AM43: =R43-AB43+AG43+W43 -> 10 | AN43: =S43-AC43+AH43+X43 -> 10 | AO43: =T43-AD43+AI43+Y43 -> 10 | AP43: 1 | AQ43: =AO43 -> 10 | AS43: 330
A44: =A43+1 -> 39 | B44: BASCULA ELECTRNICA SK 10 WP | C44: No. 1 | D44: AND | E44: SE-SK10WP | F44: 10 x 0.02 kg | G44: #VALUE! | H44: 2000 | I44: SE-BASELE-SK10KWP | J44: AND | K44: 44592 | O44: ='EQUIPO FEBRERO 2025 1'!AQ44 -> 1 | P44: =O44 -> 1 | Q44: =AK44 -> 1 | R44: =AL44 -> 1 | S44: =AM44 -> 1 | T44: =AN44 -> 1 | AJ44: ='EQUIPO ENERO 2025'!AP44 -> 1 | AK44: =P44-Z44+AE44+U44 -> 1 | AL44: =Q44-AA44+AF44+V44 -> 1 | AM44: =R44-AB44+AG44+W44 -> 1 | AN44: =S44-AC44+AH44+X44 -> 1 | AO44: =T44-AD44+AI44+Y44 -> 1 | AQ44: =AO44 -> 1
A45: =A44+1 -> 40 | B45: BASCULA ELECTRONICA 405 15 K | C45: No. 1 | D45: BRECKNELL | E45: SE-405 | F45: 15 x 0.002 kg | G45: #VALUE! | H45: 1500 | I45: SE-BASELE-405 | J45: BRECKNELL | K45: 44592 | O45: ='EQUIPO FEBRERO 2025 1'!AQ45 -> 1 | P45: =O45 -> 1 | Q45: =AK45 -> 1 | R45: =AL45 -> 1 | S45: =AM45 -> 1 | T45: =AN45 -> 1 | AJ45: ='EQUIPO ENERO 2025'!AP45 -> 1 | AK45: =P45-Z45+AE45+U45 -> 1 | AL45: =Q45-AA45+AF45+V45 -> 1 | AM45: =R45-AB45+AG45+W45 -> 1 | AN45: =S45-AC45+AH45+X45 -> 1 | AO45: =T45-AD45+AI45+Y45 -> 1 | AQ45: =AO45 -> 1
A46: =A45+1 -> 41 | B46: BASCULA ELECTRONICA C 3235 6 K | C46: No. 1 | D46: BRECKNELL | E46: SE-3235 | F46: 6 x 0.001 kg | G46: #VALUE! | H46: 3200 | I46: SE-BASELE-BRCK-C3235-6 | J46: BRECKNELL | K46: 44592 | O46: ='EQUIPO FEBRERO 2025 1'!AQ46 -> 0 | P46: =O46 -> 0 | Q46: =AK46 -> 0 | R46: =AL46 -> 0 | S46: =AM46 -> 0 | T46: =AN46 -> 0 | AJ46: ='EQUIPO ENERO 2025'!AP46 -> 0 | AK46: =P46-Z46+AE46+U46 -> 0 | AL46: =Q46-AA46+AF46+V46 -> 0 | AM46: =R46-AB46+AG46+W46 -> 0 | AN46: =S46-AC46+AH46+X46 -> 0 | AO46: =T46-AD46+AI46+Y46 -> 0 | AQ46: =AO46 -> 0
A47: =A46+1 -> 42 | B47: BASCULA ELECTRONICA C 3235 6 K (PARA DEMO) | C47: No. 1 | D47: BRECKNELL | E47: SE-3235 | F47: 6 x 0.001 kg | G47: #VALUE! | H47: 3200 | I47: SE-BASELE-BRCK-C3235-6-D | J47: BRECKNELL | K47: 44592 | O47: ='EQUIPO FEBRERO 2025 1'!AQ47 -> 1 | P47: =O47 -> 1 | Q47: =AK47 -> 1 | R47: =AL47 -> 1 | S47: =AM47 -> 1 | T47: =AN47 -> 1 | AJ47: ='EQUIPO ENERO 2025'!AP47 -> 1 | AK47: =P47-Z47+AE47+U47 -> 1 | AL47: =Q47-AA47+AF47+V47 -> 1 | AM47: =R47-AB47+AG47+W47 -> 1 | AN47: =S47-AC47+AH47+X47 -> 1 | AO47: =T47-AD47+AI47+Y47 -> 1 | AP47: 1 | AQ47: =AO47 -> 1
A48: =A47+1 -> 43 | B48: BASCULA ELECTRONICA COLGANTE BRECKNELL 45 K | C48: No. 1 | D48: BRECKNELL | E48: ELECTROSAMSON SE-ESN | F48: 45 x 0.05 kg | G48: #VALUE! | H48: 1725 | I48: SE-GE-BEC-ES-45K | J48: BRECKNELL | K48: 45693 | L48: 2130012 | M48: 153 | N48: IMSA/YEGUADA | O48: ='EQUIPO FEBRERO 2025 1'!AQ48 -> 3 | P48: =O48 -> 3 | Q48: =AK48 -> 3 | R48: =AL48 -> 3 | S48: =AM48 -> 3 | T48: =AN48 -> 3 | AJ48: ='EQUIPO ENERO 2025'!AP48 -> 1 | AK48: =P48-Z48+AE48+U48 -> 3 | AL48: =Q48-AA48+AF48+V48 -> 3 | AM48: =R48-AB48+AG48+W48 -> 3 | AN48: =S48-AC48+AH48+X48 -> 3 | AO48: =T48-AD48+AI48+Y48 -> 3 | AQ48: =AO48 -> 3 | AR48: 2774353240/1934771204 | AS48: 323/328
A49: =A48+1 -> 44 | B49: BASCULA ELECTRONICA SK 10 KEG | C49: No. 1 | D49: AND | E49: SE-SK10KEG | F49: 10 x 0.005 kg | G49: #VALUE! | H49: 1500 | I49: SE-BASELE-SK10KEG | J49: AND | K49: 44592 | O49: ='EQUIPO FEBRERO 2025 1'!AQ49 -> 1 | P49: =O49 -> 1 | Q49: =AK49 -> 1 | R49: =AL49 -> 1 | S49: =AM49 -> 1 | T49: =AN49 -> 1 | AJ49: ='EQUIPO ENERO 2025'!AP49 -> 1 | AK49: =P49-Z49+AE49+U49 -> 1 | AL49: =Q49-AA49+AF49+V49 -> 1 | AM49: =R49-AB49+AG49+W49 -> 1 | AN49: =S49-AC49+AH49+X49 -> 1 | AO49: =T49-AD49+AI49+Y49 -> 1 | AQ49: =AO49 -> 1
A50: =A49+1 -> 45 | B50: BASCULA ELECTRONICA SK 20 KEG | C50: No. 1 | D50: AND | E50: SE-SK20KEG | F50: 20 x 0.1 kg | G50: #VALUE! | H50: 1500 | I50: SE-BASELE-SK20KEG | J50: AND | K50: 44592 | O50: ='EQUIPO FEBRERO 2025 1'!AQ50 -> 1 | P50: =O50 -> 1 | Q50: =AK50 -> 1 | R50: =AL50 -> 1 | S50: =AM50 -> 1 | T50: =AN50 -> 1 | AJ50: ='EQUIPO ENERO 2025'!AP50 -> 1 | AK50: =P50-Z50+AE50+U50 -> 1 | AL50: =Q50-AA50+AF50+V50 -> 1 | AM50: =R50-AB50+AG50+W50 -> 1 | AN50: =S50-AC50+AH50+X50 -> 1 | AO50: =T50-AD50+AI50+Y50 -> 1 | AQ50: =AO50 -> 1
A51: =A50+1 -> 46 | B51: BASCULA N1124-LL MECANICA MODELO SE-1124B | C51: N/A | D51: FAIRBANKS MORSE | E51: SE-1124B | F51: 1 200 x 0.5 lb | G51: #VALUE! | H51: 9800 | I51: SE-BASC-MECA | J51: SIDASA | K51: 45315 | L51: 3673178618 | M51: 11 | O51: ='EQUIPO FEBRERO 2025 1'!AQ51 -> 0 | P51: =O51 -> 0 | Q51: =AK51 -> 0 | R51: =AL51 -> 0 | S51: =AM51 -> 0 | T51: =AN51 -> 0 | AJ51: ='EQUIPO ENERO 2025'!AP51 -> 0 | AK51: =P51-Z51+AE51+U51 -> 0 | AL51: =Q51-AA51+AF51+V51 -> 0 | AM51: =R51-AB51+AG51+W51 -> 0 | AN51: =S51-AC51+AH51+X51 -> 0 | AO51: =T51-AD51+AI51+Y51 -> 0 | AQ51: =AO51 -> 0
A52: =A51+1 -> 47 | B52: BASCULA TMF-30kg | C52: No. 2 | D52: TM | E52: TMF | F52: 30 x 0.005 kg | G52: #VALUE! | H52: 4800 | I52: SE-BAS-TMF-30 | J52: LOCOSC | K52: 45107 | L52: LP230224-1 | M52: 393 | N52: PRUEBAS OFICINA/33023202 3209 VESUVIO | O52: ='EQUIPO FEBRERO 2025 1'!AQ52 -> 1 | P52: =O52 -> 1 | Q52: =AK52 -> 1 | R52: =AL52 -> 1 | S52: =AM52 -> -1 | T52: =AN52 -> -1 | Z52: 1 | AB52: 2 | AE52: 1 | AJ52: ='EQUIPO ENERO 2025'!AP52 -> 1 | AK52: =P52+U52-Z52+AE52 -> 1 | AL52: =Q52-AA52+AF52+V52 -> 1 | AM52: =R52-AB52+AG52+W52 -> -1 | AN52: =S52-AC52+AH52+X52 -> -1 | AO52: =T52-AD52+AI52+Y52 -> -1 | AQ52: =AO52 -> -1 | AR52: 2346207087 | AS52: 364
A53: =A52+1 -> 48 | B53: BASCULA-TMF-15K | C53: No. 2 | D53: TM | F53: 15 x 0.001 kg | G53: #VALUE! | H53: 4800 | I53: SE-BASC-TMF | J53: LOCOSC | K53: 44592 | O53: ='EQUIPO FEBRERO 2025 1'!AQ53 -> 1 | P53: =O53 -> 1 | Q53: =AK53 -> 1 | R53: =AL53 -> 1 | S53: =AM53 -> 1 | T53: =AN53 -> 1 | AJ53: ='EQUIPO ENERO 2025'!AP53 -> 1 | AK53: =P53-Z53+AE53+U53 -> 1 | AL53: =Q53-AA53+AF53+V53 -> 1 | AM53: =R53-AB53+AG53+W53 -> 1 | AN53: =S53-AC53+AH53+X53 -> 1 | AO53: =T53-AD53+AI53+Y53 -> 1 | AQ53: =AO53 -> 1
A54: =A53+1 -> 49 | B54: BASCULA PESA EJES CON MARCO/INDICADOR LP7561 (SOLO MODULOS X2PADS) | C54: LAB | D54: TECNO SCALE | E54: SE-LP7662 | F54: 30 t | G54: #VALUE! | I54: SE7662-1530-30T*2PADS | J54: LOCOSC | K54: 45687 | L54: 240907-1 | M54: 144 | O54: ='EQUIPO FEBRERO 2025 1'!AQ54 -> 4 | P54: =O54 -> 4 | Q54: =AK54 -> 4 | R54: =AL54 -> 4 | S54: =AM54 -> 4 | T54: =AN54 -> 4 | AJ54: ='EQUIPO ENERO 2025'!AP54 -> 4 | AK54: =P54-Z54+AE54+U54 -> 4 | AL54: =Q54-AA54+AF54+V54 -> 4 | AM54: =R54-AB54+AG54+W54 -> 4 | AN54: =S54-AC54+AH54+X54 -> 4 | AO54: =T54-AD54+AI54+Y54 -> 4 | AQ54: =AO54 -> 4
A55: =A54+1 -> 50 | B55: BASCULA PESA EJES/INDICADOR LP7561 | C55: No.1 | D55: TECNO SCALE | E55: SE-7662 | F55: 30T | G55: #VALUE! | I55: SE-7662-1530-30T*2 PADS | J55: LOCOSC | K55: 45566 | L55: LP240702-2 | M55: 68 | N55: INGRESADO POR ALDO SOTO EN ESTE MES DE JULIO 2025 | O55: ='EQUIPO FEBRERO 2025 1'!AQ55 -> 1 | P55: =O55 -> 1 | Q55: =AK55 -> 1 | R55: =AL55 -> 1 | S55: =AM55 -> 1 | T55: =AN55 -> 1 | AJ55: ='EQUIPO ENERO 2025'!AP55 -> 0 | AK55: =P55-Z55+AE55+U55 -> 1 | AL55: =Q55-AA55+AF55+V55 -> 1 | AM55: =R55-AB55+AG55+W55 -> 1 | AN55: =S55-AC55+AH55+X55 -> 1 | AO55: =T55-AD55+AI55+Y55 -> 1 | AQ55: =AO55 -> 1
A56: =A55+1 -> 51 | B56: BASCULA PESA ANIMAL (CERDOS) SE-7628A | C56: No.1 | D56: BRECKNELL | E56: SE-7628A | F56: 2 T | G56: #VALUE! | I56: SE-7628A-1215-2T | J56: LOCOSC | K56: 45566 | L56: LP240702-2 | M56: 75 | O56: ='EQUIPO FEBRERO 2025 1'!AQ56 -> 2 | P56: =O56 -> 2 | Q56: =AK56 -> 2 | R56: =AL56 -> 2 | S56: =AM56 -> 2 | T56: =AN56 -> 2 | AJ56: ='EQUIPO ENERO 2025'!AP56 -> 2 | AK56: =P56-Z56+AE56+U56 -> 2 | AL56: =Q56-AA56+AF56+V56 -> 2 | AM56: =R56-AB56+AG56+W56 -> 2 | AN56: =S56-AC56+AH56+X56 -> 2 | AO56: =T56-AD56+AI56+Y56 -> 2 | AQ56: =AO56 -> 2
A57: =A56+1 -> 52 | B57: BASCULA PESA ANIMAL (GANADO) SE-7628A | C57: No.1 | D57: BRECKNELL | E57: SE-7628A | F57: 1.5T | G57: #VALUE! | I57: SE-7628A-0923-1.5T | J57: LOCOSC | K57: 45566 | L57: LP240702-2 | M57: 75 | O57: ='EQUIPO FEBRERO 2025 1'!AQ57 -> 7 | P57: =O57 -> 7 | Q57: =AK57 -> 7 | R57: =AL57 -> 7 | S57: =AM57 -> 7 | T57: =AN57 -> 7 | AJ57: ='EQUIPO ENERO 2025'!AP57 -> 7 | AK57: =P57-Z57+AE57+U57 -> 7 | AL57: =Q57-AA57+AF57+V57 -> 7 | AM57: =R57-AB57+AG57+W57 -> 7 | AN57: =S57-AC57+AH57+X57 -> 7 | AO57: =T57-AD57+AI57+Y57 -> 7 | AQ57: =AO57 -> 7
A58: =A57+1 -> 53 | B58: BÁSCULA BANDA DINAMICA INCLUYE 1 INDICADOR CON ARMARIO, 4 CELDAS DE CARGA TIPO S TSC 500 kg METTLER TOLEDO, 8 RODILLOS Y 1 ESTRUCTURA DE METAL | D58: TECNO SCALE | E58: SE-ICS-17A | F58: 2 T | J58: YORK | K58: 45687 | L58: 04YK01K602 | M58: 141 | O58: ='EQUIPO FEBRERO 2025 1'!AQ58 -> 1 | P58: =O58 -> 1 | Q58: =AK58 -> 1 | R58: =AL58 -> 1 | S58: =AM58 -> 1 | T58: =AN58 -> 1 | AJ58: ='EQUIPO ENERO 2025'!AP58 -> 1 | AK58: =P58-Z58+AE58+U58 -> 1 | AL58: =Q58-AA58+AF58+V58 -> 1 | AM58: =R58-AB58+AG58+W58 -> 1 | AN58: =S58-AC58+AH58+X58 -> 1 | AO58: =T58-AD58+AI58+Y58 -> 1 | AQ58: =AO58 -> 1
A59: =A58+1 -> 54 | B59: BÁSCULA CAMIONERA 50 T | D59: REVUELTA / AVERY | E59: ZM405 | F59: 50 T | K59: 45689 | M59: 151 | N59: SE COMPRO LOCAL/BETHEL | O59: ='EQUIPO FEBRERO 2025 1'!AQ59 -> 1 | P59: =O59 -> 1 | Q59: =AK59 -> 1 | R59: =AL59 -> 1 | S59: =AM59 -> 1 | T59: =AN59 -> 1 | AJ59: ='EQUIPO ENERO 2025'!AP60 -> 34 | AK59: =P59-Z59+AE59+U59 -> 1 | AL59: =Q59-AA59+AF59+V59 -> 1 | AM59: =R59-AB59+AG59+W59 -> 1 | AN59: =S59-AC59+AH59+X59 -> 1 | AO59: =T59-AD59+AI59+Y59 -> 1 | AQ59: =AO59 -> 1
A60: =A59+1 -> 55 | B60: BATERIAS 4V4AH | C60: No. 2 | D60: S/M | E60: S/M | F60: 4V | G60: #VALUE! | H60: 300 | I60: SE-BAT4V | J60: LOCOSC | K60: 45107 | L60: LP230224-1 | M60: 387 | N60: HABILITACIÓN BASCULAS DE SUPERMERCADO | O60: ='EQUIPO FEBRERO 2025 1'!AQ60 -> 32 | P60: =O60 -> 32 | Q60: =AK60 -> 30 | R60: =AL60 -> 30 | S60: =AM60 -> 30 | T60: =AN60 -> 30 | Z60: 2 | AJ60: ='EQUIPO ENERO 2025'!AP60 -> 34 | AK60: =P60-Z60+AE60+U60 -> 30 | AL60: =Q60-AA60+AF60+V60 -> 30 | AM60: =R60-AB60+AG60+W60 -> 30 | AN60: =S60-AC60+AH60+X60 -> 30 | AO60: =T60-AD60+AI60+Y60 -> 30 | AQ60: =AO60 -> 30 | AS60: 354
A61: =A60+1 -> 56 | B61: BATERIAS 6V4AH | C61: No. 2 | D61: S/M | E61: S/M | F61: 6V | G61: #VALUE! | H61: 300 | I61: SE-BAT6V | J61: LOCOSC | K61: 45107 | L61: LP230224-1 | M61: 387 | N61: INGUAMASA | O61: ='EQUIPO FEBRERO 2025 1'!AQ61 -> 53 | P61: =O61 -> 53 | Q61: =AK61 -> 53 | R61: =AL61 -> 53 | S61: =AM61 -> 51 | T61: =AN61 -> 51 | Z61: 2 | AB61: 2 | AE61: 2 | AJ61: ='EQUIPO ENERO 2025'!AP61 -> 58 | AK61: =P61-Z61+AE61+U61 -> 53 | AL61: =Q61-AA61+AF61+V61 -> 53 | AM61: =R61-AB61+AG61+W61 -> 51 | AN61: =S61-AC61+AH61+X61 -> 51 | AO61: =T61-AD61+AI61+Y61 -> 51 | AQ61: =AO61 -> 51 | AR61: 1846037081 | AS61: 363/367
A62: =A61+1 -> 57 | B62: BATERIAS 6V8A NIPPON | C62: NO. 2 | E62: S/M | F62: 6V | M62: 72 | O62: ='EQUIPO FEBRERO 2025 1'!AQ62 -> 0 | P62: =O62 -> 0 | Q62: =AK62 -> 0 | R62: =AL62 -> 0 | S62: =AM62 -> 0 | T62: =AN62 -> 0 | AJ62: ='EQUIPO ENERO 2025'!AP62 -> 0 | AK62: =P62-Z62+AE62+U62 -> 0 | AL62: =Q62-AA62+AF62+V62 -> 0 | AM62: =R62-AB62+AG62+W62 -> 0 | AN62: =S62-AC62+AH62+X62 -> 0 | AO62: =T62-AD62+AI62+Y62 -> 0 | AQ62: =AO62 -> 0
A63: =A62+1 -> 58 | B63: BATERIAS 3.7V /2000MAH | C63: NO.2 | D63: S/M | E63: GDICR18650 | F63: 3.7V/2000mAH | G63: #VALUE! | I63: SE-BAT3V | J63: LOCOSC | K63: 45574 | L63: LP3211240 | M63: 75 | O63: ='EQUIPO FEBRERO 2025 1'!AQ63 -> 24 | P63: =O63 -> 24 | Q63: =AK63 -> 24 | R63: =AL63 -> 24 | S63: =AM63 -> 24 | T63: =AN63 -> 24 | AJ63: ='EQUIPO ENERO 2025'!AP63 -> 25 | AK63: =P63-Z63+AE63+U63 -> 24 | AL63: =Q63-AA63+AF63+V63 -> 24 | AM63: =R63-AB63+AG63+W63 -> 24 | AN63: =S63-AC63+AH63+X63 -> 24 | AO63: =T63-AD63+AI63+Y63 -> 24 | AQ63: =AO63 -> 24 | AS63: 320/COPASA
A64: =A63+1 -> 59 | B64: BATERIAS 3.7V /4000mAh | C64: NO.2 | D64: S/M | E64: LPB04050 152P | F64: 3.7V/4000mAh | G64: #VALUE! | I64: SE-BAT3V- | J64: LOCOSC | K64: 45574 | L64: LP3211240 | M64: 75 | O64: ='EQUIPO FEBRERO 2025 1'!AQ64 -> 45 | P64: =O64 -> 45 | Q64: =AK64 -> 45 | R64: =AL64 -> 45 | S64: =AM64 -> 45 | T64: =AN64 -> 45 | AJ64: ='EQUIPO ENERO 2025'!AP64 -> 45 | AK64: =P64-Z64+AE64+U64 -> 45 | AL64: =Q64-AA64+AF64+V64 -> 45 | AM64: =R64-AB64+AG64+W64 -> 45 | AN64: =S64-AC64+AH64+X64 -> 45 | AO64: =T64-AD64+AI64+Y64 -> 45 | AQ64: =AO64 -> 45
A65: =A64+1 -> 60 | B65: BATERIAS 6V/5Ah | C65: NO. 2 | D65: S/M | E65: DJW6-5.0 | F65: 6V/5mAH | G65: #VALUE! | I65: SE-BAT6V/5 | J65: LOCOSC | K65: 45673 | L65: 240907-1 | M65: 130 | N65: ARROCERA LOS CORRALES INSTALADA EN BASCULAS | O65: ='EQUIPO FEBRERO 2025 1'!AQ65 -> 2 | P65: =O65 -> 2 | Q65: =AK65 -> 2 | R65: =AL65 -> 2 | S65: =AM65 -> 2 | T65: =AN65 -> 2 | AJ65: ='EQUIPO ENERO 2025'!AP65 -> 4 | AK65: =P65-Z65+AE65+U65 -> 2 | AL65: =Q65-AA65+AF65+V65 -> 2 | AM65: =R65-AB65+AG65+W65 -> 2 | AN65: =S65-AC65+AH65+X65 -> 2 | AO65: =T65-AD65+AI65+Y65 -> 2 | AQ65: =AO65 -> 2 | AR65: 3956690624 | AS65: 338
A66: =A65+1 -> 61 | B66: BATERIAS 12V/7.0Ah PARA INDICADOR LP75819 | C66: NO. 2 | D66: S/M | E66: DJW12-7.0 | F66: 12V/7.0mAh | G66: #VALUE! | I66: SE-BAT12V/7 | J66: LOCOSC | K66: 45673 | L66: 240907-1 | M66: 131 | O66: ='EQUIPO FEBRERO 2025 1'!AQ66 -> 10 | P66: =O66 -> 10 | Q66: =AK66 -> 10 | R66: =AL66 -> 10 | S66: =AM66 -> 10 | T66: =AN66 -> 10 | AJ66: ='EQUIPO ENERO 2025'!AP66 -> 10 | AK66: =P66-Z66+AE66+U66 -> 10 | AL66: =Q66-AA66+AF66+V66 -> 10 | AM66: =R66-AB66+AG66+W66 -> 10 | AN66: =S66-AC66+AH66+X66 -> 10 | AO66: =T66-AD66+AI66+Y66 -> 10 | AQ66: =AO66 -> 10
A67: =A66+1 -> 62 | B67: CABLE CELDA DE CARGA MTX (6 PINES) | C67: No. 2 | D67: METTLER TOLEDO | E67: MTX | G67: #VALUE! | I67: SE-CABLE-MTX | K67: 44592 | O67: ='EQUIPO FEBRERO 2025 1'!AQ67 -> 0 | P67: =O67 -> 0 | Q67: =AK67 -> 0 | R67: =AL67 -> 0 | S67: =AM67 -> 0 | T67: =AN67 -> 0 | AJ67: ='EQUIPO ENERO 2025'!AP67 -> 0 | AK67: =P67-Z67+AE67+U67 -> 0 | AL67: =Q67-AA67+AF67+V67 -> 0 | AM67: =R67-AB67+AG67+W67 -> 0 | AN67: =S67-AC67+AH67+X67 -> 0 | AO67: =T67-AD67+AI67+Y67 -> 0 | AQ67: =AO67 -> 0
A68: =A67+1 -> 63 | B68: CABLE CELDA DE CARGA PDX (5 PINES) | C68: No. 2 | D68: METTLER TOLEDO | E68: PDX | G68: #VALUE! | I68: SE-CABLE-PDX | K68: 44592 | O68: ='EQUIPO FEBRERO 2025 1'!AQ68 -> 0 | P68: =O68 -> 0 | Q68: =AK68 -> 0 | R68: =AL68 -> 0 | S68: =AM68 -> 0 | T68: =AN68 -> 0 | AJ68: ='EQUIPO ENERO 2025'!AP68 -> 0 | AK68: =P68-Z68+AE68+U68 -> 0 | AL68: =Q68-AA68+AF68+V68 -> 0 | AM68: =R68-AB68+AG68+W68 -> 0 | AN68: =S68-AC68+AH68+X68 -> 0 | AO68: =T68-AD68+AI68+Y68 -> 0 | AQ68: =AO68 -> 0
A69: =A68+1 -> 64 | B69: CABLE PARA BATERIA DE INDICADOR DIGITAL MODELO SE-7517 ROJO Y NEGRO | C69: No.2 | E69: SE-7517BA | I69: SE-CAB-7517BA | J69: LOCOSC | K69: 45279 | M69: 481 | O69: ='EQUIPO FEBRERO 2025 1'!AQ69 -> 12 | P69: =O69 -> 12 | Q69: =AK69 -> 12 | R69: =AL69 -> 12 | S69: =AM69 -> 12 | T69: =AN69 -> 12 | AJ69: ='EQUIPO ENERO 2025'!AP69 -> 12 | AK69: =P69-Z69+AE69+U69 -> 12 | AL69: =Q69-AA69+AF69+V69 -> 12 | AM69: =R69-AB69+AG69+W69 -> 12 | AN69: =S69-AC69+AH69+X69 -> 12 | AO69: =T69-AD69+AI69+Y69 -> 12 | AQ69: =AO69 -> 12
A70: =A69+1 -> 65 | B70: CABLE PARA INDICADOR LP7581P CON CONECTOR (CABLE ROJO Y NEGRO) | C70: NO. 2 | D70: S/M | E70: S/M | F70: S/C | G70: #VALUE! | I70: SE-CABLE-LP7581P | J70: LOCOSC | K70: 45673 | L70: 240907-1 | M70: 130 | O70: ='EQUIPO FEBRERO 2025 1'!AQ70 -> 11 | P70: =O70 -> 11 | Q70: =AK70 -> 11 | R70: =AL70 -> 11 | S70: =AM70 -> 11 | T70: =AN70 -> 11 | AJ70: ='EQUIPO ENERO 2025'!AP70 -> 11 | AK70: =P70-Z70+AE70+U70 -> 11 | AL70: =Q70-AA70+AF70+V70 -> 11 | AM70: 11 | AN70: =S70-AC70+AH70+X70 -> 11 | AO70: =T70-AD70+AI70+Y70 -> 11 | AQ70: =AO70 -> 11
A71: =A70+1 -> 66 | B71: CAJA PLASTICA IP 67 | C71: No. 2 | G71: #VALUE! | I71: SE-CAJ-IP67 | O71: ='EQUIPO FEBRERO 2025 1'!AQ71 -> 3 | P71: =O71 -> 3 | Q71: =AK71 -> 3 | R71: =AL71 -> 3 | S71: =AM71 -> 3 | T71: =AN71 -> 3 | AJ71: ='EQUIPO ENERO 2025'!AP71 -> 3 | AK71: =P71-Z71+AE71+U71 -> 3 | AL71: =Q71-AA71+AF71+V71 -> 3 | AM71: =R71-AB71+AG71+W71 -> 3 | AN71: =S71-AC71+AH71+X71 -> 3 | AO71: =T71-AD71+AI71+Y71 -> 3 | AQ71: =AO71 -> 3
A72: =A71+1 -> 67 | B72: CAJA SUMA | C72: No. 2 | D72: S/M | E72: SE-LP7312 | F72: 4 CANALES | G72: #VALUE! | H72: 1500 | I72: SE-CAJA-SUMA LP7312-A2-4 | J72: LOCOSC | K72: 45687 | L72: LP230224-1 | M72: 145 | N72: INVISA | O72: ='EQUIPO FEBRERO 2025 1'!AQ72 -> 6 | P72: =O72 -> 6 | Q72: =AK72 -> 6 | R72: =AL72 -> 6 | S72: =AM72 -> 6 | T72: =AN72 -> 6 | Z72: 1 | AE72: 1 | AJ72: ='EQUIPO ENERO 2025'!AP72 -> 6 | AK72: =P72-Z72+AE72+U72 -> 6 | AL72: =Q72-AA72+AF72+V72 -> 6 | AM72: =R72-AB72+AG72+W72 -> 6 | AN72: =S72-AC72+AH72+X72 -> 6 | AO72: =T72-AD72+AI72+Y72 -> 6 | AP72: 1 SOLO CAJA | AQ72: =AO72 -> 6 | AS72: 363
A73: =A72+1 -> 68 | B73: CAJA SUMA 4 CANALES TOTAL COMP STOCK 1007 | C73: No. 2 | D73: TOTAL COMP | E73: S-45 1250 | I73: SE-CAJA-1250-5-SS | J73: TOTAL COMP | K73: 45062 | M73: 352 | O73: ='EQUIPO FEBRERO 2025 1'!AQ73 -> 0 | P73: =O73 -> 0 | Q73: =AK73 -> 0 | R73: =AL73 -> 0 | S73: =AM73 -> 0 | T73: =AN73 -> 0 | AJ73: ='EQUIPO ENERO 2025'!AP73 -> 0 | AK73: =P73-Z73+AE73+U73 -> 0 | AL73: =Q73-AA73+AF73+V73 -> 0 | AM73: =R73-AB73+AG73+W73 -> 0 | AN73: =S73-AC73+AH73+X73 -> 0 | AO73: =T73-AD73+AI73+Y73 -> 0 | AQ73: =AO73 -> 0
A74: =A73+1 -> 69 | B74: CAJA SUMA ACERO INOX 4 CANALES 50063-0066 TORNILLOS | C74: No. 2 | D74: BRECKNELL | E74: 50063-0066 TORNILLOS | G74: #VALUE! | H74: 5500 | I74: SE-CAJASUM-4C | J74: BRECKNELL | K74: 45391 | L74: 2187074-001 | M74: 55 | O74: ='EQUIPO FEBRERO 2025 1'!AQ74 -> 1 | P74: =O74 -> 1 | Q74: =AK74 -> 1 | R74: =AL74 -> 1 | S74: =AM74 -> 1 | T74: =AN74 -> 1 | AJ74: ='EQUIPO ENERO 2025'!AP74 -> 1 | AK74: =P74-Z74+AE74+U74 -> 1 | AL74: =Q74-AA74+AF74+V74 -> 1 | AM74: =R74-AB74+AG74+W74 -> 1 | AN74: =S74-AC74+AH74+X74 -> 1 | AO74: =T74-AD74+AI74+Y74 -> 1 | AQ74: =AO74 -> 1
A75: =A74+1 -> 70 | B75: CAJA SUMA ACERO INOX 4 CANALES GRAPA AWT15-501062 06 CAMIONERAS | C75: No. 2 | D75: AVERY WEIGH TRONIX | E75: AWT15-501062 06 | G75: #VALUE! | H75: 5500 | I75: SE-CAJASUM-4C-GRA | J75: AVERY WEIGH TRONIX | K75: 45013 | L75: 2103556 | M75: 321 | N75: YEGUADA | O75: ='EQUIPO FEBRERO 2025 1'!AQ75 -> 6 | P75: =O75 -> 6 | Q75: =AK75 -> 6 | R75: =AL75 -> 6 | S75: =AM75 -> 6 | T75: =AN75 -> 4 | AC75: 2 | AJ75: ='EQUIPO ENERO 2025'!AP75 -> 6 | AK75: =P75-Z75+AE75+U75 -> 6 | AL75: =Q75-AA75+AF75+V75 -> 6 | AM75: =R75-AB75+AG75+W75 -> 6 | AN75: =S75-AC75+AH75+X75 -> 4 | AO75: =T75-AD75+AI75+Y75 -> 4 | AQ75: =AO75 -> 4 | AR75: 625363080 | AS75: 376
A76: =A75+1 -> 71 | B76: CAJA SUMA ACERO INOXIDABLE | C76: No. 2 | D76: LOCOSC | E76: SE-LP7310 | F76: 4 CANALES | G76: #VALUE! | H76: 2500 | I76: SE-LP7310-S2-4 | J76: LOCOSC | K76: 45328 | L76: LP230224-1 | M76: 32 | N76: ACEROS CESTA/banda | O76: ='EQUIPO FEBRERO 2025 1'!AQ76 -> 12 | P76: =O76 -> 12 | Q76: =AK76 -> 12 | R76: =AL76 -> 12 | S76: =AM76 -> 12 | T76: =AN76 -> 12 | AJ76: ='EQUIPO ENERO 2025'!AP76 -> 13 | AK76: =P76-Z76+AE76+U76 -> 12 | AL76: =Q76-AA76+AF76+V76 -> 12 | AM76: =R76-AB76+AG76+W76 -> 12 | AN76: =S76-AC76+AH76+X76 -> 12 | AO76: =T76-AD76+AI76+Y76 -> 12 | AQ76: =AO76 -> 12 | AS76: 324
A77: =A76+1 -> 72 | B77: CAJA SUMA ACERO INOXIDABLE | C77: NO. 2 | D77: BRECKNELL | E77: SE-7312-S2-4 | F77: 4 CANALES | G77: #VALUE! | I77: SE-7312-SS | J77: LOCOSC | K77: 45626 | L77: S/F | M77: 103 | O77: ='EQUIPO FEBRERO 2025 1'!AQ77 -> 3 | P77: =O77 -> 3 | Q77: =AK77 -> 3 | R77: =AL77 -> 3 | S77: =AM77 -> 3 | T77: =AN77 -> 3 | AJ77: ='EQUIPO ENERO 2025'!AP77 -> 3 | AK77: =P77-Z77+AE77+U77 -> 3 | AL77: =Q77-AA77+AF77+V77 -> 3 | AM77: =R77-AB77+AG77+W77 -> 3 | AN77: =S77-AC77+AH77+X77 -> 3 | AO77: =T77-AD77+AI77+Y77 -> 3 | AQ77: =AO77 -> 3
A78: =A77+1 -> 73 | B78: CAJA SUMA DE ACERO INOX CAMIONERA 12 CANALES | C78: No. 2 | D78: BRECKNELL | E78: IX-JXHG05-12-S | F78: 12 CANALES | G78: #VALUE! | I78: SE-CAJ-IX-JXHG05-12-S | J78: CNIC | K78: 45126 | L78: 2023015 | M78: 409 | O78: ='EQUIPO FEBRERO 2025 1'!AQ78 -> 0 | P78: =O78 -> 0 | Q78: =AK78 -> 0 | R78: =AL78 -> 0 | S78: =AM78 -> 0 | T78: =AN78 -> 0 | AJ78: ='EQUIPO ENERO 2025'!AP78 -> 0 | AK78: =P78-Z78+AE78+U78 -> 0 | AL78: =Q78-AA78+AF78+V78 -> 0 | AM78: =R78-AB78+AG78+W78 -> 0 | AN78: =S78-AC78+AH78+X78 -> 0 | AO78: =T78-AD78+AI78+Y78 -> 0 | AQ78: =AO78 -> 0
A79: =A78+1 -> 74 | B79: CAJA SUMA SS DE 10 CANALES (SOLO CAJA | C79: NO. 2 | D79: S/M | E79: S/M | F79: 10 CANALES | I79: S/C | K79: 45656 | L79: INGRESA DE SERVICIO EN AVICOLA GABY/BASCULAS PRECICELL | M79: 102 | O79: ='EQUIPO FEBRERO 2025 1'!AQ79 -> 1 | P79: =O79 -> 1 | Q79: =AK79 -> 1 | R79: =AL79 -> 1 | S79: =AM79 -> 1 | T79: =AN79 -> 1 | AJ79: ='EQUIPO ENERO 2025'!AP79 -> 1 | AK79: =P79-Z79+AE79+U79 -> 1 | AL79: =Q79-AA79+AF79+V79 -> 1 | AM79: =R79-AB79+AG79+W79 -> 1 | AN79: =S79-AC79+AH79+X79 -> 1 | AO79: =T79-AD79+AI79+Y79 -> 1 | AQ79: =AO79 -> 1
A80: =A79+1 -> 75 | B80: CALIBRADOR DIGITAL 0 - 150mm | C80: NO. 2 | D80: SUMIMET | E80: ACCUD 112-006-12 | F80: 0 a 150mm / 0 a 6 " | G80: #VALUE! | H80: 4200 | I80: SE-VD67 | J80: SUMINISTROS EN METROLOGIA | K80: 45670 | L80: 131207285 | M80: 124 | O80: ='EQUIPO FEBRERO 2025 1'!AQ80 -> 0 | P80: =O80 -> 0 | Q80: =AK80 -> 0 | R80: =AL80 -> 0 | S80: =AM80 -> 0 | T80: =AN80 -> 0 | AJ80: ='EQUIPO ENERO 2025'!AP80 -> 0 | AK80: =P80-Z80+AE80+U80 -> 0 | AL80: =Q80-AA80+AF80+V80 -> 0 | AM80: =R80-AB80+AG80+W80 -> 0 | AN80: =S80-AC80+AH80+X80 -> 0 | AO80: =T80-AD80+AI80+Y80 -> 0 | AQ80: =AO80 -> 0
A81: =A80+1 -> 76 | B81: CALIBRADOR DIGITAL 0 a 300mm | C81: NO. 2 | D81: SUMIMET | E81: ACCUD 112-012-12 | F81: 0 a 300 mm / 0 a 12" | G81: #VALUE! | H81: 4200 | I81: SE-VD67 | J81: SUMINISTROS EN METROLOGIA | K81: 45670 | L81: 131207285 | M81: 124 | O81: ='EQUIPO FEBRERO 2025 1'!AQ81 -> 0 | P81: =O81 -> 0 | Q81: =AK81 -> 0 | R81: =AL81 -> 0 | S81: =AM81 -> 0 | T81: =AN81 -> 0 | AJ81: ='EQUIPO ENERO 2025'!AP81 -> 0 | AK81: =P81-Z81+AE81+U81 -> 0 | AL81: =Q81-AA81+AF81+V81 -> 0 | AM81: =R81-AB81+AG81+W81 -> 0 | AN81: =S81-AC81+AH81+X81 -> 0 | AO81: =T81-AD81+AI81+Y81 -> 0 | AQ81: =AO81 -> 0
A82: =A81+1 -> 77 | B82: CARCASA DE INDICADOR SE-7517E | C82: No. 2 | D82: BRECKNELL | E82: SE-7517E | G82: #VALUE! | I82: SE-CARC-7517E | J82: LOCOSC | K82: 44592 | O82: ='EQUIPO FEBRERO 2025 1'!AQ82 -> 1 | P82: =O82 -> 1 | Q82: =AK82 -> 1 | R82: =AL82 -> 1 | S82: =AM82 -> 1 | T82: =AN82 -> 1 | AJ82: ='EQUIPO ENERO 2025'!AP82 -> 1 | AK82: =P82-Z82+AE82+U82 -> 1 | AL82: =Q82-AA82+AF82+V82 -> 1 | AM82: =R82-AB82+AG82+W82 -> 1 | AN82: =S82-AC82+AH82+X82 -> 1 | AO82: =T82-AD82+AI82+Y82 -> 1 | AQ82: =AO82 -> 1
A83: =A82+1 -> 78 | B83: CARCASA DE INDICADOR SE-7510 PARTE TRASERA CON BATERIA | C83: NO.2 | D83: BRECKNELL | E83: SE-7510 | I83: SE-CARC-7510/BAT | J83: LOCOSC | K83: 45574 | L83: LP3211240 | M83: 76 | O83: ='EQUIPO FEBRERO 2025 1'!AQ83 -> 8 | P83: =O83 -> 8 | Q83: =AK83 -> 8 | R83: =AL83 -> 8 | S83: =AM83 -> 8 | T83: =AN83 -> 8 | AJ83: ='EQUIPO ENERO 2025'!AP83 -> 8 | AK83: =P83-Z83+AE83+U83 -> 8 | AL83: =Q83-AA83+AF83+V83 -> 8 | AM83: =R83-AB83+AG83+W83 -> 8 | AN83: =S83-AC83+AH83+X83 -> 8 | AO83: =T83-AD83+AI83+Y83 -> 8 | AQ83: =AO83 -> 8
A84: =A83+1 -> 79 | B84: CARRITO DE METAL PARA BASCULA 7611 | C84: Lab | D84: SOEXSA | E84: SE-7611 | G84: #VALUE! | I84: SE-CAR-BAS7611 | J84: LOCOSC | K84: 44592 | O84: ='EQUIPO FEBRERO 2025 1'!AQ84 -> 1 | P84: =O84 -> 1 | Q84: =AK84 -> 1 | R84: =AL84 -> 1 | S84: =AM84 -> 1 | T84: =AN84 -> 1 | AJ84: ='EQUIPO ENERO 2025'!AP84 -> 1 | AK84: =P84-Z84+AE84+U84 -> 1 | AL84: =Q84-AA84+AF84+V84 -> 1 | AM84: =R84-AB84+AG84+W84 -> 1 | AN84: =S84-AC84+AH84+X84 -> 1 | AO84: =T84-AD84+AI84+Y84 -> 1 | AQ84: =AO84 -> 1
A85: =A84+1 -> 80 | B85: CARTUCHO DE TINTA PARA IMPRESORA LP7561 | C85: NO. 2 | D85: PRINT-RITE | E85: EPSON ERC05 | I85: SE-ERC05 | J85: LOCOSC | K85: 45582 | M85: 81 | O85: ='EQUIPO FEBRERO 2025 1'!AQ85 -> 10 | P85: =O85 -> 10 | Q85: =AK85 -> 10 | R85: =AL85 -> 10 | S85: =AM85 -> 10 | T85: =AN85 -> 10 | AJ85: ='EQUIPO ENERO 2025'!AP85 -> 10 | AK85: =P85-Z85+AE85+U85 -> 10 | AL85: =Q85-AA85+AF85+V85 -> 10 | AM85: =R85-AB85+AG85+W85 -> 10 | AN85: =S85-AC85+AH85+X85 -> 10 | AO85: =T85-AD85+AI85+Y85 -> 10 | AQ85: =AO85 -> 10
A86: =A85+1 -> 81 | B86: CELDA DE CARGA TIPO BARRA LP7161 | C86: No. 2 | D86: S/M | E86: LP7161 | F86: 800 kg | G86: #VALUE! | H86: 2800 | I86: SE-CELBAR-LP7161-800KG | J86: LOCOSC | K86: 45325 | M86: 12 | O86: ='EQUIPO FEBRERO 2025 1'!AQ86 -> 1 | P86: =O86 -> 1 | Q86: =AK86 -> 1 | R86: =AL86 -> 1 | S86: =AM86 -> 1 | T86: =AN86 -> 1 | AJ86: ='EQUIPO ENERO 2025'!AP86 -> 1 | AK86: =P86-Z86+AE86+U86 -> 1 | AL86: =Q86-AA86+AF86+V86 -> 1 | AM86: =R86-AB86+AG86+W86 -> 1 | AN86: =S86-AC86+AH86+X86 -> 1 | AO86: =T86-AD86+AI86+Y86 -> 1 | AQ86: =AO86 -> 1
A87: =A86+1 -> 82 | B87: CELDA DE CARGA BARRA 50K 65016-050E-NC-001F | C87: No. 2 | D87: BRECKNELL | E87: 65016-050E-NC-001F | F87: 50 k | G87: #VALUE! | H87: Q | I87: SE-CELBAR-65016-50 | J87: BRECKNELL | K87: 44592 | O87: ='EQUIPO FEBRERO 2025 1'!AQ87 -> 2 | P87: =O87 -> 2 | Q87: =AK87 -> 2 | R87: =AL87 -> 2 | S87: =AM87 -> 2 | T87: =AN87 -> 2 | AJ87: ='EQUIPO ENERO 2025'!AP87 -> 2 | AK87: =P87-Z87+AE87+U87 -> 2 | AL87: =Q87-AA87+AF87+V87 -> 2 | AM87: =R87-AB87+AG87+W87 -> 2 | AN87: =S87-AC87+AH87+X87 -> 2 | AO87: =T87-AD87+AI87+Y87 -> 2 | AQ87: =AO87 -> 2
A88: =A87+1 -> 83 | B88: CELDA DE CARGA 10 kg Total Comp | C88: No. 2 | D88: TOTAL COMP | E88: PSW-10KG 05500 | F88: 10k | G88: #VALUE! | I88: SE-CELCA-RL-10kg | J88: TOTAL COMP | K88: 44592 | O88: ='EQUIPO FEBRERO 2025 1'!AQ88 -> 1 | P88: =O88 -> 1 | Q88: =AK88 -> 1 | R88: =AL88 -> 1 | S88: =AM88 -> 1 | T88: =AN88 -> 1 | AJ88: ='EQUIPO ENERO 2025'!AP88 -> 1 | AK88: =P88-Z88+AE88+U88 -> 1 | AL88: =Q88-AA88+AF88+V88 -> 1 | AM88: =R88-AB88+AG88+W88 -> 1 | AN88: =S88-AC88+AH88+X88 -> 1 | AO88: =T88-AD88+AI88+Y88 -> 1 | AQ88: =AO88 -> 1
A89: =A88+1 -> 84 | B89: CELDA DE CARGA 20 KG MODELO SUP1-20KG | C89: No. 2 | D89: LOCOSC | E89: SUP-1-20KG | F89: 20 kg | J89: LOCOSC | K89: 45416 | M89: 59 | O89: ='EQUIPO FEBRERO 2025 1'!AQ89 -> 1 | P89: =O89 -> 1 | Q89: =AK89 -> 1 | R89: =AL89 -> 1 | S89: =AM89 -> 1 | T89: =AN89 -> 1 | AJ89: ='EQUIPO ENERO 2025'!AP89 -> 1 | AK89: =P89-Z89+AE89+U89 -> 1 | AL89: =Q89-AA89+AF89+V89 -> 1 | AM89: =R89-AB89+AG89+W89 -> 1 | AN89: =S89-AC89+AH89+X89 -> 1 | AO89: =T89-AD89+AI89+Y89 -> 1 | AQ89: =AO89 -> 1
A90: =A89+1 -> 85 | B90: CELDA DE CARGA 20K H8C-N5-20K-6YWB | C90: No. 2 | F90: 20 k | I90: SE-CELCA-20K | J90: LOCOSC | K90: 44592 | O90: ='EQUIPO FEBRERO 2025 1'!AQ90 -> 0 | P90: =O90 -> 0 | Q90: =AK90 -> 0 | R90: =AL90 -> 0 | S90: =AM90 -> 0 | T90: =AN90 -> 0 | AJ90: ='EQUIPO ENERO 2025'!AP90 -> 0 | AK90: =P90-Z90+AE90+U90 -> 0 | AL90: =Q90-AA90+AF90+V90 -> 0 | AM90: =R90-AB90+AG90+W90 -> 0 | AN90: =S90-AC90+AH90+X90 -> 0 | AO90: =T90-AD90+AI90+Y90 -> 0 | AQ90: =AO90 -> 0
A91: =A90+1 -> 86 | B91: CELDA DE CARGA 75 K LP7154 16mm DOBLE BRIDA CAMIONERO | C91: No. 2 | D91: SENSORTRONICS | E91: LP7154 | F91: 75 k | G91: #VALUE! | H91: 7500 | I91: SE7154-75klb-16m | J91: LOCOSC | K91: 45673 | L91: 240907-1 | M91: 129 | N91: IMSA | O91: ='EQUIPO FEBRERO 2025 1'!AQ91 -> 13 | P91: =O91 -> 13 | Q91: =AK91 -> 10 | R91: =AL91 -> 10 | S91: =AM91 -> 10 | T91: =AN91 -> 10 | Z91: 3 | AJ91: ='EQUIPO ENERO 2025'!AP91 -> 14 | AK91: =P91-Z91+AE91+U91 -> 10 | AL91: =Q91-AA91+AF91+V91 -> 10 | AM91: =R91-AB91+AG91+W91 -> 10 | AN91: =S91-AC91+AH91+X91 -> 10 | AO91: =T91-AD91+AI91+Y91 -> 10 | AQ91: =AO91 -> 10 | AR91: 1898398354 | AS91: 353
A92: =A91+1 -> 87 | B92: CELDA DE CARGA BARRA ILE 150 K | C92: No. 2 | E92: ILE150 | F92: 150 kg | G92: #VALUE! | I92: SE-CELCA-150K | J92: LOCOSC | K92: 44592 | O92: ='EQUIPO FEBRERO 2025 1'!AQ92 -> 0 | P92: =O92 -> 0 | Q92: =AK92 -> 0 | R92: =AL92 -> 0 | S92: =AM92 -> 0 | T92: =AN92 -> 0 | AJ92: ='EQUIPO ENERO 2025'!AP92 -> 1 | AK92: =P92-Z92+AE92+U92 -> 0 | AL92: =Q92-AA92+AF92+V92 -> 0 | AM92: =R92-AB92+AG92+W92 -> 0 | AN92: =S92-AC92+AH92+X92 -> 0 | AO92: =T92-AD92+AI92+Y92 -> 0 | AQ92: =AO92 -> 0
A93: =A92+1 -> 88 | B93: CELDA DE CARGA BARRA 1 K (INCLUYE PATA) tecnipesa | C93: No. 2 | D93: BRECKNELL | E93: Tecnipesa | F93: 1 k | G93: #VALUE! | I93: SE-CELBAR-1 K | J93: BRECKNELL | K93: 44592 | O93: ='EQUIPO FEBRERO 2025 1'!AQ93 -> 2 | P93: =O93 -> 2 | Q93: =AK93 -> 2 | R93: =AL93 -> 2 | S93: =AM93 -> 2 | T93: =AN93 -> 2 | AJ93: ='EQUIPO ENERO 2025'!AP93 -> 2 | AK93: =P93-Z93+AE93+U93 -> 2 | AL93: =Q93-AA93+AF93+V93 -> 2 | AM93: =R93-AB93+AG93+W93 -> 2 | AN93: =S93-AC93+AH93+X93 -> 2 | AO93: =T93-AD93+AI93+Y93 -> 2 | AQ93: =AO93 -> 2
A94: =A93+1 -> 89 | B94: CELDA DE CARGA BARRA 10 K-SQB-10QHSS | C94: No. 2 | D94: BRECKNELL | E94: SQB-10QHSS | F94: 10 k | G94: #VALUE! | H94: 5200 | I94: SE-CELBAR-10K | J94: BRECKNELL | K94: 44592 | O94: ='EQUIPO FEBRERO 2025 1'!AQ94 -> 0 | P94: =O94 -> 0 | Q94: =AK94 -> 0 | R94: =AL94 -> 0 | S94: =AM94 -> 0 | T94: =AN94 -> 0 | AJ94: ='EQUIPO ENERO 2025'!AP94 -> 0 | AK94: =P94-Z94+AE94+U94 -> 0 | AL94: =Q94-AA94+AF94+V94 -> 0 | AM94: =R94-AB94+AG94+W94 -> 0 | AN94: =S94-AC94+AH94+X94 -> 0 | AO94: =T94-AD94+AI94+Y94 -> 0 | AQ94: =AO94 -> 0
A95: =A94+1 -> 90 | B95: CELDA DE CARGA BARRA 2KG | C95: No. 2 | D95: S/M | E95: HBM | F95: 2 kg | G95: #VALUE! | I95: SE-CELCA-2K | J95: LOCOSC | K95: 44592 | O95: ='EQUIPO FEBRERO 2025 1'!AQ95 -> 1 | P95: =O95 -> 1 | Q95: =AK95 -> 1 | R95: =AL95 -> 1 | S95: =AM95 -> 1 | T95: =AN95 -> 1 | AJ95: ='EQUIPO ENERO 2025'!AP95 -> 1 | AK95: =P95-Z95+AE95+U95 -> 1 | AL95: =Q95-AA95+AF95+V95 -> 1 | AM95: =R95-AB95+AG95+W95 -> 1 | AN95: =S95-AC95+AH95+X95 -> 1 | AO95: =T95-AD95+AI95+Y95 -> 1 | AQ95: =AO95 -> 1
A96: =A95+1 -> 91 | B96: BASCULA DE PISO PLATAFORMA /ABS ARMADAS DEMO | D96: BRECKNELL | E96: SE-LP7611 | F96: 600 x 0.5 kg | G96: #VALUE! | H96: 4500 | I96: SE-LP7611-DEMO | J96: LOCOSC | K96: 44592 | O96: ='EQUIPO FEBRERO 2025 1'!AQ96 -> 0 | P96: =O96 -> 0 | Q96: =AK96 -> 0 | R96: =AL96 -> 0 | S96: =AM96 -> 0 | T96: =AN96 -> 0 | AJ96: ='EQUIPO ENERO 2025'!AP96 -> 0 | AK96: =P96-Z96+AE96+U96 -> 0 | AL96: =Q96-AA96+AF96+V96 -> 0 | AM96: =R96-AB96+AG96+W96 -> 0 | AN96: =S96-AC96+AH96+X96 -> 0 | AO96: =T96-AD96+AI96+Y96 -> 0 | AQ96: =AO96 -> 0
A97: =A96+1 -> 92 | B97: CELDA DE CARGA BARRA 5 k 65016-005-NC-01F | C97: No. 2 | D97: SENSORTRONICS | E97: 65016-005-NC-01F | F97: 5 k | G97: #VALUE! | I97: SE-CELBAR-65061-5 | J97: BRECKNELL | K97: 44592 | O97: ='EQUIPO FEBRERO 2025 1'!AQ97 -> 0 | P97: =O97 -> 0 | Q97: =AK97 -> 0 | R97: =AL97 -> 0 | S97: =AM97 -> 0 | T97: =AN97 -> 0 | AJ97: ='EQUIPO ENERO 2025'!AP97 -> 0 | AK97: =P97-Z97+AE97+U97 -> 0 | AL97: =Q97-AA97+AF97+V97 -> 0 | AM97: =R97-AB97+AG97+W97 -> 0 | AN97: =S97-AC97+AH97+X97 -> 0 | AO97: =T97-AD97+AI97+Y97 -> 0 | AQ97: =AO97 -> 0
A98: =A97+1 -> 93 | B98: CELDA DE CARGA BARRA 5 K H8C-N5-5KSE-6YWB-SC-D27 ZEMIC | C98: No. 2 | D98: BRECKNELL | E98: H8C-N5-5KSE-6YWB-SC-D27 | F98: 5 k | G98: #VALUE! | I98: SE-CELBAR-5 K | J98: BRECKNELL | K98: 44592 | O98: ='EQUIPO FEBRERO 2025 1'!AQ98 -> 3 | P98: =O98 -> 3 | Q98: =AK98 -> 3 | R98: =AL98 -> 3 | S98: =AM98 -> 3 | T98: =AN98 -> 3 | AJ98: ='EQUIPO ENERO 2025'!AP98 -> 3 | AK98: =P98-Z98+AE98+U98 -> 3 | AL98: =Q98-AA98+AF98+V98 -> 3 | AM98: =R98-AB98+AG98+W98 -> 3 | AN98: =S98-AC98+AH98+X98 -> 3 | AO98: =T98-AD98+AI98+Y98 -> 3 | AQ98: =AO98 -> 3
A99: =A98+1 -> 94 | B99: CELDA DE CARGA BARRA 5 K PINTADA (USADAS) ZEMIC H8C-N5-5KSE-6YWB-SC-D2 | C99: No. 2 | D99: BRECKNELL | E99: H8C-N5-5KSE-6YWB-SC-D2 | F99: 5 k | G99: #VALUE! | I99: SE-CELBAR- 5 K U | J99: BRECKNELL | K99: 44592 | O99: ='EQUIPO FEBRERO 2025 1'!AQ99 -> 3 | P99: =O99 -> 3 | Q99: =AK99 -> 3 | R99: =AL99 -> 3 | S99: =AM99 -> 3 | T99: =AN99 -> 3 | AJ99: ='EQUIPO ENERO 2025'!AP99 -> 3 | AK99: =P99-Z99+AE99+U99 -> 3 | AL99: =Q99-AA99+AF99+V99 -> 3 | AM99: =R99-AB99+AG99+W99 -> 3 | AN99: =S99-AC99+AH99+X99 -> 3 | AO99: =T99-AD99+AI99+Y99 -> 3 | AQ99: =AO99 -> 3
A100: =A99+1 -> 95 | B100: CELDA DE CARGA BARRA 50 K 65061-050E-B1-00F | C100: No. 2 | D100: SENSORTRONICS | E100: 65061-050E-B1-00F | F100: 50 k | G100: #VALUE! | H100: Q | I100: SE-CELBAR-65061-50 | J100: VPG | K100: 45505 | L100: 2410004753 | M100: 17 | O100: ='EQUIPO FEBRERO 2025 1'!AQ100 -> 2 | P100: =O100 -> 2 | Q100: =AK100 -> 2 | R100: =AL100 -> 2 | S100: =AM100 -> 2 | T100: =AN100 -> 2 | AJ100: ='EQUIPO ENERO 2025'!AP100 -> 2 | AK100: =P100-Z100+AE100+U100 -> 2 | AL100: =Q100-AA100+AF100+V100 -> 2 | AM100: =R100-AB100+AG100+W100 -> 2 | AN100: =S100-AC100+AH100+X100 -> 2 | AO100: =T100-AD100+AI100+Y100 -> 2 | AQ100: =AO100 -> 2
A101: =A100+1 -> 96 | B101: CELDA DE CARGA BARRA 40 K 65061-040E-B1-01F | C101: No. 2 | D101: SENSORTRONICS | E101: 65061-040E-BI-01F | F101: 40 k | G101: #VALUE! | J101: VPG | K101: 45505 | L101: 2410004752 | M101: 17 | N101: AGREGADO POR ALDO SOTO | O101: ='EQUIPO FEBRERO 2025 1'!AQ101 -> 1 | P101: =O101 -> 1 | Q101: =AK101 -> 1 | R101: =AL101 -> 1 | S101: =AM101 -> 1 | T101: =AN101 -> 1 | AJ101: ='EQUIPO ENERO 2025'!AP101 -> 0 | AK101: =P101-Z101+AE101+U101 -> 1 | AL101: =Q101-AA101+AF101+V101 -> 1 | AM101: =R101-AB101+AG101+W101 -> 1 | AN101: =S101-AC101+AH101+X101 -> 1 | AO101: =T101-AD101+AI101+Y101 -> 1 | AQ101: =AO101 -> 1
...

Sheet EQUIPO ABRIL 2025  1
B1: SOLUCIONES EXACTAS, S.A. | AR1: Codigo: FO-SE-053 | AV1: Codigo: FO-SE-053
B3: LISTADO INVENTARIO BODEGAS FEBRERO | AK3: ABRIL | AR3: Versión: 02 | AV3: Versión: 02
A4: No. | B4: PRODUCTO | C4: No. BODEGA | D4: MARCA | E4: MODELO | F4: CAPACIDAD | G4: IMAGEN | H4: PRECIO | I4: CODIGO INTERNO | J4: PROVEEDOR | K4: FECHA INGRESO BODEGA | L4: FACTURA No. PROVEEDOR | M4: BOLETA INGRESO BODEGA | N4: OBSERVACION | O4: VIENE MES ANTERIOR | P4: EXISTENCIA INICIO SEMANA | U4: INGRESO POR IMPORTACION O COMPRA | Z4: DESCARGA Y/O SALIDA | AE4: DEVOLUCIONES | AJ4: INICIO DE MES | AK4: EXISTENCIA POR SEMANA | AP4: DEMO | AQ4: TOTAL EXISTENCIA MENSUAL | AR4: FACTURA VENTA | AS4: BOLETA DE SALIDA | AT4: ENVIO | AU4: FIRMA ULTIMO INVENTARIO | AV4: FECHA ULTIMA REVISION
P5: 1 | Q5: 2 | R5: 3 | S5: 4 | T5: 5 | U5: 1 | V5: 2 | W5: 3 | X5: 4 | Y5: 5 | Z5: 1 | AA5: 2 | AB5: 3 | AC5: 4 | AD5: 5 | AE5: 1 | AF5: 2 | AG5: 3 | AH5: 4 | AI5: 5 | AK5: 1 | AL5: 2 | AM5: 3 | AN5: 4 | AO5: 5
A6: 1 | B6: ADAPTADOR PARA INDICADOR 9V1.2A MODELO: KEERDA | C6: No. 2 | D6: KEERDA | E6: DZ012ELL090120U | F6: 9V | G6: #VALUE! | H6: 395 | I6: SE-ADAT9V | J6: SIZEIN | K6: 45666 | L6: LK24112701 | M6: 118 | N6: aromas y esencias/ | O6: ='EQUIPO MARZO 2025 1'!AQ6 -> 43 | P6: =O6 -> 43 | Q6: =AK6 -> 43 | R6: =AL6 -> 43 | S6: =AM6 -> 41 | T6: =AN6 -> 40 | AB6: 2 | AC6: 1 | AJ6: ='EQUIPO ENERO 2025'!AP6 -> 47 | AK6: =P6-Z6+AE6+U6 -> 43 | AL6: =Q6-AA6+AF6+V6 -> 43 | AM6: =R6-AB6+AG6+W6 -> 41 | AN6: =S6-AC6+AH6+X6 -> 40 | AO6: =T6-AD6+AI6+Y6 -> 40 | AQ6: =AO6 -> 40 | AR6: S/F | AS6: 397
A7: =A6+1 -> 2 | B7: ADAPTADOR GENERICO 9V 600 mA | C7: No.2 | D7: Byp | F7: 9v | K7: 45712 | M7: 162 | N7: ferteco | O7: ='EQUIPO MARZO 2025 1'!AQ7 -> 9 | P7: =O7 -> 9 | Q7: =AK7 -> 9 | R7: =AL7 -> 9 | S7: =AM7 -> 9 | T7: =AN7 -> 8 | AC7: 1 | AK7: =P7-Z7+AE7+U7 -> 9 | AL7: =Q7-AA7+AF7+V7 -> 9 | AM7: =R7-AB7+AG7+W7 -> 9 | AN7: =S7-AC7+AH7+X7 -> 8 | AO7: =T7-AD7+AI7+Y7 -> 8 | AQ7: =AO7 -> 8 | AR7: 3499117857 | AS7: 400
A8: =A7+1 -> 3 | B8: ADAPTADORES GENERICOS 5 V 1 AMP AC/DC | C8: No. 2 | D8: BRECKNELL | E8: S/M | G8: #VALUE! | I8: SE-ADAP-1 AMP | J8: BRECKNELL | K8: 44592 | O8: ='EQUIPO MARZO 2025 1'!AQ8 -> 2 | P8: =O8 -> 2 | Q8: =AK8 -> 2 | R8: =AL8 -> 2 | S8: =AM8 -> 2 | T8: =AN8 -> 2 | AJ8: ='EQUIPO ENERO 2025'!AP8 -> 2 | AK8: =P8-Z8+AE8+U8 -> 2 | AL8: =Q8-AA8+AF8+V8 -> 2 | AM8: =R8-AB8+AG8+W8 -> 2 | AN8: =S8-AC8+AH8+X8 -> 2 | AO8: =T8-AD8+AI8+Y8 -> 2 | AQ8: =AO8 -> 2
A9: =A8+1 -> 4 | B9: ADAPTADORES SBI 505 ORIGINAL AWT05-505896 | C9: No. 2 | D9: AVERY WEIGH TRONIX | E9: AWT05-505896 | G9: #VALUE! | H9: 550 | I9: SE-ADAP-SBI505 | J9: AVERY WEIGH TRONIX | K9: 44592 | O9: ='EQUIPO MARZO 2025 1'!AQ9 -> 8 | P9: =O9 -> 8 | Q9: =AK9 -> 8 | R9: =AL9 -> 8 | S9: =AM9 -> 8 | T9: =AN9 -> 8 | AJ9: ='EQUIPO ENERO 2025'!AP9 -> 8 | AK9: =P9-Z9+AE9+U9 -> 8 | AL9: =Q9-AA9+AF9+V9 -> 8 | AM9: =R9-AB9+AG9+W9 -> 8 | AN9: =S9-AC9+AH9+X9 -> 8 | AO9: =T9-AD9+AI9+Y9 -> 8 | AQ9: =AO9 -> 8
A10: =A9+1 -> 5 | B10: ADAPTADOR BI 12T | C10: No. 2 | D10: BRECKNELL | E10: BI 12T | F10: 12t | G10: #VALUE! | I10: SE-ADAP-BI-12T | J10: BRECKNELL | K10: 44592 | O10: ='EQUIPO MARZO 2025 1'!AQ10 -> 1 | P10: =O10 -> 1 | Q10: =AK10 -> 1 | R10: =AL10 -> 1 | S10: =AM10 -> 1 | T10: =AN10 -> 1 | AJ10: ='EQUIPO ENERO 2025'!AP10 -> 1 | AK10: =P10-Z10+AE10+U10 -> 1 | AL10: =Q10-AA10+AF10+V10 -> 1 | AM10: =R10-AB10+AG10+W10 -> 1 | AN10: =S10-AC10+AH10+X10 -> 1 | AO10: =T10-AD10+AI10+Y10 -> 1 | AQ10: =AO10 -> 1
A11: =A10+1 -> 6 | B11: ADAPTADOR DE MODULOS INALAMBRICOS SE-7660 | C11: No.2 | E11: SE-ADAPT-7660 | G11: #VALUE! | J11: LOCOSC | K11: 45464 | M11: 87 | O11: ='EQUIPO MARZO 2025 1'!AQ11 -> 2 | P11: =O11 -> 2 | Q11: =AK11 -> 2 | R11: =AL11 -> 2 | S11: =AM11 -> 2 | T11: =AN11 -> 2 | AJ11: ='EQUIPO ENERO 2025'!AP11 -> 2 | AK11: =P11-Z11+AE11+U11 -> 2 | AL11: =Q11-AA11+AF11+V11 -> 2 | AM11: =R11-AB11+AG11+W11 -> 2 | AN11: =S11-AC11+AH11+X11 -> 2 | AO11: =T11-AD11+AI11+Y11 -> 2 | AQ11: =AO11 -> 2
A12: =A11+1 -> 7 | B12: ADAPTADOR DE CORRIENTE DE INDICADOR SE7517/ REPARADO DE CABLE | C12: NO.2 | D12: KEERDA | E12: DZ007AHL050100U | F12: 5.0V/1.0Ah | I12: SE-DZ007 | J12: LOCOSC | M12: 113 | O12: ='EQUIPO MARZO 2025 1'!AQ12 -> 1 | P12: =O12 -> 1 | Q12: =AK12 -> 1 | R12: =AL12 -> 1 | S12: =AM12 -> 1 | T12: =AN12 -> 1 | AJ12: ='EQUIPO ENERO 2025'!AP12 -> 1 | AK12: =P12-Z12+AE12+U12 -> 1 | AL12: =Q12-AA12+AF12+V12 -> 1 | AM12: =R12-AB12+AG12+W12 -> 1 | AN12: =S12-AC12+AH12+X12 -> 1 | AO12: =T12-AD12+AI12+Y12 -> 1 | AQ12: =AO12 -> 1
A13: =A12+1 -> 8 | B13: ADAPTADORES DE CORRIENTE PARA MODULOS INALAMBRICOS SE-7519A | C13: NO.2 | D13: S/M | E13: ZF120A-0421000 | F13: 4.2V/10A | G13: #VALUE! | I13: SE-ADAP-A | J13: LOCOSC | K13: 45582 | M13: 81 | O13: ='EQUIPO MARZO 2025 1'!AQ13 -> 2 | P13: =O13 -> 2 | Q13: =AK13 -> 2 | R13: =AL13 -> 2 | S13: =AM13 -> 2 | T13: =AN13 -> 2 | AJ13: ='EQUIPO ENERO 2025'!AP13 -> 2 | AK13: =P13-Z13+AE13+U13 -> 2 | AL13: =Q13-AA13+AF13+V13 -> 2 | AM13: =R13-AB13+AG13+W13 -> 2 | AN13: =S13-AC13+AH13+X13 -> 2 | AO13: =T13-AD13+AI13+Y13 -> 2 | AQ13: =AO13 -> 2
A14: =A13+1 -> 9 | B14: ARMARIOS ELECTRICOS ST4-420 | C14: No. 2 | D14: BRECKNELL | E14: ST4-420 | G14: #VALUE! | I14: SE-ARMAELEC | J14: BRECKNELL | K14: 44592 | O14: ='EQUIPO MARZO 2025 1'!AQ14 -> 3 | P14: =O14 -> 3 | Q14: =AK14 -> 3 | R14: =AL14 -> 3 | S14: =AM14 -> 3 | T14: =AN14 -> 3 | AJ14: ='EQUIPO ENERO 2025'!AP14 -> 3 | AK14: =P14-Z14+AE14+U14 -> 3 | AL14: =Q14-AA14+AF14+V14 -> 3 | AM14: =R14-AB14+AG14+W14 -> 3 | AN14: =S14-AC14+AH14+X14 -> 3 | AO14: =T14-AD14+AI14+Y14 -> 3 | AQ14: =AO14 -> 3
A15: =A14+1 -> 10 | B15: ARGOLLAS PARA BÁSCULAS PESA EJES | C15: NO.2 | D15: S/M | E15: M-20 | F15: S/C | G15: #VALUE! | I15: SE-ARG-PPEJES | J15: LOCOSC | K15: 45673 | L15: 240907-1 | M15: 131 | O15: ='EQUIPO MARZO 2025 1'!AQ15 -> 0 | P15: =O15 -> 0 | Q15: =AK15 -> 0 | R15: =AL15 -> 0 | S15: =AM15 -> 0 | T15: =AN15 -> 0 | AJ15: ='EQUIPO ENERO 2025'!AP15 -> 0 | AK15: =P15-Z15+AE15+U15 -> 0 | AL15: =Q15-AA15+AF15+V15 -> 0 | AM15: =R15-AB15+AG15+W15 -> 0 | AN15: =S15-AC15+AH15+X15 -> 0 | AO15: =T15-AD15+AI15+Y15 -> 0 | AQ15: =AO15 -> 0
A16: =A15+1 -> 11 | B16: BALANZA DE BOLSILLO CAPACIDAD DE 200x0.01g | C16: No. 1 | E16: HY-YH-J100120 | F16: 2 000 x 0.01 g | G16: #VALUE! | H16: 150 | I16: SE-FAB-GUA | K16: 44592 | O16: ='EQUIPO MARZO 2025 1'!AQ16 -> 5 | P16: =O16 -> 5 | Q16: =AK16 -> 5 | R16: =AL16 -> 5 | S16: =AM16 -> 5 | T16: =AN16 -> 5 | AJ16: ='EQUIPO ENERO 2025'!AP16 -> 5 | AK16: =P16-Z16+AE16+U16 -> 5 | AL16: =Q16-AA16+AF16+V16 -> 5 | AM16: =R16-AB16+AG16+W16 -> 5 | AN16: =S16-AC16+AH16+X16 -> 5 | AO16: =T16-AD16+AI16+Y16 -> 5 | AQ16: =AO16 -> 5
A17: =A16+1 -> 12 | B17: BALANZA DE LABORATORIO 1 000 x0.01g | C17: N/A | D17: ELECTRONIC BALANCE | E17: SE10002K | F17: 1 000 x 0.01 g | G17: #VALUE! | H17: 9180 | I17: SE-WTB1002K | J17: LOCOSC | K17: 45316 | M17: 15 | O17: ='EQUIPO MARZO 2025 1'!AQ17 -> 0 | P17: =O17 -> 0 | Q17: =AK17 -> 0 | R17: =AL17 -> 0 | S17: =AM17 -> 0 | T17: =AN17 -> 0 | AJ17: ='EQUIPO ENERO 2025'!AP17 -> 0 | AK17: =P17-Z17+AE17+U17 -> 0 | AL17: =Q17-AA17+AF17+V17 -> 0 | AM17: =R17-AB17+AG17+W17 -> 0 | AN17: =S17-AC17+AH17+X17 -> 0 | AO17: =T17-AD17+AI17+Y17 -> 0 | AQ17: =AO17 -> 0
A18: =A17+1 -> 13 | B18: BALANZA DE LABORATORIO 10000x0.1g | C18: No. 1 | D18: ELECTRONIC BALANCE | E18: SE-WT100001X | F18: 1 000 x 0.1 g | G18: #VALUE! | H18: 4600 | I18: SE-WT100001X | J18: LOCOSC | K18: 45216 | L18: 2015 | M18: 451 | O18: ='EQUIPO MARZO 2025 1'!AQ18 -> 0 | P18: =O18 -> 0 | Q18: =AK18 -> 0 | R18: =AL18 -> 0 | S18: =AM18 -> 0 | T18: =AN18 -> 0 | AJ18: ='EQUIPO ENERO 2025'!AP18 -> 0 | AK18: =P18-Z18+AE18+U18 -> 0 | AL18: =Q18-AA18+AF18+V18 -> 0 | AM18: =R18-AB18+AG18+W18 -> 0 | AN18: =S18-AC18+AH18+X18 -> 0 | AO18: =T18-AD18+AI18+Y18 -> 0 | AQ18: =AO18 -> 0
A19: =A18+1 -> 14 | B19: BALANZA DE LABORATORIO 1500g x 0.5g | C19: N/A | D19: ELECTRONIC BALANCE | E19: SE-WT15002KF | F19: 1 500 x 0.05 kg | G19: #VALUE! | H19: 2800 | I19: SE-WT15002KF-5 | J19: LOCOSC | K19: 45107 | L19: LP230224-1 | M19: 393 | O19: ='EQUIPO MARZO 2025 1'!AQ19 -> 5 | P19: =O19 -> 5 | Q19: =AK19 -> 5 | R19: =AL19 -> 5 | S19: =AM19 -> 5 | T19: =AN19 -> 5 | AJ19: ='EQUIPO ENERO 2025'!AP19 -> 5 | AK19: =P19-Z19+AE19+U19 -> 5 | AL19: =Q19-AA19+AF19+V19 -> 5 | AM19: =R19-AB19+AG19+W19 -> 5 | AN19: =S19-AC19+AH19+X19 -> 5 | AO19: =T19-AD19+AI19+Y19 -> 5 | AQ19: =AO19 -> 5
A20: =A19+1 -> 15 | B20: BALANZA DE LABORATORIO CAPACIDAD 15 kg x 0.1g | C20: No. 1 | D20: ELECTRONIC BALANCE | E20: SE150001XD | F20: 15 kg x 0.1 g | G20: #VALUE! | H20: 9180 | I20: SE-WT150001XD | J20: LOCOSC | K20: 45316 | M20: 15 | O20: ='EQUIPO MARZO 2025 1'!AQ20 -> 0 | P20: =O20 -> 0 | Q20: =AK20 -> 0 | R20: =AL20 -> 0 | S20: =AM20 -> 0 | T20: =AN20 -> 0 | AJ20: ='EQUIPO ENERO 2025'!AP20 -> 0 | AK20: =P20-Z20+AE20+U20 -> 0 | AL20: =Q20-AA20+AF20+V20 -> 0 | AM20: =R20-AB20+AG20+W20 -> 0 | AN20: =S20-AC20+AH20+X20 -> 0 | AO20: =T20-AD20+AI20+Y20 -> 0 | AQ20: =AO20 -> 0
A21: =A20+1 -> 16 | B21: BALANZA DE LABORATORIO CAPACIDAD 300 g x 1 mg | C21: N/A | D21: ELECTRONIC BALANCE | E21: SE-3003GH | F21: 300 g x 1 mg | G21: #VALUE! | H21: 36300 | I21: SE3003GH | J21: LOCOSC | K21: 45299 | M21: 6 | O21: ='EQUIPO MARZO 2025 1'!AQ21 -> 0 | P21: =O21 -> 0 | Q21: =AK21 -> 0 | R21: =AL21 -> 0 | S21: =AM21 -> 0 | T21: =AN21 -> 0 | AJ21: ='EQUIPO ENERO 2025'!AP21 -> 0 | AK21: =P21-Z21+AE21+U21 -> 0 | AL21: =Q21-AA21+AF21+V21 -> 0 | AM21: =R21-AB21+AG21+W21 -> 0 | AN21: =S21-AC21+AH21+X21 -> 0 | AO21: =T21-AD21+AI21+Y21 -> 0 | AQ21: =AO21 -> 0
A22: =A21+1 -> 17 | B22: BALANZA ANALITICA CAPACIDAD DE 5 000g x 0.01 g | C22: N/A | D22: ELECTRONIC BALANCE | E22: SE-5 0002CF | F22: 5 000 x 0.01 g | G22: #VALUE! | I22: SE50002CF | J22: LOCOSC | K22: 45336 | L22: 669885E9 | M22: 37 | O22: ='EQUIPO MARZO 2025 1'!AQ22 -> 0 | P22: =O22 -> 0 | Q22: =AK22 -> 0 | R22: =AL22 -> 0 | S22: =AM22 -> 0 | T22: =AN22 -> 0 | AJ22: ='EQUIPO ENERO 2025'!AP22 -> 0 | AK22: =P22-Z22+AE22+U22 -> 0 | AL22: =Q22-AA22+AF22+V22 -> 0 | AM22: =R22-AB22+AG22+W22 -> 0 | AN22: =S22-AC22+AH22+X22 -> 0 | AO22: =T22-AD22+AI22+Y22 -> 0 | AQ22: =AO22 -> 0
A23: =A22+1 -> 18 | B23: BALANZA ANALITICA CAPACIDAD DE 1 000 g x 20 mg | C23: N/A | D23: ELECTRONIC BALANCE | E23: SE-10003N | F23: 1 000 g x 20 mg | G23: #VALUE! | I23: SE10003N | J23: LOCOSC | K23: 45336 | L23: 669885E9 | M23: 37 | O23: ='EQUIPO MARZO 2025 1'!AQ23 -> 0 | P23: =O23 -> 0 | Q23: =AK23 -> 0 | R23: =AL23 -> 0 | S23: =AM23 -> 0 | T23: =AN23 -> 0 | AJ23: ='EQUIPO ENERO 2025'!AP23 -> 0 | AK23: =P23-Z23+AE23+U23 -> 0 | AL23: =Q23-AA23+AF23+V23 -> 0 | AM23: =R23-AB23+AG23+W23 -> 0 | AN23: =S23-AC23+AH23+X23 -> 0 | AO23: =T23-AD23+AI23+Y23 -> 0 | AQ23: =AO23 -> 0
A24: =A23+1 -> 19 | B24: BALANZA ANALITICA CAPACIDAD DE 210 g x 10 mg | C24: N/A | D24: ELECTRONIC BALANCE | E24: SE-2085A | F24: 210 g x 10 mg | G24: #VALUE! | I24: SE2085A | J24: LOCOSC | K24: 45336 | L24: 669885E9 | M24: 38 | O24: ='EQUIPO MARZO 2025 1'!AQ24 -> 0 | P24: =O24 -> 0 | Q24: =AK24 -> 0 | R24: =AL24 -> 0 | S24: =AM24 -> 0 | T24: =AN24 -> 0 | AJ24: ='EQUIPO ENERO 2025'!AP24 -> 0 | AK24: =P24-Z24+AE24+U24 -> 0 | AL24: =Q24-AA24+AF24+V24 -> 0 | AM24: =R24-AB24+AG24+W24 -> 0 | AN24: =S24-AC24+AH24+X24 -> 0 | AO24: =T24-AD24+AI24+Y24 -> 0 | AQ24: =AO24 -> 0
A25: =A24+1 -> 20 | B25: BALANZA DE LABORATORIO CAPACIDAD 420 x 0.001g LUNA | C25: No.1 | E25: SE-LPB423E | F25: 420 x 0.001 g | G25: #VALUE! | I25: LPB423E | J25: ADAM | K25: 45454 | L25: 34687-035292 | M25: 76 | O25: ='EQUIPO MARZO 2025 1'!AQ25 -> 0 | P25: =O25 -> 0 | Q25: =AK25 -> 0 | R25: =AL25 -> 0 | S25: =AM25 -> 0 | T25: =AN25 -> 0 | AJ25: ='EQUIPO ENERO 2025'!AP25 -> 0 | AK25: =P25-Z25+AE25+U25 -> 0 | AL25: =Q25-AA25+AF25+V25 -> 0 | AM25: =R25-AB25+AG25+W25 -> 0 | AN25: =S25-AC25+AH25+X25 -> 0 | AO25: =T25-AD25+AI25+Y25 -> 0 | AQ25: =AO25 -> 0
A26: =A25+1 -> 21 | B26: BÁSCULA DE MESA | C26: No. 1 | D26: BRECKNELL | E26: SE-7680W | F26: 3 x 0.005 kg | G26: #VALUE! | H26: 2800 | I26: SE-LP7680-3Kg | J26: LOCOSC | K26: 45574 | L26: LP3211240 | M26: 71 | O26: ='EQUIPO MARZO 2025 1'!AQ26 -> 8 | P26: =O26 -> 8 | Q26: =AK26 -> 8 | R26: =AL26 -> 8 | S26: =AM26 -> 8 | T26: =AN26 -> 8 | AJ26: ='EQUIPO ENERO 2025'!AP26 -> 8 | AK26: =P26-Z26+AE26+U26 -> 8 | AL26: =Q26-AA26+AF26+V26 -> 8 | AM26: =R26-AB26+AG26+W26 -> 8 | AN26: =S26-AC26+AH26+X26 -> 8 | AO26: =T26-AD26+AI26+Y26 -> 8 | AQ26: =AO26 -> 8
A27: =A26+1 -> 22 | B27: BÁSCULA DE MESA | C27: No. 1 | D27: BRECKNELL | E27: SE-7680W | F27: 6 x 0.001 kg | G27: #VALUE! | H27: 2800 | I27: SE-LP7680-6Kg | J27: LOCOSC | K27: 45574 | L27: LP3211240 | M27: 71 | N27: coporacion empresarial la paz | O27: ='EQUIPO MARZO 2025 1'!AQ27 -> 10 | P27: =O27 -> 10 | Q27: =AK27 -> 10 | R27: =AL27 -> 10 | S27: =AM27 -> 10 | T27: =AN27 -> 10 | AD27: 1 | AJ27: ='EQUIPO ENERO 2025'!AP27 -> 10 | AK27: =P27-Z27+AE27+U27 -> 10 | AL27: =Q27-AA27+AF27+V27 -> 10 | AM27: =R27-AB27+AG27+W27 -> 10 | AN27: =S27-AC27+AH27+X27 -> 10 | AO27: =T27-AD27+AI27+Y27 -> 9 | AQ27: =AO27 -> 9 | AR27: 2522433885 | AS27: 405
A28: =A27+1 -> 23 | B28: BÁSCULA DE MESA | C28: No. 1 | D28: BRECKNELL | E28: SE-7680W | F28: 15 x 0.002 kg | G28: #VALUE! | H28: 2800 | I28: SE-LP7680-15Kg | J28: LOCOSC | K28: 45574 | L28: LP3211240 | M28: 71 | O28: ='EQUIPO MARZO 2025 1'!AQ28 -> 6 | P28: =O28 -> 6 | Q28: =AK28 -> 6 | R28: =AL28 -> 6 | S28: =AM28 -> 6 | T28: =AN28 -> 6 | AJ28: ='EQUIPO ENERO 2025'!AP28 -> 6 | AK28: =P28-Z28+AE28+U28 -> 6 | AL28: =Q28-AA28+AF28+V28 -> 6 | AM28: =R28-AB28+AG28+W28 -> 6 | AN28: =S28-AC28+AH28+X28 -> 6 | AO28: =T28-AD28+AI28+Y28 -> 6 | AQ28: =AO28 -> 6
A29: =A28+1 -> 24 | B29: BASCULA DE MESA MODELO SE-7680W | C29: No. 1 | D29: BRECKNELL | E29: SE-7680W | F29: 30 x 0.005 kg | G29: #VALUE! | H29: 3000 | I29: SE-LP7680-30kg | J29: LOCOSC | K29: 45107 | L29: LP230224-1 | M29: 390 | O29: ='EQUIPO MARZO 2025 1'!AQ29 -> 5 | P29: =O29 -> 5 | Q29: =AK29 -> 5 | R29: =AL29 -> 5 | S29: =AM29 -> 5 | T29: =AN29 -> 5 | AJ29: ='EQUIPO ENERO 2025'!AP29 -> 5 | AK29: =P29-Z29+AE29+U29 -> 5 | AL29: =Q29-AA29+AF29+V29 -> 5 | AM29: =R29-AB29+AG29+W29 -> 5 | AN29: =S29-AC29+AH29+X29 -> 5 | AO29: =T29-AD29+AI29+Y29 -> 5 | AQ29: =AO29 -> 5
A30: =A29+1 -> 25 | B30: BALANZA ELECTRONIC BALANCE MODELO SE-2003CH DE 2000gx1mg | C30: N/A | D30: ELECTRONIC BALANCE | E30: SE-2003CH | F30: 200 x 1 mg | G30: #VALUE! | H30: 6300 | I30: SE-2003CH | J30: LOCOSC | K30: 45139 | L30: 781781092133 | M30: 419 | O30: ='EQUIPO MARZO 2025 1'!AQ30 -> 0 | P30: =O30 -> 0 | Q30: =AK30 -> 0 | R30: =AL30 -> 0 | S30: =AM30 -> 0 | T30: =AN30 -> 0 | AJ30: ='EQUIPO ENERO 2025'!AP30 -> 0 | AK30: =P30-Z30+AE30+U30 -> 0 | AL30: =Q30-AA30+AF30+V30 -> 0 | AM30: =R30-AB30+AG30+W30 -> 0 | AN30: =S30-AC30+AH30+X30 -> 0 | AO30: =T30-AD30+AI30+Y30 -> 0 | AQ30: =AO30 -> 0
A31: =A30+1 -> 26 | B31: BASES DE CELDA DE CARGA PARA CELDAS DE ACEROS DE GUATEMALA | C31: NO. 2 | D31: S/M | E31: S/M | G31: #VALUE! | K31: 45568 | M31: 62 | O31: ='EQUIPO MARZO 2025 1'!AQ31 -> 2 | P31: =O31 -> 2 | Q31: =AK31 -> 2 | R31: =AL31 -> 2 | S31: =AM31 -> 2 | T31: =AN31 -> 2 | AJ31: ='EQUIPO ENERO 2025'!AP31 -> 2 | AK31: =P31-Z31+AE31+U31 -> 2 | AL31: =Q31-AA31+AF31+V31 -> 2 | AM31: =R31-AB31+AG31+W31 -> 2 | AN31: =S31-AC31+AH31+X31 -> 2 | AO31: =T31-AD31+AI31+Y31 -> 2 | AQ31: =AO31 -> 2
A32: =A31+1 -> 27 | B32: BASCULA COLGANTE CAPACIDAD 5 t LP7650G | C32: NO.2 | D32: BRECKNELL | E32: SE-7650 | F32: 5 T | G32: #VALUE! | H32: 9500 | I32: SE-LP7650G-5T | J32: SIZEN | K32: 45666 | L32: LK24112701 | M32: 117 | O32: ='EQUIPO MARZO 2025 1'!AQ32 -> 1 | P32: =O32 -> 1 | Q32: =AK32 -> 1 | R32: =AL32 -> 1 | S32: =AM32 -> 1 | T32: =AN32 -> 1 | AJ32: ='EQUIPO ENERO 2025'!AP32 -> 1 | AK32: =P32-Z32+AE32+U32 -> 1 | AL32: =Q32-AA32+AF32+V32 -> 1 | AM32: =R32-AB32+AG32+W32 -> 1 | AN32: =S32-AC32+AH32+X32 -> 1 | AO32: =T32-AD32+AI32+Y32 -> 1 | AQ32: =AO32 -> 1
A33: =A32+1 -> 28 | B33: BASCULA COLGANTE CAPACIDAD 10 t LP7650G | C33: No. 2 | D33: BRECKNELL | E33: SE-7650 | F33: 10 t | G33: #VALUE! | H33: Q16,800.00 Consultar primero | I33: SE-LP7650G-10T | J33: LOCOSC | K33: 45107 | L33: LP230224-1 | M33: 393 | O33: ='EQUIPO MARZO 2025 1'!AQ33 -> 1 | P33: =O33 -> 1 | Q33: =AK33 -> 1 | R33: =AL33 -> 1 | S33: =AM33 -> 1 | T33: =AN33 -> 1 | AJ33: ='EQUIPO ENERO 2025'!AP33 -> 1 | AK33: =P33-Z33+AE33+U33 -> 1 | AL33: =Q33-AA33+AF33+V33 -> 1 | AM33: =R33-AB33+AG33+W33 -> 1 | AN33: =S33-AC33+AH33+X33 -> 1 | AO33: =T33-AD33+AI33+Y33 -> 1 | AQ33: =AO33 -> 1
A34: =A33+1 -> 29 | B34: BASCULA COLGANTE CAPACIDAD 300kg LP7652G | C34: No. 1 | D34: BRECKNELL | E34: SE-7652 | F34: 300 x 0.1 kg | G34: #VALUE! | H34: 650 | I34: SE-COLG-LP7652G | J34: LOCOSC | K34: 45107 | L34: LP230224-1 | M34: 389 | O34: ='EQUIPO MARZO 2025 1'!AQ34 -> 11 | P34: =O34 -> 11 | Q34: =AK34 -> 11 | R34: =AL34 -> 11 | S34: =AM34 -> 11 | T34: =AN34 -> 11 | AJ34: ='EQUIPO ENERO 2025'!AP34 -> 11 | AK34: =P34-Z34+AE34+U34 -> 11 | AL34: =Q34-AA34+AF34+V34 -> 11 | AM34: =R34-AB34+AG34+W34 -> 11 | AN34: =S34-AC34+AH34+X34 -> 11 | AO34: =T34-AD34+AI34+Y34 -> 11 | AQ34: =AO34 -> 11
A35: =A34+1 -> 30 | B35: BASCULA COLGANTE PANTALLA LED DE 5 DIGITOS | C35: No. 1 | D35: BRECKNELL | E35: SE-7561 | F35: 300 x 0.1 kg | G35: #VALUE! | H35: 1800 | I35: SE-LP7561E | J35: LOCOSC | K35: 44592 | O35: ='EQUIPO MARZO 2025 1'!AQ35 -> 6 | P35: =O35 -> 6 | Q35: =AK35 -> 6 | R35: =AL35 -> 6 | S35: =AM35 -> 6 | T35: =AN35 -> 6 | AJ35: ='EQUIPO ENERO 2025'!AP35 -> 6 | AK35: =P35-Z35+AE35+U35 -> 6 | AL35: =Q35-AA35+AF35+V35 -> 6 | AM35: =R35-AB35+AG35+W35 -> 6 | AN35: =S35-AC35+AH35+X35 -> 6 | AO35: =T35-AD35+AI35+Y35 -> 6 | AQ35: =AO35 -> 6
A36: =A35+1 -> 31 | B36: BASCULA DE MESA CAPACIDAD 30kgx1g | C36: No. 1 | D36: ELECTRONIC BALANCE | E36: SE-WT300001X | F36: 30 kg x 1 g | G36: #VALUE! | H36: 3400 | I36: SE-WT300001X | J36: LOCOSC | K36: 45107 | L36: LP230224-1 | M36: 393 | O36: ='EQUIPO MARZO 2025 1'!AQ36 -> 4 | P36: =O36 -> 4 | Q36: =AK36 -> 4 | R36: =AL36 -> 4 | S36: =AM36 -> 4 | T36: =AN36 -> 4 | AJ36: ='EQUIPO ENERO 2025'!AP36 -> 4 | AK36: =P36-Z36+AE36+U36 -> 4 | AL36: =Q36-AA36+AF36+V36 -> 4 | AM36: =R36-AB36+AG36+W36 -> 4 | AN36: =S36-AC36+AH36+X36 -> 4 | AO36: =T36-AD36+AI36+Y36 -> 4 | AQ36: =AO36 -> 4
A37: =A36+1 -> 32 | B37: BASCULA DE MESA MODELO SE-Y2-208 CAPACIDAD 40kg X 5g | C37: No. 1 | D37: TECNO SCALE | E37: SE-Y2-208 | F37: 40 kg x 5 g | G37: #VALUE! | H37: 550 | I37: SE-Y2-208 | J37: LOCOSC | K37: 45328 | L37: LP230224-1 | M37: 32 | O37: ='EQUIPO MARZO 2025 1'!AQ37 -> 12 | P37: =O37 -> 12 | Q37: =AK37 -> 12 | R37: =AL37 -> 12 | S37: =AM37 -> 12 | T37: =AN37 -> 12 | AJ37: ='EQUIPO ENERO 2025'!AP37 -> 14 | AK37: =P37-Z37+AE37+U37 -> 12 | AL37: =Q37-AA37+AF37+V37 -> 12 | AM37: =R37-AB37+AG37+W37 -> 12 | AN37: =S37-AC37+AH37+X37 -> 12 | AO37: =T37-AD37+AI37+Y37 -> 12 | AQ37: =AO37 -> 12
A38: =A37+1 -> 33 | B38: BASCULA DE PISO ACERO INOXIDABLE CAPACIDAD 150kg DE 40X50 | C38: No. 1 | D38: BRECKNELL | E38: SE-7610W | F38: 150 x 0.02 kg | G38: #VALUE! | H38: 7500 | I38: SE-7510W-150kg | J38: LOCOSC | K38: 45107 | L38: LP230224-1 | M38: 392 | O38: ='EQUIPO MARZO 2025 1'!AQ38 -> 5 | P38: =O38 -> 5 | Q38: =AK38 -> 5 | R38: =AL38 -> 5 | S38: =AM38 -> 5 | T38: =AN38 -> 5 | AJ38: ='EQUIPO ENERO 2025'!AP38 -> 5 | AK38: =P38-Z38+AE38+U38 -> 5 | AL38: =Q38-AA38+AF38+V38 -> 5 | AM38: =R38-AB38+AG38+W38 -> 5 | AN38: =S38-AC38+AH38+X38 -> 5 | AO38: =T38-AD38+AI38+Y38 -> 5 | AP38: 1 | AQ38: =AO38 -> 5
A39: =A38+1 -> 34 | B39: BÁSCULA DE PISO SS ACERO INOXIDABLE CAPACIDAD 150 kg DE 60 x 60 cm | C39: NO. 1 | D39: BRECKNELL | E39: SE-7610WSS | F39: 150 x 0.02 kg | G39: #VALUE! | H39: 10800 | I39: SE7610W-SS-6060-150kg | J39: LOCOSC | K39: 45673 | L39: 240907-1 | M39: 126 | O39: ='EQUIPO MARZO 2025 1'!AQ39 -> 5 | P39: =O39 -> 5 | Q39: =AK39 -> 5 | R39: =AL39 -> 5 | S39: =AM39 -> 5 | T39: =AN39 -> 5 | AJ39: ='EQUIPO ENERO 2025'!AP39 -> 5 | AK39: =P39-Z39+AE39+U39 -> 5 | AL39: =Q39-AA39+AF39+V39 -> 5 | AM39: =R39-AB39+AG39+W39 -> 5 | AN39: =S39-AC39+AH39+X39 -> 5 | AO39: =T39-AD39+AI39+Y39 -> 5 | AP39: 1 | AQ39: =AO39 -> 5
A40: =A39+1 -> 35 | B40: BASCULA DE PISO CAPACIDAD 30kg DE 40X40 | C40: No. 1 | D40: BRECKNELL | E40: SE-7610 | F40: 30 x 0.005 kg | G40: #VALUE! | H40: 2800 | I40: SE-LP7610-30kg | J40: LOCOSC | K40: 45574 | L40: LP3211240 | M40: 71 | N40: HBSC S.A. AE0230329006/ coporacion empresarial la paz AE0230329005 | O40: ='EQUIPO MARZO 2025 1'!AQ40 -> 6 | P40: =O40 -> 6 | Q40: =AK40 -> 5 | R40: =AL40 -> 5 | S40: =AM40 -> 5 | T40: =AN40 -> 5 | Z40: 1 | AD40: 1 | AJ40: ='EQUIPO ENERO 2025'!AP40 -> 8 | AK40: =P40-Z40+AE40+U40 -> 5 | AL40: =Q40-AA40+AF40+V40 -> 5 | AM40: =R40-AB40+AG40+W40 -> 5 | AN40: =S40-AC40+AH40+X40 -> 5 | AO40: =T40-AD40+AI40+Y40 -> 4 | AP40: 1 | AQ40: =AO40 -> 4 | AR40: 1596673948/2522433885 | AS40: 383/398
A41: =A40+1 -> 36 | B41: BASCULA DE PISO CAPACIDAD 60kg DE 40X50 | C41: No. 1 | D41: BRECKNELL | E41: SE-7610 | F41: 60 x 0.01 kg | G41: #VALUE! | H41: 2800 | I41: SE-LP7610-60kg | J41: LOCOSC | K41: 45574 | L41: LP3211240 | M41: 71 | O41: ='EQUIPO MARZO 2025 1'!AQ41 -> 2 | P41: =O41 -> 2 | Q41: =AK41 -> 2 | R41: =AL41 -> 2 | S41: =AM41 -> 2 | T41: =AN41 -> 2 | AJ41: ='EQUIPO ENERO 2025'!AP41 -> 2 | AK41: =P41-Z41+AE41+U41 -> 2 | AL41: =Q41-AA41+AF41+V41 -> 2 | AM41: =R41-AB41+AG41+W41 -> 2 | AN41: =S41-AC41+AH41+X41 -> 2 | AO41: =T41-AD41+AI41+Y41 -> 2 | AP41: 0 | AQ41: =AO41 -> 2
A42: =A41+1 -> 37 | B42: BASCULA DE PISO PLATAFORMA /ABS CAJA | C42: No. 1 | D42: BRECKNELL | E42: SE-LP7611 | F42: 600 x 0.5 kg | G42: #VALUE! | H42: 5500 | I42: SE7611J-5060-600kg | J42: LOCOSC | K42: 45673 | L42: 240907-1 | M42: 127 | N42: parma 241012003,241012004 | O42: ='EQUIPO MARZO 2025 1'!AQ42 -> 9 | P42: =O42 -> 9 | Q42: =AK42 -> 7 | R42: =AL42 -> 7 | S42: =AM42 -> 7 | T42: =AN42 -> 7 | Z42: 2 | AJ42: ='EQUIPO ENERO 2025'!AP42 -> 10 | AK42: =P42-Z42+AE42+U42 -> 7 | AL42: =Q42-AA42+AF42+V42 -> 7 | AM42: =R42-AB42+AG42+W42 -> 7 | AN42: =S42-AC42+AH42+X42 -> 7 | AO42: =T42-AD42+AI42+Y42 -> 7 | AP42: 1 | AQ42: =AO42 -> 7 | AR42: 996035683 | AS42: 392
A43: =A42+1 -> 38 | B43: BÁSCULA DE PLATAFORMA SE7611 DE 1 000 kg | C43: LAB | D43: BRECKNELL | E43: SE7611T | F43: 1 000 kg | G43: #VALUE! | I43: SE7611-1X1M-1T | J43: LOCOSC | K43: 45673 | L43: 240907-1 | M43: 128 | O43: ='EQUIPO MARZO 2025 1'!AQ43 -> 10 | P43: =O43 -> 10 | Q43: =AK43 -> 10 | R43: =AL43 -> 10 | S43: =AM43 -> 10 | T43: =AN43 -> 10 | AJ43: ='EQUIPO ENERO 2025'!AP43 -> 10 | AK43: =P43-Z43+AE43+U43 -> 10 | AL43: =Q43-AA43+AF43+V43 -> 10 | AM43: =R43-AB43+AG43+W43 -> 10 | AN43: =S43-AC43+AH43+X43 -> 10 | AO43: =T43-AD43+AI43+Y43 -> 10 | AP43: 1 | AQ43: =AO43 -> 10
A44: =A43+1 -> 39 | B44: BASCULA ELECTRNICA SK 10 WP | C44: No. 1 | D44: AND | E44: SE-SK10WP | F44: 10 x 0.02 kg | G44: #VALUE! | H44: 2000 | I44: SE-BASELE-SK10KWP | J44: AND | K44: 44592 | O44: ='EQUIPO MARZO 2025 1'!AQ44 -> 1 | P44: =O44 -> 1 | Q44: =AK44 -> 1 | R44: =AL44 -> 1 | S44: =AM44 -> 1 | T44: =AN44 -> 1 | AJ44: ='EQUIPO ENERO 2025'!AP44 -> 1 | AK44: =P44-Z44+AE44+U44 -> 1 | AL44: =Q44-AA44+AF44+V44 -> 1 | AM44: =R44-AB44+AG44+W44 -> 1 | AN44: =S44-AC44+AH44+X44 -> 1 | AO44: =T44-AD44+AI44+Y44 -> 1 | AQ44: =AO44 -> 1
A45: =A44+1 -> 40 | B45: BASCULA ELECTRONICA 405 15 K | C45: No. 1 | D45: BRECKNELL | E45: SE-405 | F45: 15 x 0.002 kg | G45: #VALUE! | H45: 1500 | I45: SE-BASELE-405 | J45: BRECKNELL | K45: 44592 | O45: ='EQUIPO MARZO 2025 1'!AQ45 -> 1 | P45: =O45 -> 1 | Q45: =AK45 -> 1 | R45: =AL45 -> 1 | S45: =AM45 -> 1 | T45: =AN45 -> 1 | AJ45: ='EQUIPO ENERO 2025'!AP45 -> 1 | AK45: =P45-Z45+AE45+U45 -> 1 | AL45: =Q45-AA45+AF45+V45 -> 1 | AM45: =R45-AB45+AG45+W45 -> 1 | AN45: =S45-AC45+AH45+X45 -> 1 | AO45: =T45-AD45+AI45+Y45 -> 1 | AQ45: =AO45 -> 1
A46: =A45+1 -> 41 | B46: BASCULA ELECTRONICA C 3235 6 K | C46: No. 1 | D46: BRECKNELL | E46: SE-3235 | F46: 6 x 0.001 kg | G46: #VALUE! | H46: 3200 | I46: SE-BASELE-BRCK-C3235-6 | J46: BRECKNELL | K46: 44592 | O46: ='EQUIPO MARZO 2025 1'!AQ46 -> 0 | P46: =O46 -> 0 | Q46: =AK46 -> 0 | R46: =AL46 -> 0 | S46: =AM46 -> 0 | T46: =AN46 -> 0 | AJ46: ='EQUIPO ENERO 2025'!AP46 -> 0 | AK46: =P46-Z46+AE46+U46 -> 0 | AL46: =Q46-AA46+AF46+V46 -> 0 | AM46: =R46-AB46+AG46+W46 -> 0 | AN46: =S46-AC46+AH46+X46 -> 0 | AO46: =T46-AD46+AI46+Y46 -> 0 | AQ46: =AO46 -> 0
A47: =A46+1 -> 42 | B47: BASCULA ELECTRONICA C 3235 6 K (PARA DEMO) | C47: No. 1 | D47: BRECKNELL | E47: SE-3235 | F47: 6 x 0.001 kg | G47: #VALUE! | H47: 3200 | I47: SE-BASELE-BRCK-C3235-6-D | J47: BRECKNELL | K47: 44592 | O47: ='EQUIPO MARZO 2025 1'!AQ47 -> 1 | P47: =O47 -> 1 | Q47: =AK47 -> 1 | R47: =AL47 -> 1 | S47: =AM47 -> 1 | T47: =AN47 -> 1 | AJ47: ='EQUIPO ENERO 2025'!AP47 -> 1 | AK47: =P47-Z47+AE47+U47 -> 1 | AL47: =Q47-AA47+AF47+V47 -> 1 | AM47: =R47-AB47+AG47+W47 -> 1 | AN47: =S47-AC47+AH47+X47 -> 1 | AO47: =T47-AD47+AI47+Y47 -> 1 | AP47: 1 | AQ47: =AO47 -> 1
A48: =A47+1 -> 43 | B48: BASCULA ELECTRONICA COLGANTE BRECKNELL 45 K | C48: No. 1 | D48: BRECKNELL | E48: ELECTROSAMSON SE-ESN | F48: 45 x 0.05 kg | G48: #VALUE! | H48: 1725 | I48: SE-GE-BEC-ES-45K | J48: BRECKNELL | K48: 45693 | L48: 2130012 | M48: 153 | O48: ='EQUIPO MARZO 2025 1'!AQ48 -> 3 | P48: =O48 -> 3 | Q48: =AK48 -> 3 | R48: =AL48 -> 3 | S48: =AM48 -> 3 | T48: =AN48 -> 3 | AJ48: ='EQUIPO ENERO 2025'!AP48 -> 1 | AK48: =P48-Z48+AE48+U48 -> 3 | AL48: =Q48-AA48+AF48+V48 -> 3 | AM48: =R48-AB48+AG48+W48 -> 3 | AN48: =S48-AC48+AH48+X48 -> 3 | AO48: =T48-AD48+AI48+Y48 -> 3 | AQ48: =AO48 -> 3
A49: =A48+1 -> 44 | B49: BASCULA ELECTRONICA SK 10 KEG | C49: No. 1 | D49: AND | E49: SE-SK10KEG | F49: 10 x 0.005 kg | G49: #VALUE! | H49: 1500 | I49: SE-BASELE-SK10KEG | J49: AND | K49: 44592 | O49: ='EQUIPO MARZO 2025 1'!AQ49 -> 1 | P49: =O49 -> 1 | Q49: =AK49 -> 1 | R49: =AL49 -> 1 | S49: =AM49 -> 1 | T49: =AN49 -> 1 | AJ49: ='EQUIPO ENERO 2025'!AP49 -> 1 | AK49: =P49-Z49+AE49+U49 -> 1 | AL49: =Q49-AA49+AF49+V49 -> 1 | AM49: =R49-AB49+AG49+W49 -> 1 | AN49: =S49-AC49+AH49+X49 -> 1 | AO49: =T49-AD49+AI49+Y49 -> 1 | AQ49: =AO49 -> 1
A50: =A49+1 -> 45 | B50: BASCULA ELECTRONICA SK 20 KEG | C50: No. 1 | D50: AND | E50: SE-SK20KEG | F50: 20 x 0.1 kg | G50: #VALUE! | H50: 1500 | I50: SE-BASELE-SK20KEG | J50: AND | K50: 44592 | O50: ='EQUIPO MARZO 2025 1'!AQ50 -> 1 | P50: =O50 -> 1 | Q50: =AK50 -> 1 | R50: =AL50 -> 1 | S50: =AM50 -> 1 | T50: =AN50 -> 1 | AJ50: ='EQUIPO ENERO 2025'!AP50 -> 1 | AK50: =P50-Z50+AE50+U50 -> 1 | AL50: =Q50-AA50+AF50+V50 -> 1 | AM50: =R50-AB50+AG50+W50 -> 1 | AN50: =S50-AC50+AH50+X50 -> 1 | AO50: =T50-AD50+AI50+Y50 -> 1 | AQ50: =AO50 -> 1
A51: =A50+1 -> 46 | B51: BASCULA N1124-LL MECANICA MODELO SE-1124B | C51: N/A | D51: FAIRBANKS MORSE | E51: SE-1124B | F51: 1 200 x 0.5 lb | G51: #VALUE! | H51: 9800 | I51: SE-BASC-MECA | J51: SIDASA | K51: 45315 | L51: 3673178618 | M51: 11 | O51: ='EQUIPO MARZO 2025 1'!AQ51 -> 0 | P51: =O51 -> 0 | Q51: =AK51 -> 0 | R51: =AL51 -> 0 | S51: =AM51 -> 0 | T51: =AN51 -> 0 | AJ51: ='EQUIPO ENERO 2025'!AP51 -> 0 | AK51: =P51-Z51+AE51+U51 -> 0 | AL51: =Q51-AA51+AF51+V51 -> 0 | AM51: =R51-AB51+AG51+W51 -> 0 | AN51: =S51-AC51+AH51+X51 -> 0 | AO51: =T51-AD51+AI51+Y51 -> 0 | AQ51: =AO51 -> 0
A52: =A51+1 -> 47 | B52: BASCULA TMF-30kg | C52: No. 2 | D52: TM | E52: TMF | F52: 30 x 0.005 kg | G52: #VALUE! | H52: 4800 | I52: SE-BAS-TMF-30 | J52: LOCOSC | K52: 45107 | L52: LP230224-1 | M52: 393 | O52: ='EQUIPO MARZO 2025 1'!AQ52 -> -1 | P52: =O52 -> -1 | Q52: =AK52 -> -1 | R52: =AL52 -> -1 | S52: =AM52 -> -1 | T52: =AN52 -> 3 | X52: 4 | AJ52: ='EQUIPO ENERO 2025'!AP52 -> 1 | AK52: =P52-Z52+AE52+U52 -> -1 | AL52: =Q52-AA52+AF52+V52 -> -1 | AM52: =R52-AB52+AG52+W52 -> -1 | AN52: =S52-AC52+AH52+X52 -> 3 | AO52: =T52-AD52+AI52+Y52 -> 3 | AQ52: =AO52 -> 3
A53: =A52+1 -> 48 | B53: BASCULA-TMF-15K | C53: No. 2 | D53: TM | F53: 15 x 0.001 kg | G53: #VALUE! | H53: 4800 | I53: SE-BASC-TMF | J53: LOCOSC | K53: 44592 | O53: ='EQUIPO MARZO 2025 1'!AQ53 -> 1 | P53: =O53 -> 1 | Q53: =AK53 -> 1 | R53: =AL53 -> 1 | S53: =AM53 -> 1 | T53: =AN53 -> 1 | AJ53: ='EQUIPO ENERO 2025'!AP53 -> 1 | AK53: =P53-Z53+AE53+U53 -> 1 | AL53: =Q53-AA53+AF53+V53 -> 1 | AM53: =R53-AB53+AG53+W53 -> 1 | AN53: =S53-AC53+AH53+X53 -> 1 | AO53: =T53-AD53+AI53+Y53 -> 1 | AQ53: =AO53 -> 1
A54: =A53+1 -> 49 | B54: BASCULA PESA EJES CON MARCO/INDICADOR LP7561 (SOLO MODULOS X2PADS) | C54: LAB | D54: TECNO SCALE | E54: SE-LP7662 | F54: 30 t | G54: #VALUE! | I54: SE7662-1530-30T*2PADS | J54: LOCOSC | K54: 45687 | L54: 240907-1 | M54: 144 | O54: ='EQUIPO MARZO 2025 1'!AQ54 -> 4 | P54: =O54 -> 4 | Q54: =AK54 -> 4 | R54: =AL54 -> 4 | S54: =AM54 -> 4 | T54: =AN54 -> 4 | AJ54: ='EQUIPO ENERO 2025'!AP54 -> 4 | AK54: =P54-Z54+AE54+U54 -> 4 | AL54: =Q54-AA54+AF54+V54 -> 4 | AM54: =R54-AB54+AG54+W54 -> 4 | AN54: =S54-AC54+AH54+X54 -> 4 | AO54: =T54-AD54+AI54+Y54 -> 4 | AQ54: =AO54 -> 4
A55: =A54+1 -> 50 | B55: BASCULA PESA EJES/INDICADOR LP7561 | C55: No.1 | D55: TECNO SCALE | E55: SE-7662 | F55: 30T | G55: #VALUE! | I55: SE-7662-1530-30T*2 PADS | J55: LOCOSC | K55: 45566 | L55: LP240702-2 | M55: 68 | O55: ='EQUIPO MARZO 2025 1'!AQ55 -> 1 | P55: =O55 -> 1 | Q55: =AK55 -> 1 | R55: =AL55 -> 1 | S55: =AM55 -> 1 | T55: =AN55 -> 1 | AJ55: ='EQUIPO ENERO 2025'!AP55 -> 0 | AK55: =P55-Z55+AE55+U55 -> 1 | AL55: =Q55-AA55+AF55+V55 -> 1 | AM55: =R55-AB55+AG55+W55 -> 1 | AN55: =S55-AC55+AH55+X55 -> 1 | AO55: =T55-AD55+AI55+Y55 -> 1 | AQ55: =AO55 -> 1
A56: =A55+1 -> 51 | B56: BASCULA PESA ANIMAL (CERDOS) SE-7628A | C56: No.1 | D56: BRECKNELL | E56: SE-7628A | F56: 2 T | G56: #VALUE! | I56: SE-7628A-1215-2T | J56: LOCOSC | K56: 45566 | L56: LP240702-2 | M56: 75 | N56: grupo salva | O56: ='EQUIPO MARZO 2025 1'!AQ56 -> 2 | P56: =O56 -> 2 | Q56: =AK56 -> 2 | R56: =AL56 -> 2 | S56: =AM56 -> 2 | T56: =AN56 -> 2 | AC56: 1 | AH56: 1 | AJ56: ='EQUIPO ENERO 2025'!AP56 -> 2 | AK56: =P56-Z56+AE56+U56 -> 2 | AL56: =Q56-AA56+AF56+V56 -> 2 | AM56: =R56-AB56+AG56+W56 -> 2 | AN56: =S56-AC56+AH56+X56 -> 2 | AO56: =T56-AD56+AI56+Y56 -> 2 | AQ56: =AO56 -> 2 | AR56: 567561408 | AS56: 394
A57: =A56+1 -> 52 | B57: BASCULA PESA ANIMAL (GANADO) SE-7628A | C57: No.1 | D57: BRECKNELL | E57: SE-7628A | F57: 1.5T | G57: #VALUE! | I57: SE-7628A-0923-1.5T | J57: LOCOSC | K57: 45566 | L57: LP240702-2 | M57: 75 | O57: ='EQUIPO MARZO 2025 1'!AQ57 -> 7 | P57: =O57 -> 7 | Q57: =AK57 -> 7 | R57: =AL57 -> 7 | S57: =AM57 -> 7 | T57: =AN57 -> 7 | AJ57: ='EQUIPO ENERO 2025'!AP57 -> 7 | AK57: =P57-Z57+AE57+U57 -> 7 | AL57: =Q57-AA57+AF57+V57 -> 7 | AM57: =R57-AB57+AG57+W57 -> 7 | AN57: =S57-AC57+AH57+X57 -> 7 | AO57: =T57-AD57+AI57+Y57 -> 7 | AQ57: =AO57 -> 7
A58: =A57+1 -> 53 | B58: BÁSCULA BANDA DINAMICA INCLUYE 1 INDICADOR CON ARMARIO, 4 CELDAS DE CARGA TIPO S TSC 500 kg METTLER TOLEDO, 8 RODILLOS Y 1 ESTRUCTURA DE METAL | D58: TECNO SCALE | E58: SE-ICS-17A | F58: 2 T | J58: YORK | K58: 45687 | L58: 04YK01K602 | M58: 141 | O58: ='EQUIPO MARZO 2025 1'!AQ58 -> 1 | P58: =O58 -> 1 | Q58: =AK58 -> 1 | R58: =AL58 -> 1 | S58: =AM58 -> 1 | T58: =AN58 -> 1 | AJ58: ='EQUIPO ENERO 2025'!AP58 -> 1 | AK58: =P58-Z58+AE58+U58 -> 1 | AL58: =Q58-AA58+AF58+V58 -> 1 | AM58: =R58-AB58+AG58+W58 -> 1 | AN58: =S58-AC58+AH58+X58 -> 1 | AO58: =T58-AD58+AI58+Y58 -> 1 | AQ58: =AO58 -> 1
A59: =A58+1 -> 54 | B59: BÁSCULA CAMIONERA 50 T | D59: REVUELTA / AVERY | E59: ZM405 | F59: 50 T | K59: 45689 | M59: 151 | O59: ='EQUIPO MARZO 2025 1'!AQ59 -> 1 | P59: =O59 -> 1 | Q59: =AK59 -> 1 | R59: =AL59 -> 1 | S59: =AM59 -> 1 | T59: =AN59 -> 1 | AJ59: ='EQUIPO ENERO 2025'!AP60 -> 34 | AK59: =P59-Z59+AE59+U59 -> 1 | AL59: =Q59-AA59+AF59+V59 -> 1 | AM59: =R59-AB59+AG59+W59 -> 1 | AN59: =S59-AC59+AH59+X59 -> 1 | AO59: =T59-AD59+AI59+Y59 -> 1 | AQ59: =AO59 -> 1
A60: =A59+1 -> 55 | B60: BATERIAS 4V4AH | C60: No. 2 | D60: S/M | E60: S/M | F60: 4V | G60: #VALUE! | H60: 300 | I60: SE-BAT4V | J60: LOCOSC | K60: 45107 | L60: LP230224-1 | M60: 387 | O60: ='EQUIPO MARZO 2025 1'!AQ60 -> 30 | P60: =O60 -> 30 | Q60: =AK60 -> 30 | R60: =AL60 -> 30 | S60: =AM60 -> 30 | T60: =AN60 -> 30 | AJ60: ='EQUIPO ENERO 2025'!AP60 -> 34 | AK60: =P60-Z60+AE60+U60 -> 30 | AL60: =Q60-AA60+AF60+V60 -> 30 | AM60: =R60-AB60+AG60+W60 -> 30 | AN60: =S60-AC60+AH60+X60 -> 30 | AO60: =T60-AD60+AI60+Y60 -> 30 | AQ60: =AO60 -> 30
A61: =A60+1 -> 56 | B61: BATERIAS 6V4AH | C61: No. 2 | D61: S/M | E61: S/M | F61: 6V | G61: #VALUE! | H61: 300 | I61: SE-BAT6V | J61: LOCOSC | K61: 45107 | L61: LP230224-1 | M61: 387 | N61: apparell&textil/metaleenvase/ guamolsa | O61: ='EQUIPO MARZO 2025 1'!AQ61 -> 51 | P61: =O61 -> 51 | Q61: =AK61 -> 49 | R61: =AL61 -> 49 | S61: =AM61 -> 49 | T61: =AN61 -> 48 | Z61: 2 | AC61: 1 | AJ61: ='EQUIPO ENERO 2025'!AP61 -> 58 | AK61: =P61-Z61+AE61+U61 -> 49 | AL61: =Q61-AA61+AF61+V61 -> 49 | AM61: =R61-AB61+AG61+W61 -> 49 | AN61: =S61-AC61+AH61+X61 -> 48 | AO61: =T61-AD61+AI61+Y61 -> 48 | AQ61: =AO61 -> 48 | AR61: 4294068844/37355/3499117857 | AS61: 379/381/400
A62: =A61+1 -> 57 | B62: BATERIAS 6V8A NIPPON | C62: NO. 2 | E62: S/M | F62: 6V | M62: 72 | O62: ='EQUIPO MARZO 2025 1'!AQ62 -> 0 | P62: =O62 -> 0 | Q62: =AK62 -> 0 | R62: =AL62 -> 0 | S62: =AM62 -> 0 | T62: =AN62 -> 0 | AJ62: ='EQUIPO ENERO 2025'!AP62 -> 0 | AK62: =P62-Z62+AE62+U62 -> 0 | AL62: =Q62-AA62+AF62+V62 -> 0 | AM62: =R62-AB62+AG62+W62 -> 0 | AN62: =S62-AC62+AH62+X62 -> 0 | AO62: =T62-AD62+AI62+Y62 -> 0 | AQ62: =AO62 -> 0
A63: =A62+1 -> 58 | B63: BATERIAS 3.7V /2000MAH | C63: NO.2 | D63: S/M | E63: GDICR18650 | F63: 3.7V/2000mAH | G63: #VALUE! | I63: SE-BAT3V | J63: LOCOSC | K63: 45574 | L63: LP3211240 | M63: 75 | O63: ='EQUIPO MARZO 2025 1'!AQ63 -> 24 | P63: =O63 -> 24 | Q63: =AK63 -> 24 | R63: =AL63 -> 24 | S63: =AM63 -> 24 | T63: =AN63 -> 24 | AJ63: ='EQUIPO ENERO 2025'!AP63 -> 25 | AK63: =P63-Z63+AE63+U63 -> 24 | AL63: =Q63-AA63+AF63+V63 -> 24 | AM63: =R63-AB63+AG63+W63 -> 24 | AN63: =S63-AC63+AH63+X63 -> 24 | AO63: =T63-AD63+AI63+Y63 -> 24 | AQ63: =AO63 -> 24
A64: =A63+1 -> 59 | B64: BATERIAS 3.7V /4000mAh | C64: NO.2 | D64: S/M | E64: LPB04050 152P | F64: 3.7V/4000mAh | G64: #VALUE! | I64: SE-BAT3V- | J64: LOCOSC | K64: 45574 | L64: LP3211240 | M64: 75 | O64: ='EQUIPO MARZO 2025 1'!AQ64 -> 45 | P64: =O64 -> 45 | Q64: =AK64 -> 45 | R64: =AL64 -> 45 | S64: =AM64 -> 45 | T64: =AN64 -> 45 | AJ64: ='EQUIPO ENERO 2025'!AP64 -> 45 | AK64: =P64-Z64+AE64+U64 -> 45 | AL64: =Q64-AA64+AF64+V64 -> 45 | AM64: =R64-AB64+AG64+W64 -> 45 | AN64: =S64-AC64+AH64+X64 -> 45 | AO64: =T64-AD64+AI64+Y64 -> 45 | AQ64: =AO64 -> 45
A65: =A64+1 -> 60 | B65: BATERIAS 6V/5Ah | C65: NO. 2 | D65: S/M | E65: DJW6-5.0 | F65: 6V/5mAH | G65: #VALUE! | I65: SE-BAT6V/5 | J65: LOCOSC | K65: 45673 | L65: 240907-1 | M65: 130 | O65: ='EQUIPO MARZO 2025 1'!AQ65 -> 2 | P65: =O65 -> 2 | Q65: =AK65 -> 2 | R65: =AL65 -> 2 | S65: =AM65 -> 2 | T65: =AN65 -> 2 | AJ65: ='EQUIPO ENERO 2025'!AP65 -> 4 | AK65: =P65-Z65+AE65+U65 -> 2 | AL65: =Q65-AA65+AF65+V65 -> 2 | AM65: =R65-AB65+AG65+W65 -> 2 | AN65: =S65-AC65+AH65+X65 -> 2 | AO65: =T65-AD65+AI65+Y65 -> 2 | AQ65: =AO65 -> 2
A66: =A65+1 -> 61 | B66: BATERIAS 12V/7.0Ah PARA INDICADOR LP75819 | C66: NO. 2 | D66: S/M | E66: DJW12-7.0 | F66: 12V/7.0mAh | G66: #VALUE! | I66: SE-BAT12V/7 | J66: LOCOSC | K66: 45673 | L66: 240907-1 | M66: 131 | O66: ='EQUIPO MARZO 2025 1'!AQ66 -> 10 | P66: =O66 -> 10 | Q66: =AK66 -> 10 | R66: =AL66 -> 10 | S66: =AM66 -> 10 | T66: =AN66 -> 10 | AJ66: ='EQUIPO ENERO 2025'!AP66 -> 10 | AK66: =P66-Z66+AE66+U66 -> 10 | AL66: =Q66-AA66+AF66+V66 -> 10 | AM66: =R66-AB66+AG66+W66 -> 10 | AN66: =S66-AC66+AH66+X66 -> 10 | AO66: =T66-AD66+AI66+Y66 -> 10 | AQ66: =AO66 -> 10
A67: =A66+1 -> 62 | B67: CABLE CELDA DE CARGA MTX (6 PINES) | C67: No. 2 | D67: METTLER TOLEDO | E67: MTX | G67: #VALUE! | I67: SE-CABLE-MTX | K67: 44592 | O67: ='EQUIPO MARZO 2025 1'!AQ67 -> 0 | P67: =O67 -> 0 | Q67: =AK67 -> 0 | R67: =AL67 -> 0 | S67: =AM67 -> 0 | T67: =AN67 -> 0 | AJ67: ='EQUIPO ENERO 2025'!AP67 -> 0 | AK67: =P67-Z67+AE67+U67 -> 0 | AL67: =Q67-AA67+AF67+V67 -> 0 | AM67: =R67-AB67+AG67+W67 -> 0 | AN67: =S67-AC67+AH67+X67 -> 0 | AO67: =T67-AD67+AI67+Y67 -> 0 | AQ67: =AO67 -> 0
A68: =A67+1 -> 63 | B68: CABLE CELDA DE CARGA PDX (5 PINES) | C68: No. 2 | D68: METTLER TOLEDO | E68: PDX | G68: #VALUE! | I68: SE-CABLE-PDX | K68: 44592 | O68: ='EQUIPO MARZO 2025 1'!AQ68 -> 0 | P68: =O68 -> 0 | Q68: =AK68 -> 0 | R68: =AL68 -> 0 | S68: =AM68 -> 0 | T68: =AN68 -> 0 | AJ68: ='EQUIPO ENERO 2025'!AP68 -> 0 | AK68: =P68-Z68+AE68+U68 -> 0 | AL68: =Q68-AA68+AF68+V68 -> 0 | AM68: =R68-AB68+AG68+W68 -> 0 | AN68: =S68-AC68+AH68+X68 -> 0 | AO68: =T68-AD68+AI68+Y68 -> 0 | AQ68: =AO68 -> 0
A69: =A68+1 -> 64 | B69: CABLE PARA BATERIA DE INDICADOR DIGITAL MODELO SE-7517 ROJO Y NEGRO | C69: No.2 | E69: SE-7517BA | I69: SE-CAB-7517BA | J69: LOCOSC | K69: 45279 | M69: 481 | O69: ='EQUIPO MARZO 2025 1'!AQ69 -> 12 | P69: =O69 -> 12 | Q69: =AK69 -> 12 | R69: =AL69 -> 12 | S69: =AM69 -> 12 | T69: =AN69 -> 12 | AJ69: ='EQUIPO ENERO 2025'!AP69 -> 12 | AK69: =P69-Z69+AE69+U69 -> 12 | AL69: =Q69-AA69+AF69+V69 -> 12 | AM69: =R69-AB69+AG69+W69 -> 12 | AN69: =S69-AC69+AH69+X69 -> 12 | AO69: =T69-AD69+AI69+Y69 -> 12 | AQ69: =AO69 -> 12
A70: =A69+1 -> 65 | B70: CABLE PARA INDICADOR LP7581P CON CONECTOR (CABLE ROJO Y NEGRO) | C70: NO. 2 | D70: S/M | E70: S/M | F70: S/C | G70: #VALUE! | I70: SE-CABLE-LP7581P | J70: LOCOSC | K70: 45673 | L70: 240907-1 | M70: 130 | O70: ='EQUIPO MARZO 2025 1'!AQ70 -> 11 | P70: =O70 -> 11 | Q70: =AK70 -> 11 | R70: =AL70 -> 11 | S70: =AM70 -> 11 | T70: =AN70 -> 11 | AJ70: ='EQUIPO ENERO 2025'!AP70 -> 11 | AK70: =P70-Z70+AE70+U70 -> 11 | AL70: =Q70-AA70+AF70+V70 -> 11 | AM70: =R70-AB70+AG70+W70 -> 11 | AN70: =S70-AC70+AH70+X70 -> 11 | AO70: =T70-AD70+AI70+Y70 -> 11 | AQ70: =AO70 -> 11
A71: =A70+1 -> 66 | B71: CAJA PLASTICA IP 67 | C71: No. 2 | G71: #VALUE! | I71: SE-CAJ-IP67 | O71: ='EQUIPO MARZO 2025 1'!AQ71 -> 3 | P71: =O71 -> 3 | Q71: =AK71 -> 3 | R71: =AL71 -> 3 | S71: =AM71 -> 3 | T71: =AN71 -> 3 | AJ71: ='EQUIPO ENERO 2025'!AP71 -> 3 | AK71: =P71-Z71+AE71+U71 -> 3 | AL71: =Q71-AA71+AF71+V71 -> 3 | AM71: =R71-AB71+AG71+W71 -> 3 | AN71: =S71-AC71+AH71+X71 -> 3 | AO71: =T71-AD71+AI71+Y71 -> 3 | AQ71: =AO71 -> 3
A72: =A71+1 -> 67 | B72: CAJA SUMA | C72: No. 2 | D72: S/M | E72: SE-LP7312 | F72: 4 CANALES | G72: #VALUE! | H72: 1500 | I72: SE-CAJA-SUMA LP7312-A2-4 | J72: LOCOSC | K72: 45687 | L72: LP230224-1 | M72: 145 | N72: pegaso la caja fue reemplazada y completentada en el kit | O72: ='EQUIPO MARZO 2025 1'!AQ72 -> 6 | P72: =O72 -> 6 | Q72: =AK72 -> 5 | R72: =AL72 -> 5 | S72: =AM72 -> 5 | T72: =AN72 -> 5 | Z72: 1 | AJ72: ='EQUIPO ENERO 2025'!AP72 -> 6 | AK72: =P72-Z72+AE72+U72 -> 5 | AL72: =Q72-AA72+AF72+V72 -> 5 | AM72: =R72-AB72+AG72+W72 -> 5 | AN72: =S72-AC72+AH72+X72 -> 5 | AO72: =T72-AD72+AI72+Y72 -> 5 | AP72: 1 SOLO CAJA | AQ72: =AO72 -> 5 | AR72: 2835172828 | AS72: 378
A73: =A72+1 -> 68 | B73: CAJA SUMA 4 CANALES TOTAL COMP STOCK 1007 | C73: No. 2 | D73: TOTAL COMP | E73: S-45 1250 | I73: SE-CAJA-1250-5-SS | J73: TOTAL COMP | K73: 45062 | M73: 352 | O73: ='EQUIPO MARZO 2025 1'!AQ73 -> 0 | P73: =O73 -> 0 | Q73: =AK73 -> 0 | R73: =AL73 -> 0 | S73: =AM73 -> 0 | T73: =AN73 -> 0 | AJ73: ='EQUIPO ENERO 2025'!AP73 -> 0 | AK73: =P73-Z73+AE73+U73 -> 0 | AL73: =Q73-AA73+AF73+V73 -> 0 | AM73: =R73-AB73+AG73+W73 -> 0 | AN73: =S73-AC73+AH73+X73 -> 0 | AO73: =T73-AD73+AI73+Y73 -> 0 | AQ73: =AO73 -> 0
A74: =A73+1 -> 69 | B74: CAJA SUMA ACERO INOX 4 CANALES 50063-0066 TORNILLOS | C74: No. 2 | D74: BRECKNELL | E74: 50063-0066 TORNILLOS | G74: #VALUE! | H74: 5500 | I74: SE-CAJASUM-4C | J74: BRECKNELL | K74: 45391 | L74: 2187074-001 | M74: 55 | O74: ='EQUIPO MARZO 2025 1'!AQ74 -> 1 | P74: =O74 -> 1 | Q74: =AK74 -> 1 | R74: =AL74 -> 1 | S74: =AM74 -> 1 | T74: =AN74 -> 1 | AJ74: ='EQUIPO ENERO 2025'!AP74 -> 1 | AK74: =P74-Z74+AE74+U74 -> 1 | AL74: =Q74-AA74+AF74+V74 -> 1 | AM74: =R74-AB74+AG74+W74 -> 1 | AN74: =S74-AC74+AH74+X74 -> 1 | AO74: =T74-AD74+AI74+Y74 -> 1 | AQ74: =AO74 -> 1
